Workbook
Name PED_CUM_MES: #REF!
Name PED_CUM_MES: #REF!
Name PED_CUM_MES: #REF!
Name VTA_ACUM_MES: #REF!
Name VTA_ACUM_MES: #REF!
Name VTA_ACUM_MES: #REF!

Sheet BD
A1: REGIONAL | B1: PEDIDO TUTI | C1: FECHA Y HORA | D1: CLIENTE | E1: VENDEDOR | F1: ESTADO | G1: VALOR | H1: ZONA | I1: RUTA
A2: MEDELLIN | B2: 105780 | C2: 45961.559 | D2: EDELIO DE JESUS VELEZ CORTES | E2: DUBY YARLENY BEDOYA FLOREZ 102 | F2: Procesada | G2: 6554.64 | H2: 102 | I2: 1306
A3: MEDELLIN | B3: 105781 | C3: 45961.561 | D3: EDWIN ARLEY BUILES RUA | E3: GEORLAN GARCIA PANIAGUA 117 | F3: Procesada | G3: 10793.95 | H3: 117 | I3: 1398
A4: MEDELLIN | B4: 105782 | C4: 45961.564 | D4: ADRIAN ARCANGEL ARROYAVE MUNERA | E4: GEORLAN GARCIA PANIAGUA 117 | F4: Procesada | G4: 56613.32 | H4: 117 | I4: 1398
A5: CUCUTA | B5: 105783 | C5: 45961.565 | D5: REINALDO TRIANA MUÑOZ | E5: FREDY ESTEPA 409 CUCUTA | F5: Procesada | G5: 12145.39 | H5: 409 | I5: 1674
A6: CUCUTA | B6: 105784 | C6: 45961.567 | D6: ISMENIA SERRANO VERGEL | E6: ZULY RANGEL GARCIA 413 CUCUTA | F6: Procesada | G6: 32850.82 | H6: 413 | I6: 1684
A7: MEDELLIN | B7: 105785 | C7: 45961.57 | D7: NOVIELA DEL SOCORRO VELEZ CORTES | E7: DUBY YARLENY BEDOYA FLOREZ 102 | F7: Procesada | G7: 21109.55 | H7: 102 | I7: 1306
A8: MEDELLIN | B8: 105786 | C8: 45961.573 | D8: RAUL OROZCO OROZCO | E8: KATHERINE GAVIRIA MAZO 103 | F8: Procesada | G8: 23086 | H8: 103 | I8: 1309
A9: BARRANQUILLA | B9: 105787 | C9: 45961.576 | D9: ISABEL ANGARITA SUAREZ | E9: JESUS ENRIQUE GIRALDO SOTO 714 BARRANQUILLA | F9: Procesada | G9: 31932.92 | H9: 714 | I9: 1940
A10: MEDELLIN | B10: 105788 | C10: 45961.581 | D10: DARIO ELEXANDER ROLDAN ZAPATA | E10: ELIANA GOMEZ 107 | F10: Procesada | G10: 24652.28 | H10: 107 | I10: 1321
A11: BARRANQUILLA | B11: 105789 | C11: 45961.582 | D11: YULEIMI PATRICIA PEREZ CABARCAS | E11: ALVARO ENRIQUE CASTAÑEDA MANJARRES 715 BARRANQUILLA | F11: Procesada | G11: 49336.6 | H11: 715 | I11: 1945
A12: PEREIRA | B12: 105790 | C12: 45961.586 | D12: JAIME DE JESUS PEREZ CARDONA | E12: LEONARDO RIOS HENAO 612 | F12: Procesada | G12: 28907.64 | H12: 612 | I12: 1834
A13: MONTERIA | B13: 105791 | C13: 45961.586 | D13: RUBIA ESTELA GARCIA MACEA | E13: JOSE GREGORIO OSTEN MERCADO 509 | F13: Procesada | G13: 28349.8 | H13: 509 | I13: 1737
... A619: MONTERIA | B619: 106446 | C619: 45965.997 | D619: ADELA GONZALEZ LONDOÑO | E619: NELSON ENRIQUE LOPEZ GONZALEZ 510 | F619: Procesada | G619: 9024.38 | H619: 510 | I619: 1714
A620: CUCUTA | B620: 106447 | C620: 2025-11-05 12:12:50 | D620: LUZ STELLA URIBE ORTIZ | E620: FREDY ESTEPA 409 CUCUTA | F620: Procesada | G620: 20911.227 | H620: 409 | I620: 1675
A621: BARRANQUILLA | B621: 106448 | C621: 2025-11-05 12:25:33 | D621: YESIR CARRASCAL MONTEJO | E621: MARIELA ESTER DE LEON 720 BARRANQUILLA | F621: Procesada | G621: 31932.916 | H621: 720 | I621: 1982
A622: BARRANQUILLA | B622: 106449 | C622: 2025-11-05 12:35:29 | D622: JOBANY DE JESUS ROA MARTINEZ | E622: MARIELA ESTER DE LEON 720 BARRANQUILLA | F622: Procesada | G622: 16806.798 | H622: 720 | I622: 1982
A623: BARRANQUILLA | B623: 106450 | C623: 2025-11-05 13:04:05 | D623: WILDER MARTINEZ MARTINEZ | E623: MARIELA ESTER DE LEON 720 BARRANQUILLA | F623: Procesada | G623: 8067.2437 | H623: 720 | I623: 1982
A624: BARRANQUILLA | B624: 106451 | C624: 2025-11-05 13:17:51 | D624: ROBERTO ENRIQUE PACHECO BARROS | E624: JESUS ENRIQUE GIRALDO SOTO 714 BARRANQUILLA | F624: Procesada | G624: 31932.916 | H624: 714 | I624: 1942
A625: CUCUTA | B625: 106452 | C625: 2025-11-05 13:21:11 | D625: LEONILDE CARRILLO PARRA | E625: MAIRA TORRES 411 CUCUTA | F625: Procesada | G625: 12983.193 | H625: 411 | I625: 1678
A626: MEDELLIN | B626: 106453 | C626: 2025-11-05 13:27:57 | D626: ANDRES JULIAN IDARRAGA SALAZAR | E626: GEORLAN GARCIA PANIAGUA 117 | F626: Procesada | G626: 11543 | H626: 117 | I626: 1398
A627: CUCUTA | B627: 106454 | C627: 2025-11-05 13:29:16 | D627: MARIA JULIA ANGEL DIEZ | E627: FREDY ESTEPA 409 CUCUTA | F627: Procesada | G627: 8542.0168 | H627: 409 | I627: 1675
A628: MONTERIA | B628: 106455 | C628: 2025-11-05 13:31:08 | D628: SVETLANA MARIA GONZALEZ DIAZ | E628: JOSE GREGORIO OSTEN MERCADO 509 | F628: Procesada | G628: 128333.7 | H628: 509 | I628: 1737
A629: BARRANQUILLA | B629: 106456 | C629: 2025-11-05 13:33:06 | D629: YADIRA DURAN LOPEZ | E629: STHEFANY OJITO BARRANQUILLA 712 | F629: Procesada | G629: 41290.496 | H629: 712 | I629: 1934
A630: CUCUTA | B630: 106457 | C630: 2025-11-05 13:34:13 | D630: DORIS AMPARO BURITICA DAZA | E630: ZULY RANGEL GARCIA 413 CUCUTA | F630: Procesada | G630: 28541.824 | H630: 413 | I630: 1684
A631: MEDELLIN | B631: 106459 | C631: 2025-11-05 13:35:30 | D631: JOHAN ANDRES CEBALLOS | E631: ELIANA GOMEZ 107 | F631: Procesada | G631: 31008.361 | H631: 107 | I631: 1321
... A1143: MEDELLIN | B1143: 106998 | C1143: 2025-11-06 18:16:52 | D1143: FRANCISCO IVAN TORO CARMONA | E1143: SEBASTIAN DIAZ VELEZ 105 | F1143: Procesada | G1143: 4078.1513 | H1143: 105 | I1143: 1314
A1144: MEDELLIN | B1144: 106999 | C1144: 2025-11-06 18:20:58 | D1144: ANA MARIA ORTIZ VILLA | F1144: Procesada | G1144: 126161.72 | H1144: 114 | I1144: 1343
A1145: BOGOTA | B1145: 107000 | C1145: 2025-11-06 18:24:17 | D1145: JOHN RONALD CUELLAR CAMACHO | E1145: CARLOS EDUARDO ROMERO 934 | F1145: Procesada | G1145: 41698.16 | H1145: 934 | I1145: 2196
A1146: BOGOTA | B1146: 107001 | C1146: 2025-11-06 18:25:39 | D1146: JOSE ALEJANDRO GUERRERO AVILA | E1146: MARIBEL REDONDO 918 | F1146: Procesada | G1146: 115927.63 | H1146: 918 | I1146: 2130
A1147: BOGOTA | B1147: 107002 | C1147: 2025-11-06 18:25:44 | D1147: JOSE ADOLFO FANDIÑO DIAZ | E1147: MONICA RODRIGUEZ RONCANCIO 946 | F1147: Procesada | G1147: 19845 | H1147: 946 | I1147: 2237
A1148: MEDELLIN | B1148: 107003 | C1148: 2025-11-06 18:29:18 | D1148: ASTRIS ELENA ESTRADA SERNA | E1148: ANDRES GRACIANO SERNA 104 | F1148: Procesada | G1148: 55868.723 | H1148: 104 | I1148: 1310
A1149: BOGOTA | B1149: 107004 | C1149: 2025-11-06 18:30:09 | D1149: JOSE ARBEY RAMIREZ YEPES | E1149: LEONARDO MANCERA BOLAÑOS 926 | F1149: Procesada | G1149: 20381.58 | H1149: 926 | I1149: 2158
A1150: VALLEDUPAR | B1150: 107005 | C1150: 2025-11-06 18:32:02 | D1150: ANDRES MAURICIO ESTRADA LOPEZ | E1150: LILIANA BLANCO LOPEZ 705 VALLEDUPAR | F1150: Procesada | G1150: 39117.58 | H1150: 705 | I1150: 1914
A1151: BOGOTA | B1151: 107006 | C1151: 2025-11-06 18:32:47 | D1151: ELVA LUCERO NUÑEZ CORREA | E1151: LEONARDO MANCERA BOLAÑOS 926 | F1151: Procesada | G1151: 35394.723 | H1151: 926 | I1151: 2158
A1152: BOGOTA | B1152: 107007 | C1152: 2025-11-06 18:34:08 | D1152: LUIS FERNANDO GUTIERREZ ESCOBAR | E1152: WILLIAM ALBERTO VELASQUEZ BERNAL 920 | F1152: Procesada | G1152: 139080 | H1152: 920 | I1152: 2136
A1153: BOGOTA | B1153: 107008 | C1153: 2025-11-06 18:34:11 | D1153: CARLOS JULIO SUAREZ CELIS | E1153: LEONARDO MANCERA BOLAÑOS 926 | F1153: Procesada | G1153: 31932.84 | H1153: 926 | I1153: 2158
A1154: BOGOTA | B1154: 107009 | C1154: 2025-11-06 18:35:24 | D1154: MARIA GILMA ECHEVERRI CEBALLOS | E1154: LEONARDO MANCERA BOLAÑOS 926 | F1154: Procesada | G1154: 15504.176 | H1154: 926 | I1154: 2158
A1155: BOGOTA | B1155: 107010 | C1155: 2025-11-06 18:36:22 | D1155: MARIA BARBARA MORA VARGAS | E1155: LEONARDO MANCERA BOLAÑOS 926 | F1155: Procesada | G1155: 16806.798 | H1155: 926 | I1155: 2158
A1156: BOGOTA | B1156: 107011 | C1156: 2025-11-06 18:36:34 | D1156: MARTHA LUISA SALDAÑA NOVA | E1156: WILSON JAVIER MONTAÑEZ MARTINEZ 923 | F1156: Procesada | G1156: 16806.798 | H1156: 923 | I1156: 2149
... A2171: MEDELLIN | B2171: 108138 | C2171: 2025-11-11 17:12:00 | D2171: EDISON GOMEZ GOMEZ | E2171: ELIANA GOMEZ 107 | F2171: Procesada | G2171: 34149.714 | H2171: 107 | I2171: 1320
A2172: MEDELLIN | B2172: 108139 | C2172: 2025-11-11 17:13:55 | D2172: SANDRA PATRICIA VELA TORRIJOS | F2172: Procesada | G2172: 32570.218 | H2172: 102 | I2172: 1304
A2173: BOGOTA | B2173: 108140 | C2173: 2025-11-11 17:15:33 | D2173: MARISOL MURILLO MOSQUERA | E2173: SOL KATHERINE BERNAL MONTANO 907 | F2173: Procesada | G2173: 11543 | H2173: 907 | I2173: 2100
A2174: MEDELLIN | B2174: 108141 | C2174: 2025-11-11 17:16:21 | D2174: JESUS IVAN MONSALVE MONSALVE | E2174: ELIANA GOMEZ 107 | F2174: Procesada | G2174: 14190.059 | H2174: 107 | I2174: 1320
A2175: CALI | B2175: 108142 | C2175: 2025-11-11 17:17:26 | D2175: JOSE RAMON MUNOZ | E2175: GERALDINE MEZA VALENCIA 620 | F2175: Procesada | G2175: 36223.143 | H2175: 620 | I2175: 1877
A2176: MEDELLIN | B2176: 108144 | C2176: 2025-11-11 17:18:19 | D2176: JESSICA BRAN RAMIREZ | E2176: MARIA ELENA JARAMILLO GALEANO 114 | F2176: Procesada | G2176: 10944.076 | H2176: 114 | I2176: 1343
A2177: MEDELLIN | B2177: 108145 | C2177: 2025-11-11 17:18:55 | D2177: SILVIA MARCELA CARDONA ARANGO | E2177: ELIANA GOMEZ 107 | F2177: Procesada | G2177: 11543 | H2177: 107 | I2177: 1320
A2178: BARRANQUILLA | B2178: 108146 | C2178: 2025-11-11 17:20:04 | D2178: JOHN JAIRO CORTES ZULETA | E2178: MARIELA ESTER DE LEON 720 BARRANQUILLA | F2178: Procesada | G2178: 23870.42 | H2178: 720 | I2178: 1980
A2179: VILLAVICENCIO | B2179: 108147 | C2179: 2025-11-11 17:20:42 | D2179: ELIZABETH VARGAS SUAREZ | E2179: JHONTAN MENDOZA 906 | F2179: Procesada | G2179: 122622.28 | H2179: 906 | I2179: 2913
A2180: BOGOTA | B2180: 108148 | C2180: 2025-11-11 17:21:30 | D2180: DIANA MILENA JIMENEZ RUIZ | E2180: SOL KATHERINE BERNAL MONTANO 907 | F2180: Procesada | G2180: 11543 | H2180: 907 | I2180: 2100
A2181: CUCUTA | B2181: 108149 | C2181: 2025-11-11 17:23:04 | D2181: MAURICIO ORTIZ | E2181: FREDY ESTEPA 409 CUCUTA | F2181: Procesada | G2181: 11415.966 | H2181: 409 | I2181: 1673
A2182: BOGOTA | B2182: 108150 | C2182: 2025-11-11 17:25:26 | D2182: CAYETANO GUERRERO FERNANDEZ | E2182: MONICA RODRIGUEZ RONCANCIO 946 | F2182: Procesada | G2182: 23668 | H2182: 946 | I2182: 2235
A2183: BARRANQUILLA | B2183: 108151 | C2183: 2025-11-11 17:26:10 | D2183: ELIANA ARIAS DIAZ | E2183: YOANY SARMIENTO PEREZ 713 BARRANQUILLA | F2183: Procesada | G2183: 20085.017 | H2183: 713 | I2183: 1938
A2184: MEDELLIN | B2184: 108152 | C2184: 2025-11-11 17:28:38 | D2184: RESFA NELLY ACEVEDO VELEZ | E2184: EDISON ALBERTO SALAZAR YEPES 116 | F2184: Procesada | G2184: 24590.924 | H2184: 116 | I2184: 1347
... A2798: CUCUTA | B2798: 108867 | C2798: 2025-11-13 17:12:15 | D2798: DELCY STEFANNY GOMEZ SIERRA | E2798: FREDY ESTEPA 409 CUCUTA | F2798: Procesada | G2798: 29700 | H2798: 409 | I2798: 1673
A2799: BUCARAMANGA | B2799: 108869 | C2799: 2025-11-13 17:12:41 | D2799: ISRAEL PLATA RUIZ | F2799: Procesada | G2799: 40714.294 | H2799: 405 | I2799: 1642
A2800: BOGOTA | B2800: 108870 | C2800: 2025-11-13 17:13:39 | D2800: ERNESTO MONTOYA CARDENAS | E2800: ANGIE JOHANA BEDOYA HERRENO 908 | F2800: Procesada | G2800: 23109.202 | H2800: 908 | I2800: 2103
A2801: MEDELLIN | B2801: 108871 | C2801: 2025-11-13 17:15:53 | D2801: ANA YOLANDA PULGARIN VALLE | E2801: MARIA ELENA JARAMILLO GALEANO 114 | F2801: Procesada | G2801: 61781.849 | H2801: 114 | I2801: 1343
A2802: MEDELLIN | B2802: 108872 | C2802: 2025-11-13 17:16:49 | D2802: LORENA DEL SOCORRO GOMEZ RAMIREZ | E2802: INGRID RESTREPO 115 | F2802: Procesada | G2802: 72481.126 | H2802: 115 | I2802: 1340
A2803: BOGOTA | B2803: 108873 | C2803: 2025-11-13 17:17:51 | D2803: VALENTINA CORDOBA MADARIAGA | E2803: CRISTINA QUINTERO RUDAS 945 | F2803: Procesada | G2803: 52865.303 | H2803: 945 | I2803: 2232
A2804: BOGOTA | B2804: 108874 | C2804: 2025-11-13 17:20:32 | D2804: MARYURY RAMIREZ | E2804: SANDRA PATRICIA ORTIZ ROMERO 919 | F2804: Procesada | G2804: 21176.403 | H2804: 919 | I2804: 2131
A2805: VILLAVICENCIO | B2805: 108876 | C2805: 2025-11-13 17:22:19 | D2805: LUIS JACOBO RUEDA | E2805: JHONTAN MENDOZA 906 | F2805: Procesada | G2805: 20866.798 | H2805: 906 | I2805: 2913
A2806: BOGOTA | B2806: 108877 | C2806: 2025-11-13 17:25:00 | D2806: BLANCA ELVIRA COLORADO DE MENDEZ | E2806: LEYDY YURLEY MUNEVAR ESPITIA 921 | F2806: Procesada | G2806: 34770 | H2806: 921 | I2806: 2137
A2807: BOGOTA | B2807: 108878 | C2807: 2025-11-13 17:25:02 | D2807: HOOD S A S | E2807: SANDRA PATRICIA ORTIZ ROMERO 919 | F2807: Procesada | G2807: 37815.101 | H2807: 919 | I2807: 2131
A2808: BOGOTA | B2808: 108880 | C2808: 2025-11-13 17:27:01 | D2808: DORALBA AVILA RINCON | E2808: ANGIE JOHANA BEDOYA HERRENO 908 | F2808: Procesada | G2808: 37815.101 | H2808: 908 | I2808: 2103
A2809: MEDELLIN | B2809: 108882 | C2809: 2025-11-13 17:27:20 | D2809: JUAN CAMILO ECHEVERRY ACEVEDO | E2809: DUBY YARLENY BEDOYA FLOREZ 102 | F2809: Procesada | G2809: 27162.395 | H2809: 102 | I2809: 1305
A2810: MEDELLIN | B2810: 108883 | C2810: 2025-11-13 17:37:18 | D2810: JOSE HERIBERTO MARIN BUITRAGO | E2810: MARIA ELENA JARAMILLO GALEANO 114 | F2810: Procesada | G2810: 23925.63 | H2810: 114 | I2810: 1343
A2811: MEDELLIN | B2811: 108884 | C2811: 2025-11-13 17:42:59 | D2811: MARIA OFIR HOLGUIN | E2811: MIGUEL ANGEL HIDALGO SANTOS 113 | F2811: Procesada | G2811: 29243.756 | H2811: 113 | I2811: 1339
... A3092: CUCUTA | B3092: 108867 | C3092: 2025-11-13 17:12:15 | D3092: DELCY STEFANNY GOMEZ SIERRA | E3092: FREDY ESTEPA 409 CUCUTA | F3092: Procesada | G3092: 29700 | H3092: 409 | I3092: 1673
A3093: BUCARAMANGA | B3093: 108869 | C3093: 2025-11-13 17:12:41 | D3093: ISRAEL PLATA RUIZ | F3093: Procesada | G3093: 40714.294 | H3093: 405 | I3093: 1642
A3094: BOGOTA | B3094: 108870 | C3094: 2025-11-13 17:13:39 | D3094: ERNESTO MONTOYA CARDENAS | E3094: ANGIE JOHANA BEDOYA HERRENO 908 | F3094: Procesada | G3094: 23109.202 | H3094: 908 | I3094: 2103
A3095: MEDELLIN | B3095: 108871 | C3095: 2025-11-13 17:15:53 | D3095: ANA YOLANDA PULGARIN VALLE | E3095: MARIA ELENA JARAMILLO GALEANO 114 | F3095: Procesada | G3095: 61781.849 | H3095: 114 | I3095: 1343
A3096: MEDELLIN | B3096: 108872 | C3096: 2025-11-13 17:16:49 | D3096: LORENA DEL SOCORRO GOMEZ RAMIREZ | E3096: INGRID RESTREPO 115 | F3096: Procesada | G3096: 72481.126 | H3096: 115 | I3096: 1340
A3097: BOGOTA | B3097: 108873 | C3097: 2025-11-13 17:17:51 | D3097: VALENTINA CORDOBA MADARIAGA | E3097: CRISTINA QUINTERO RUDAS 945 | F3097: Procesada | G3097: 52865.303 | H3097: 945 | I3097: 2232
A3098: BOGOTA | B3098: 108874 | C3098: 2025-11-13 17:20:32 | D3098: MARYURY RAMIREZ | E3098: SANDRA PATRICIA ORTIZ ROMERO 919 | F3098: Procesada | G3098: 21176.403 | H3098: 919 | I3098: 2131
A3099: VILLAVICENCIO | B3099: 108876 | C3099: 2025-11-13 17:22:19 | D3099: LUIS JACOBO RUEDA | E3099: JHONTAN MENDOZA 906 | F3099: Procesada | G3099: 20866.798 | H3099: 906 | I3099: 2913
A3100: BOGOTA | B3100: 108877 | C3100: 2025-11-13 17:25:00 | D3100: BLANCA ELVIRA COLORADO DE MENDEZ | E3100: LEYDY YURLEY MUNEVAR ESPITIA 921 | F3100: Procesada | G3100: 34770 | H3100: 921 | I3100: 2137
A3101: BOGOTA | B3101: 108878 | C3101: 2025-11-13 17:25:02 | D3101: HOOD S A S | E3101: SANDRA PATRICIA ORTIZ ROMERO 919 | F3101: Procesada | G3101: 37815.101 | H3101: 919 | I3101: 2131
A3102: BOGOTA | B3102: 108880 | C3102: 2025-11-13 17:27:01 | D3102: DORALBA AVILA RINCON | E3102: ANGIE JOHANA BEDOYA HERRENO 908 | F3102: Procesada | G3102: 37815.101 | H3102: 908 | I3102: 2103
A3103: MEDELLIN | B3103: 108882 | C3103: 2025-11-13 17:27:20 | D3103: JUAN CAMILO ECHEVERRY ACEVEDO | E3103: DUBY YARLENY BEDOYA FLOREZ 102 | F3103: Procesada | G3103: 27162.395 | H3103: 102 | I3103: 1305
A3104: MEDELLIN | B3104: 108883 | C3104: 2025-11-13 17:37:18 | D3104: JOSE HERIBERTO MARIN BUITRAGO | E3104: MARIA ELENA JARAMILLO GALEANO 114 | F3104: Procesada | G3104: 23925.63 | H3104: 114 | I3104: 1343
A3105: MEDELLIN | B3105: 108884 | C3105: 2025-11-13 17:42:59 | D3105: MARIA OFIR HOLGUIN | E3105: MIGUEL ANGEL HIDALGO SANTOS 113 | F3105: Procesada | G3105: 29243.756 | H3105: 113 | I3105: 1339
... A3899: MEDELLIN | B3899: 109797 | C3899: 2025-11-19 16:09:45 | D3899: YESICA TATIANA GIRALDO ZULUAGA | E3899: KATHERINE GAVIRIA MAZO 103 | F3899: Procesada | G3899: 57648.697 | H3899: 103 | I3899: 1308
A3900: BUCARAMANGA | B3900: 109798 | C3900: 2025-11-19 16:09:49 | D3900: ISRAEL PLATA RUIZ | F3900: Procesada | G3900: 52289.899 | H3900: 405 | I3900: 1642
A3901: BOGOTA | B3901: 109799 | C3901: 2025-11-19 16:13:44 | D3901: DIANA CUELLAR | E3901: LEYDY YURLEY MUNEVAR ESPITIA 921 | F3901: Procesada | G3901: 12628.151 | H3901: 921 | I3901: 2138
A3902: BOGOTA | B3902: 109800 | C3902: 2025-11-19 16:13:59 | D3902: JOSE ROBINSON HURTADO PARDO | E3902: MARIBEL REDONDO 918 | F3902: Procesada | G3902: 167845.8 | H3902: 918 | I3902: 2129
A3903: BUCARAMANGA | B3903: 109801 | C3903: 2025-11-19 16:14:48 | D3903: ISRAEL PLATA RUIZ | F3903: Procesada | G3903: 56663.412 | H3903: 405 | I3903: 1642
A3904: BOGOTA | B3904: 109802 | C3904: 2025-11-19 16:16:17 | D3904: YAMID AMARU CALDERON QUINTERO | E3904: YULIETH HERNANDEZ | F3904: Procesada | G3904: 29553.798 | H3904: 936 | I3904: 2201
A3905: BOGOTA | B3905: 109803 | C3905: 2025-11-19 16:17:03 | D3905: EVEDMELEC LATORRE ROMERO | E3905: SOL KATHERINE BERNAL MONTANO 907 | F3905: Procesada | G3905: 10588.202 | H3905: 907 | I3905: 2101
A3906: MEDELLIN | B3906: 109805 | C3906: 2025-11-19 16:18:11 | D3906: RUBEN DARIO BOTERO ZULUAGA | E3906: KATHERINE GAVIRIA MAZO 103 | F3906: Procesada | G3906: 35211 | H3906: 103 | I3906: 1308
A3907: BOGOTA | B3907: 109806 | C3907: 2025-11-19 16:19:31 | D3907: JAQUELINE RAMIREZ GOMEZ | E3907: LEYDY YURLEY MUNEVAR ESPITIA 921 | F3907: Procesada | G3907: 59510.924 | H3907: 921 | I3907: 2138
A3908: BOGOTA | B3908: 109807 | C3908: 2025-11-19 16:24:14 | D3908: LUIS ARMANDO GUASCA MORALES | E3908: MONICA RODRIGUEZ RONCANCIO 946 | F3908: Procesada | G3908: 11147.748 | H3908: 946 | I3908: 2236
A3909: CUCUTA | B3909: 109808 | C3909: 2025-11-19 16:24:21 | D3909: BERTHA CECILIA REYES VARGAS | E3909: ZULY RANGEL GARCIA 413 CUCUTA | F3909: Procesada | G3909: 19411.782 | H3909: 413 | I3909: 1683
A3910: MONTERIA | B3910: 109809 | C3910: 2025-11-19 16:24:36 | D3910: LIDA YANETH CARVAJAL FERNANDEZ | E3910: JOSE GREGORIO OSTEN MERCADO 509 | F3910: Procesada | G3910: 113678.28 | H3910: 509 | I3910: 1736
A3911: VILLAVICENCIO | B3911: 109810 | C3911: 2025-11-19 16:26:16 | D3911: ANGELICA MARIA HENAO MARTINEZ | E3911: JHONTAN MENDOZA 906 | F3911: Procesada | G3911: 61630.588 | H3911: 906 | I3911: 2914
A3912: BOGOTA | B3912: 109811 | C3912: 2025-11-19 16:28:03 | D3912: CARMEN ROSA MALAMBO OSORIO | E3912: NELLY MARTINEZ FLEREZ 935 | F3912: Procesada | G3912: 48724.832 | H3912: 935 | I3912: 2198
A3913: MEDELLIN | B3913: 109812 | C3913: 2025-11-19 16:32:52 | D3913: LUIS CARLOS MARIN CARDONA | E3913: ANDRES GRACIANO SERNA 104 | F3913: Procesada | G3913: 44940 | H3913: 104 | I3913: 1312
A3914: MONTERIA | B3914: 109813 | C3914: 2025-11-19 16:33:12 | D3914: HERNAN ANTONIO MENDOZA MANCHEGO | E3914: JOSE GREGORIO OSTEN MERCADO 509 | F3914: Procesada | G3914: 42294.244 | H3914: 509 | I3914: 1736
A3915: MONTERIA | B3915: 109814 | C3915: 2025-11-19 16:33:58 | D3915: JONATHAN MORA MARTINEZ | E3915: NELSON ENRIQUE LOPEZ GONZALEZ 510 | F3915: Procesada | G3915: 611934.73 | H3915: 510 | I3915: 1731
... A4481: MEDELLIN | B4481: 110479 | C4481: 2025-11-20 22:37:38 | D4481: SEBASTIAN RUIZ PELAEZ | E4481: INES LILIANA PIEDRAHITA MESA 111 | F4481: Procesada | G4481: 38207.723 | H4481: 111 | I4481: 1331

Sheet BD VENTAS TERCEROS
A1: Fecha | B1: Factura | C1: Número de producto | D1: ProductName | E1: Concat Referencia | F1: Cantidad | G1: Precio unitario | H1: LineTotalDiscountAmount | I1: Importe | J1: Almacén | K1: Und Negocio | L1: Centro de Costos | M1: Nombre CC | N1: Regional | O1: Tipo Producto | P1: Semana | Q1: Ruta | R1: Zona | S1: Dia | T1: Referencia | U1: Cant Multiplicar | V1: Cantidad Real | W1: Canal | X1: Cliente | Y1: Tipo de Venta | Z1: Documento del Cliente | AA1: Cedula Vendedor | AB1: Nombre de Entrega
A2: 45965 | B2: HHBQ000722628 | C2: YACAN50 | D2: CANDADO 50 MM | E2: YACAN50 - CANDADO 50 MM | F2: 2 | G2: 4327.73 | H2: 0 | I2: 8655.46 | J2: VLL04 | K2: 1 | L2: 213 | M2: Tuti Valledupar | N2: ZONA NORTE | O2: TERCEROS | P2: 2025 SEM 45 | Q2: 1917 | R2: 706 | S2: martes | T2: YASS | U2: 1 | V2: 2 | W2: TAT | X2: ISRAELA MATILDE AMAYA IGUARAN | Y2: Preventa | Z2: 40791787 | AA2: 49794720 | AB2: DOÑA MATI
A3: 45965 | B3: HHMO000623487 | C3: LYLIMPLAV200DX1 | D3: LIMPIAYA LIMPIADOR LAVANDA 200 ML X1 | E3: LYLIMPLAV200DX1 - LIMPIAYA LIMPIADOR LAVANDA 200 ML X1 | F3: 6 | G3: 1120 | H3: 0 | I3: 6720 | J3: MT11 | K3: 1 | L3: 156 | M3: TUTI Monteria | N3: ZONA CENTRO | O3: TERCEROS | P3: 2025 SEM 45 | Q3: 1714 | R3: 510 | S3: martes | T3: ETERNA | U3: 1 | V3: 6 | W3: TAT | X3: SAMIR DAVID ARRIETA HERNANDEZ | Y3: Preventa | Z3: 1002997934 | AA3: 1067887069 | AB3: TIENDA LA COLMENA
A4: 45965 | B4: HHME001459620 | C4: PBDESCOJINX18 | D4: DES. AFM DPL ORIG 12G X18 | E4: PBDESCOJINX18 - DES. AFM DPL ORIG 12G X18 | F4: 2 | G4: 11900 | H4: 714 | I4: 23086 | J4: MD06 | K4: 1 | L4: 125 | M4: TUTI Medellin | N4: ZONA CENTRO | O4: TERCEROS | P4: 2025 SEM 45 | Q4: 1398 | R4: 117 | S4: martes | T4: PREBEL | U4: 1 | V4: 2 | W4: TAT | X4: ADRIAN ARCANGEL ARROYAVE MUNERA | Y4: Preventa | Z4: 8156669 | AA4: 8432406 | AB4: LA VENTANITA
A5: 45965 | B5: HHME001459620 | C5: LYESPOOROX12 | D5: LIMPIAYA ESPONJA ORO/PLATA X12 | E5: LYESPOOROX12 - LIMPIAYA ESPONJA ORO/PLATA X12 | F5: 2 | G5: 8991.6 | H5: 899.16 | I5: 17084.04 | J5: MD06 | K5: 1 | L5: 125 | M5: TUTI Medellin | N5: ZONA CENTRO | O5: TERCEROS | P5: 2025 SEM 45 | Q5: 1398 | R5: 117 | S5: martes | T5: ETERNA | U5: 1 | V5: 2 | W5: TAT | X5: ADRIAN ARCANGEL ARROYAVE MUNERA | Y5: Preventa | Z5: 8156669 | AA5: 8432406 | AB5: LA VENTANITA
A6: 45965 | B6: HHME001459620 | C6: YAPANIAZU | D6: PAÑITOS HUMEDOS DAMPY X 20 AZUL | E6: YAPANIAZU - PAÑITOS HUMEDOS DAMPY X 20 AZUL | F6: 5 | G6: 1344.54 | H6: 0 | I6: 6722.7 | J6: MD06 | K6: 1 | L6: 125 | M6: TUTI Medellin | N6: ZONA CENTRO | O6: TERCEROS | P6: 2025 SEM 45 | Q6: 1398 | R6: 117 | S6: martes | T6: YASS | U6: 1 | V6: 5 | W6: TAT | X6: ADRIAN ARCANGEL ARROYAVE MUNERA | Y6: Preventa | Z6: 8156669 | AA6: 8432406 | AB6: LA VENTANITA
A7: 45965 | B7: HHME001459620 | C7: YAPADAM150 | D7: PAÑITOS HUMEDOS DAMPY X 150 UND AZUL | E7: YAPADAM150 - PAÑITOS HUMEDOS DAMPY X 150 UND AZUL | F7: 2 | G7: 6422.4 | H7: 0 | I7: 12844.8 | J7: MD06 | K7: 1 | L7: 125 | M7: TUTI Medellin | N7: ZONA CENTRO | O7: TERCEROS | P7: 2025 SEM 45 | Q7: 1398 | R7: 117 | S7: martes | T7: YASS | U7: 1 | V7: 2 | W7: TAT | X7: ADRIAN ARCANGEL ARROYAVE MUNERA | Y7: Preventa | Z7: 8156669 | AA7: 8432406 | AB7: LA VENTANITA
A8: 45965 | B8: HHBO001170394 | C8: LYLOZA700DX1 | D8: LIMPIAYA LAVA LOZA DOYPACK 700 ML X1 | E8: LYLOZA700DX1 - LIMPIAYA LAVA LOZA DOYPACK 700 ML X1 | F8: 1 | G8: 3562.19 | H8: 0 | I8: 3562.19 | J8: BG13 | K8: 1 | L8: 126 | M8: TUTI Bogota | N8: ZONA BOGOTA | O8: TERCEROS | P8: 2025 SEM 45 | Q8: 2209 | R8: 938 | S8: martes | T8: ETERNA | U8: 1 | V8: 1 | W8: TAT | X8: SIERVO ALONSO PEREZ RODRIGUEZ | Y8: Preventa | Z8: 1074415224 | AA8: 1016001588 | AB8: PAPELERIA BOTICA DE EMANUEL
A9: 45965 | B9: HHBO001170394 | C9: LYDETE1800DX1 | D9: DETERGENTE ETERNA DOYPACK 1800 ML X1 | E9: LYDETE1800DX1 - DETERGENTE ETERNA DOYPACK 1800 ML X1 | F9: 1 | G9: 12000 | H9: 0 | I9: 12000 | J9: BG13 | K9: 1 | L9: 126 | M9: TUTI Bogota | N9: ZONA BOGOTA | O9: TERCEROS | P9: 2025 SEM 45 | Q9: 2209 | R9: 938 | S9: martes | T9: ETERNA | U9: 1 | V9: 1 | W9: TAT | X9: SIERVO ALONSO PEREZ RODRIGUEZ | Y9: Preventa | Z9: 1074415224 | AA9: 1016001588 | AB9: PAPELERIA BOTICA DE EMANUEL
A10: 45965 | B10: HHME001459642 | C10: YAVABY20GR | D10: VASELINA BABY, 20 GRAMOS, MARCA JUHNIOS | E10: YAVABY20GR - VASELINA BABY, 20 GRAMOS, MARCA JUHNIOS | F10: 6 | G10: 1444 | H10: 0 | I10: 8664 | J10: MD02 | K10: 1 | L10: 125 | M10: TUTI Medellin | N10: ZONA CENTRO | O10: TERCEROS | P10: 2025 SEM 45 | Q10: 1345 | R10: 116 | S10: martes | T10: YASS | U10: 1 | V10: 6 | W10: TAT | X10: LUIS ALFONSO ZAPATA TAPIAS | Y10: Preventa | Z10: 71700770 | AA10: 71381318 | AB10: LA TIENDA DE LUCHO
A11: 45965 | B11: HHME001459689 | C11: DRDESOPIES | D11: DESODORANTE PARA PIES | E11: DRDESOPIES - DESODORANTE PARA PIES | F11: 1 | G11: 9636 | H11: 0 | I11: 9636 | J11: MD30 | K11: 1 | L11: 1 | M11: MEDELLIN | N11: ZONA CENTRO | O11: TERCEROS | P11: 2025 SEM 45 | Q11: 1338 | R11: 115 | S11: martes | T11: DROMATIC | U11: 1 | V11: 1 | W11: TAT | X11: MARILENI VELASQUEZ PEREZ | Y11: Preventa | Z11: 44007369 | AA11: 1036639459 | AB11: GRANERO EL VECINO
A12: 45965 | B12: HHBQ000722645 | C12: YACAN50 | D12: CANDADO 50 MM | E12: YACAN50 - CANDADO 50 MM | F12: 2 | G12: 4327.73 | H12: 0 | I12: 8655.46 | J12: VLL04 | K12: 1 | L12: 213 | M12: Tuti Valledupar | N12: ZONA NORTE | O12: TERCEROS | P12: 2025 SEM 45 | Q12: 1916 | R12: 706 | S12: martes | T12: YASS | U12: 1 | V12: 2 | W12: TAT | X12: ANA EDILZA SANCHEZ PEREZ | Y12: Preventa | Z12: 60330338 | AA12: 49794720 | AB12: PROVISIONES BRENDA
A13: 45965 | B13: HHBQ000722645 | C13: YACAN38 | D13: CANDADO 38 MM | E13: YACAN38 - CANDADO 38 MM | F13: 2 | G13: 2668.75 | H13: 0 | I13: 5337.5 | J13: VLL04 | K13: 1 | L13: 213 | M13: Tuti Valledupar | N13: ZONA NORTE | O13: TERCEROS | P13: 2025 SEM 45 | Q13: 1916 | R13: 706 | S13: martes | T13: YASS | U13: 1 | V13: 2 | W13: TAT | X13: ANA EDILZA SANCHEZ PEREZ | Y13: Preventa | Z13: 60330338 | AA13: 49794720 | AB13: PROVISIONES BRENDA
... A83: 45965 | B83: HHBO001170461 | C83: YAGOM90 | D83: GOMINA N17 EN SOBRE 90G | E83: YAGOM90 - GOMINA N17 EN SOBRE 90G | F83: 1 | G83: 1092.44 | H83: 0 | I83: 1092.44 | J83: BG22 | K83: 1 | L83: 126 | M83: TUTI Bogota | N83: ZONA BOGOTA | O83: TERCEROS | P83: 2025 SEM 45 | Q83: 2130 | R83: 918 | S83: martes | T83: YASS | U83: 1 | V83: 1 | W83: TAT | X83: ANGELA CRUZ CAMACHO | Y83: Preventa | Z83: 53074221 | AA83: 22639797 | AB83: MINIMARKET PLUS
A84: 45965 | B84: HHME001459766 | C84: YALAPIZAMAX12 | D84: LAPIZ ESCOLAR AMARILLO X12 | E84: YALAPIZAMAX12 - LAPIZ ESCOLAR AMARILLO X12 | F84: 1 | G84: 4853 | H84: 0 | I84: 4853 | J84: MD01 | K84: 1 | L84: 125 | M84: TUTI Medellin | N84: ZONA CENTRO | O84: TERCEROS | P84: 2025 SEM 45 | Q84: 1342 | R84: 114 | S84: martes | T84: 0 | U84: 1 | V84: 1 | W84: TAT | X84: MARIA ESTELA CIRO CASTAÑO | Y84: Preventa | Z84: 43069565 | AA84: 1039023085 | AB84: LA MANO DE DIOS
A85: 45965 | B85: HHME001459766 | C85: YALAPIROX12 | D85: LAPIZ ROJO X12 UND | E85: YALAPIROX12 - LAPIZ ROJO X12 UND | F85: 1 | G85: 4882 | H85: 0 | I85: 4882 | J85: MD01 | K85: 1 | L85: 125 | M85: TUTI Medellin | N85: ZONA CENTRO | O85: TERCEROS | P85: 2025 SEM 45 | Q85: 1342 | R85: 114 | S85: martes | T85: YASS | U85: 1 | V85: 1 | W85: TAT | X85: MARIA ESTELA CIRO CASTAÑO | Y85: Preventa | Z85: 43069565 | AA85: 1039023085 | AB85: LA MANO DE DIOS
A86: 45965 | B86: HHCA000425934 | C86: YACONDSEX | D86: CONDONES X3 UNIDADES ECONOMICO | E86: YACONDSEX - CONDONES X3 UNIDADES ECONOMICO | F86: 20 | G86: 866.2 | H86: 0 | I86: 17324 | J86: CL07 | K86: 1 | L86: 171 | M86: TUTI Cali | N86: ZONA SUR | O86: TERCEROS | P86: 2025 SEM 45 | Q86: 1878 | R86: 620 | S86: martes | T86: YASS | U86: 1 | V86: 20 | W86: TAT | X86: YORMAN SANTIAGO LOPEZ CARDONA | Y86: Preventa | Z86: 1108252886 | AA86: 1143845966 | AB86: SUPERMERCADO 4 ESQUINAS
A87: 45965 | B87: HHCA000425934 | C87: YASEDA20 | D87: SEDA DENTAL CON CERA 20 MT | E87: YASEDA20 - SEDA DENTAL CON CERA 20 MT | F87: 20 | G87: 1092.44 | H87: 0 | I87: 21848.8 | J87: CL07 | K87: 1 | L87: 171 | M87: TUTI Cali | N87: ZONA SUR | O87: TERCEROS | P87: 2025 SEM 45 | Q87: 1878 | R87: 620 | S87: martes | T87: YASS | U87: 1 | V87: 20 | W87: TAT | X87: YORMAN SANTIAGO LOPEZ CARDONA | Y87: Preventa | Z87: 1108252886 | AA87: 1143845966 | AB87: SUPERMERCADO 4 ESQUINAS
A88: 45965 | B88: HHME001459853 | C88: PDELLAECONX10 | D88: ELLAS ECONOMICA X 10 | E88: PDELLAECONX10 - ELLAS ECONOMICA X 10 | F88: 5 | G88: 2544 | H88: 1272 | I88: 11448 | J88: TT02 | K88: 1 | L88: 125 | M88: TUTI Medellin | N88: ZONA CENTRO | O88: TERCEROS | P88: 2025 SEM 45 | Q88: 1321 | R88: 107 | S88: martes | T88: PRODUSA | U88: 1 | V88: 5 | W88: TAT | X88: JAVIER LEON ARISTIZBAL HOYOS | Y88: Preventa | Z88: 70383361 | AA88: 1037949442 | AB88: MI TIENDITA
A89: 45965 | B89: HHME001459853 | C89: PDTOAVEN60X8 | D89: VENUS DELGADA PACA 60 X 8 | E89: PDTOAVEN60X8 - VENUS DELGADA PACA 60 X 8 | F89: 5 | G89: 1718 | H89: 859 | I89: 7731 | J89: TT02 | K89: 1 | L89: 125 | M89: TUTI Medellin | N89: ZONA CENTRO | O89: TERCEROS | P89: 2025 SEM 45 | Q89: 1321 | R89: 107 | S89: martes | T89: PRODUSA | U89: 1 | V89: 5 | W89: TAT | X89: JAVIER LEON ARISTIZBAL HOYOS | Y89: Preventa | Z89: 70383361 | AA89: 1037949442 | AB89: MI TIENDITA
A90: 45965 | B90: HHME001459853 | C90: KNLIMTEN | D90: LIMPIADOR DE TENNIS KNIGHT | E90: KNLIMTEN - LIMPIADOR DE TENNIS KNIGHT | F90: 1 | G90: 6350 | H90: 635 | I90: 5715 | J90: TT02 | K90: 1 | L90: 125 | M90: TUTI Medellin | N90: ZONA CENTRO | O90: TERCEROS | P90: 2025 SEM 45 | Q90: 1321 | R90: 107 | S90: martes | T90: KNIGHT | U90: 1 | V90: 1 | W90: TAT | X90: JAVIER LEON ARISTIZBAL HOYOS | Y90: Preventa | Z90: 70383361 | AA90: 1037949442 | AB90: MI TIENDITA
A91: 45965 | B91: HHME001459853 | C91: YAGOM90 | D91: GOMINA N17 EN SOBRE 90G | E91: YAGOM90 - GOMINA N17 EN SOBRE 90G | F91: 3 | G91: 1092.44 | H91: 0 | I91: 3277.32 | J91: TT02 | K91: 1 | L91: 125 | M91: TUTI Medellin | N91: ZONA CENTRO | O91: TERCEROS | P91: 2025 SEM 45 | Q91: 1321 | R91: 107 | S91: martes | T91: YASS | U91: 1 | V91: 3 | W91: TAT | X91: JAVIER LEON ARISTIZBAL HOYOS | Y91: Preventa | Z91: 70383361 | AA91: 1037949442 | AB91: MI TIENDITA
A92: 45965 | B92: HHBO001170571 | C92: YACAN63 | D92: CANDADO 63 MM | E92: YACAN63 - CANDADO 63 MM | F92: 1 | G92: 5940 | H92: 0 | I92: 5940 | J92: BG13 | K92: 1 | L92: 2 | M92: CIUDAD BOGOTA | N92: ZONA BOGOTA | O92: TERCEROS | P92: 2025 SEM 45 | Q92: 2234 | R92: 945 | S92: martes | T92: YASS | U92: 1 | V92: 1 | W92: TAT | X92: DIANA CATALINA CORREDOR PRIETO | Y92: Preventa | Z92: 1012387423 | AA92: 52460170 | AB92: MINIMARKET ROY
A93: 45965 | B93: HHBO001170578 | C93: YACONDSEX | D93: CONDONES X3 UNIDADES ECONOMICO | E93: YACONDSEX - CONDONES X3 UNIDADES ECONOMICO | F93: 3 | G93: 866.2 | H93: 0 | I93: 2598.6 | J93: BG23 | K93: 1 | L93: 166 | M93: VILLAVICENCIO | N93: ZONA BOGOTA | O93: TERCEROS | P93: 2025 SEM 45 | Q93: 2910 | R93: 905 | S93: martes | T93: YASS | U93: 1 | V93: 3 | W93: TAT | X93: BLANCA CECILIA RODRIGUEZ DUARTE | Y93: Preventa | Z93: 41655922 | AA93: 86065145 | AB93: EL ESQUINAZO J30
A94: 45965 | B94: HHBO001170578 | C94: YAPANIAZUX12 | D94: PAÑITOS HUMEDOS DAMPY AAZUL X 12UND | E94: YAPANIAZUX12 - PAÑITOS HUMEDOS DAMPY AAZUL X 12UND | F94: 6 | G94: 870 | H94: 0 | I94: 5220 | J94: BG23 | K94: 1 | L94: 166 | M94: VILLAVICENCIO | N94: ZONA BOGOTA | O94: TERCEROS | P94: 2025 SEM 45 | Q94: 2910 | R94: 905 | S94: martes | T94: YASS | U94: 1 | V94: 6 | W94: TAT | X94: BLANCA CECILIA RODRIGUEZ DUARTE | Y94: Preventa | Z94: 41655922 | AA94: 86065145 | AB94: EL ESQUINAZO J30
A95: 45965 | B95: HHBQ000722805 | C95: YACAN38 | D95: CANDADO 38 MM | E95: YACAN38 - CANDADO 38 MM | F95: 6 | G95: 2668.75 | H95: 0 | I95: 16012.5 | J95: BQ15 | K95: 1 | L95: 212 | M95: Tuti Cartagena | N95: ZONA NORTE | O95: TERCEROS | P95: 2025 SEM 45 | Q95: 1959 | R95: 718 | S95: martes | T95: YASS | U95: 1 | V95: 6 | W95: TAT | X95: ROSA URBINA GUTIERREZ PEÑARANDA | Y95: Preventa | Z95: 30882589 | AA95: 1044921552 | AB95: TIENDA Y VARIEDAD ROCHY
A96: 45965 | B96: HHBQ000722805 | C96: YACAN50 | D96: CANDADO 50 MM | E96: YACAN50 - CANDADO 50 MM | F96: 4 | G96: 4327.73 | H96: 0 | I96: 17310.92 | J96: BQ15 | K96: 1 | L96: 212 | M96: Tuti Cartagena | N96: ZONA NORTE | O96: TERCEROS | P96: 2025 SEM 45 | Q96: 1959 | R96: 718 | S96: martes | T96: YASS | U96: 1 | V96: 4 | W96: TAT | X96: ROSA URBINA GUTIERREZ PEÑARANDA | Y96: Preventa | Z96: 30882589 | AA96: 1044921552 | AB96: TIENDA Y VARIEDAD ROCHY
... A112: 45965 | B112: HHBO001170558 | C112: LYDETE3X1800 | D112: COMBO DETERGENTE ETERNA 3.000+1.800 OFERTA | E112: LYDETE3X1800 - COMBO DETERGENTE ETERNA 3.000+1.800 OFERTA | F112: 1 | G112: 28655.46 | H112: 0 | I112: 28655.46 | J112: BG23 | K112: 1 | L112: 166 | M112: VILLAVICENCIO | N112: ZONA BOGOTA | O112: TERCEROS | P112: 2025 SEM 45 | Q112: 2911 | R112: 905 | S112: martes | T112: ETERNA | U112: 1 | V112: 1 | W112: TAT | X112: CARLOS IVAN ROJAS CANO | Y112: Preventa | Z112: 1123801553 | AA112: 86065145 | AB112: TIENDA EL GORDO
A113: 45965 | B113: HHME001459888 | C113: YALAPIZAMAX12 | D113: LAPIZ ESCOLAR AMARILLO X12 | E113: YALAPIZAMAX12 - LAPIZ ESCOLAR AMARILLO X12 | F113: 1 | G113: 4853 | H113: 0 | I113: 4853 | J113: MD04 | K113: 1 | L113: 125 | M113: TUTI Medellin | N113: ZONA CENTRO | O113: TERCEROS | P113: 2025 SEM 45 | Q113: 1306 | R113: 102 | S113: martes | T113: 0 | U113: 1 | V113: 1 | W113: TAT | X113: MARIA ELCY VARGAS MARIN | Y113: Preventa | Z113: 55056060 | AA113: 1036660589 | AB113: TIENDA SAMU
A114: 45965 | B114: HHME001459896 | C114: YAGOM90 | D114: GOMINA N17 EN SOBRE 90G | E114: YAGOM90 - GOMINA N17 EN SOBRE 90G | F114: 12 | G114: 1092.44 | H114: 0 | I114: 13109.28 | J114: MD02 | K114: 1 | L114: 125 | M114: TUTI Medellin | N114: ZONA CENTRO | O114: TERCEROS | P114: 2025 SEM 45 | Q114: 1398 | R114: 117 | S114: martes | T114: YASS | U114: 1 | V114: 12 | W114: TAT | X114: HAROL CASTRILLON GOMEZ | Y114: Preventa | Z114: 1003757794 | AA114: 8432406 | AB114: MILAGROS LA 38
A115: 45965 | B115: HHME001459940 | C115: PBDESCOJINX18 | D115: DES. AFM DPL ORIG 12G X18 | E115: PBDESCOJINX18 - DES. AFM DPL ORIG 12G X18 | F115: 1 | G115: 11900 | H115: 357 | I115: 11543 | J115: MD06 | K115: 1 | L115: 125 | M115: TUTI Medellin | N115: ZONA CENTRO | O115: TERCEROS | P115: 2025 SEM 45 | Q115: 1309 | R115: 103 | S115: martes | T115: PREBEL | U115: 1 | V115: 1 | W115: TAT | X115: JOSE ANTONIO YARCE RAIGOSA | Y115: Preventa | Z115: 4391768 | AA115: 1037594291 | AB115: GRANERO NELSON
A116: 45965 | B116: HHBO001170607 | C116: YALAPIZAMAX12 | D116: LAPIZ ESCOLAR AMARILLO X12 | E116: YALAPIZAMAX12 - LAPIZ ESCOLAR AMARILLO X12 | F116: 1 | G116: 4853 | H116: 0 | I116: 4853 | J116: BG13 | K116: 1 | L116: 126 | M116: TUTI Bogota | N116: ZONA BOGOTA | O116: TERCEROS | P116: 2025 SEM 45 | Q116: 2234 | R116: 945 | S116: martes | T116: 0 | U116: 1 | V116: 1 | W116: TAT | X116: NUBIA JANET CONTRERAS ARIAS | Y116: Preventa | Z116: 51899379 | AA116: 52460170 | AB116: BAVIERA EXPRESS
A117: 45965 | B117: HHBO001170607 | C117: YALAPIROX12 | D117: LAPIZ ROJO X12 UND | E117: YALAPIROX12 - LAPIZ ROJO X12 UND | F117: 1 | G117: 4882 | H117: 0 | I117: 4882 | J117: BG13 | K117: 1 | L117: 126 | M117: TUTI Bogota | N117: ZONA BOGOTA | O117: TERCEROS | P117: 2025 SEM 45 | Q117: 2234 | R117: 945 | S117: martes | T117: YASS | U117: 1 | V117: 1 | W117: TAT | X117: NUBIA JANET CONTRERAS ARIAS | Y117: Preventa | Z117: 51899379 | AA117: 52460170 | AB117: BAVIERA EXPRESS
A118: 45965 | B118: HHBO001170607 | C118: YASEDA20 | D118: SEDA DENTAL CON CERA 20 MT | E118: YASEDA20 - SEDA DENTAL CON CERA 20 MT | F118: 6 | G118: 1092.44 | H118: 0 | I118: 6554.64 | J118: BG13 | K118: 1 | L118: 126 | M118: TUTI Bogota | N118: ZONA BOGOTA | O118: TERCEROS | P118: 2025 SEM 45 | Q118: 2234 | R118: 945 | S118: martes | T118: YASS | U118: 1 | V118: 6 | W118: TAT | X118: NUBIA JANET CONTRERAS ARIAS | Y118: Preventa | Z118: 51899379 | AA118: 52460170 | AB118: BAVIERA EXPRESS
A119: 45965 | B119: HHBO001170607 | C119: YAPANIAMA | D119: PAÑITOS HUMEDOS DAMPY AMARILLOS X 15 UND | E119: YAPANIAMA - PAÑITOS HUMEDOS DAMPY AMARILLOS X 15 UND | F119: 6 | G119: 1260.5 | H119: 0 | I119: 7563 | J119: BG13 | K119: 1 | L119: 126 | M119: TUTI Bogota | N119: ZONA BOGOTA | O119: TERCEROS | P119: 2025 SEM 45 | Q119: 2234 | R119: 945 | S119: martes | T119: YASS | U119: 1 | V119: 6 | W119: TAT | X119: NUBIA JANET CONTRERAS ARIAS | Y119: Preventa | Z119: 51899379 | AA119: 52460170 | AB119: BAVIERA EXPRESS
A120: 45965 | B120: HHBO001170609 | C120: LYDETE1800DX1 | D120: DETERGENTE ETERNA DOYPACK 1800 ML X1 | E120: LYDETE1800DX1 - DETERGENTE ETERNA DOYPACK 1800 ML X1 | F120: 1 | G120: 12000 | H120: 0 | I120: 12000 | J120: BG13 | K120: 1 | L120: 2 | M120: CIUDAD BOGOTA | N120: ZONA BOGOTA | O120: TERCEROS | P120: 2025 SEM 45 | Q120: 2234 | R120: 945 | S120: martes | T120: ETERNA | U120: 1 | V120: 1 | W120: TAT | X120: BRYAN ALEXANDER RAMOS RODRIGUEZ | Y120: Preventa | Z120: 1022948813 | AA120: 52460170 | AB120: BRAYAN RAMOS
A121: 45965 | B121: HHME001459999 | C121: YABOLSAMED | D121: BOLSA BASURA PAQUETE X8 UNIDADES | E121: YABOLSAMED - BOLSA BASURA PAQUETE X8 UNIDADES | F121: 12 | G121: 1344.54 | H121: 0 | I121: 16134.48 | J121: MD01 | K121: 1 | L121: 125 | M121: TUTI Medellin | N121: ZONA CENTRO | O121: TERCEROS | P121: 2025 SEM 45 | Q121: 1333 | R121: 113 | S121: martes | T121: YASS | U121: 1 | V121: 12 | W121: TAT | X121: FABIO HURTADO BERMUDEZ | Y121: Preventa | Z121: 71664546 | AA121: 79389221 | AB121: FABIO HURTADO BERMUDEZ
A122: 45965 | B122: HHME001460006 | C122: YABOLSAMED | D122: BOLSA BASURA PAQUETE X8 UNIDADES | E122: YABOLSAMED - BOLSA BASURA PAQUETE X8 UNIDADES | F122: 30 | G122: 1344.54 | H122: 0 | I122: 40336.2 | J122: MD01 | K122: 1 | L122: 125 | M122: TUTI Medellin | N122: ZONA CENTRO | O122: TERCEROS | P122: 2025 SEM 45 | Q122: 1333 | R122: 113 | S122: martes | T122: YASS | U122: 1 | V122: 30 | W122: TAT | X122: VICTOR JAIME ECHEVERRI GONZALEZ | Y122: Preventa | Z122: 3563520 | AA122: 79389221 | AB122: VICTOR JAIME ECHEVERRI GONZALEZ
A123: 45965 | B123: HHBO001170618 | C123: PBTAL85X2 | D123: TALCO 85GR X 2 | E123: PBTAL85X2 - TALCO 85GR X 2 | F123: 1 | G123: 12290.73 | H123: 0 | I123: 12290.73 | J123: BG23 | K123: 1 | L123: 166 | M123: VILLAVICENCIO | N123: ZONA BOGOTA | O123: TERCEROS | P123: 2025 SEM 45 | Q123: 2910 | R123: 905 | S123: martes | T123: PREBEL | U123: 1 | V123: 1 | W123: TAT | X123: FRANCISCO CELY PALACIOS | Y123: Preventa | Z123: 17335606 | AA123: 86065145 | AB123: AUTOSERVICIO EL ALTO
A124: 45965 | B124: HHBU000696923 | C124: LYSUAV190DX1 | D124: LIMPIAYA SUAVIZANTE DOYPACK 190 ML X1 | E124: LYSUAV190DX1 - LIMPIAYA SUAVIZANTE DOYPACK 190 ML X1 | F124: 6 | G124: 977 | H124: 0 | I124: 5862 | J124: CU02 | K124: 1 | L124: 211 | M124: Tuti Cúcuta | N124: ZONA SANTANDER | O124: TERCEROS | P124: 2025 SEM 45 | Q124: 1675 | R124: 409 | S124: martes | T124: ETERNA | U124: 1 | V124: 6 | W124: TAT | X124: ANGELA DANIELA VILLEGAS CACERES | Y124: Preventa | Z124: 1092339092 | AA124: 1090387974 | AB124: TIENDA MIXTA PANDA
A125: 45965 | B125: HHBU000696923 | C125: LYLIMPLAV200DX1 | D125: LIMPIAYA LIMPIADOR LAVANDA 200 ML X1 | E125: LYLIMPLAV200DX1 - LIMPIAYA LIMPIADOR LAVANDA 200 ML X1 | F125: 6 | G125: 1120 | H125: 0 | I125: 6720 | J125: CU02 | K125: 1 | L125: 211 | M125: Tuti Cúcuta | N125: ZONA SANTANDER | O125: TERCEROS | P125: 2025 SEM 45 | Q125: 1675 | R125: 409 | S125: martes | T125: ETERNA | U125: 1 | V125: 6 | W125: TAT | X125: ANGELA DANIELA VILLEGAS CACERES | Y125: Preventa | Z125: 1092339092 | AA125: 1090387974 | AB125: TIENDA MIXTA PANDA
A126: 45965 | B126: HHBU000696932 | C126: YABOLSAMED | D126: BOLSA BASURA PAQUETE X8 UNIDADES | E126: YABOLSAMED - BOLSA BASURA PAQUETE X8 UNIDADES | F126: 2 | G126: 1344.54 | H126: 0 | I126: 2689.08 | J126: CU02 | K126: 1 | L126: 211 | M126: Tuti Cúcuta | N126: ZONA SANTANDER | O126: TERCEROS | P126: 2025 SEM 45 | Q126: 1675 | R126: 409 | S126: martes | T126: YASS | U126: 1 | V126: 2 | W126: TAT | X126: LUIS GERARDO REYES VELANDIA | Y126: Preventa | Z126: 88189948 | AA126: 1090387974 | AB126: TIENDE LOS REYES
A127: 45965 | B127: HHBU000696936 | C127: LYGUANT8NGX2 | D127: LIMPIAYA GUANTE NEGRO TALLA8 X2 | E127: LYGUANT8NGX2 - LIMPIAYA GUANTE NEGRO TALLA8 X2 | F127: 3 | G127: 3180 | H127: 0 | I127: 9540 | J127: CU02 | K127: 1 | L127: 211 | M127: Tuti Cúcuta | N127: ZONA SANTANDER | O127: TERCEROS | P127: 2025 SEM 45 | Q127: 1675 | R127: 409 | S127: martes | T127: ETERNA | U127: 1 | V127: 3 | W127: TAT | X127: LUZ MERY LEGUIZAMON CAÑON | Y127: Preventa | Z127: 39540539 | AA127: 1090387974 | AB127: TIENDA EL RINCONCITO
A128: 45965 | B128: HHME001460042 | C128: YAPADAM150 | D128: PAÑITOS HUMEDOS DAMPY X 150 UND AZUL | E128: YAPADAM150 - PAÑITOS HUMEDOS DAMPY X 150 UND AZUL | F128: 2 | G128: 6422.4 | H128: 0 | I128: 12844.8 | J128: TT02 | K128: 1 | L128: 125 | M128: TUTI Medellin | N128: ZONA CENTRO | O128: TERCEROS | P128: 2025 SEM 45 | Q128: 1321 | R128: 107 | S128: martes | T128: YASS | U128: 1 | V128: 2 | W128: TAT | X128: MAGNOLIA EUGENIA GARCIA ARIAS | Y128: Preventa | Z128: 43467888 | AA128: 1037949442 | AB128: LA TIENDA
... A156: 45965 | B156: HHBO001170606 | C156: PBTALCO30 | D156: TALCO POLVO AFM 30 GR | E156: PBTALCO30 - TALCO POLVO AFM 30 GR | F156: 1 | G156: 2900.04 | H156: 0 | I156: 2900.04 | J156: BG19 | K156: 1 | L156: 126 | M156: TUTI Bogota | N156: ZONA BOGOTA | O156: TERCEROS | P156: 2025 SEM 45 | Q156: 2196 | R156: 934 | S156: martes | T156: PREBEL | U156: 1 | V156: 1 | W156: TAT | X156: DAVID PEÑALOZA PEÑALOZA | Y156: Preventa | Z156: 79209980 | AA156: 79903522 | AB156: DULCERIA DULCE ESTACION
A157: 45965 | B157: HHBU000696938 | C157: YALAPIZAMAX12 | D157: LAPIZ ESCOLAR AMARILLO X12 | E157: YALAPIZAMAX12 - LAPIZ ESCOLAR AMARILLO X12 | F157: 4 | G157: 4853 | H157: 0 | I157: 19412 | J157: CU02 | K157: 1 | L157: 211 | M157: Tuti Cúcuta | N157: ZONA SANTANDER | O157: TERCEROS | P157: 2025 SEM 45 | Q157: 1675 | R157: 409 | S157: martes | T157: 0 | U157: 1 | V157: 4 | W157: TAT | X157: GERARDO ROBAYO | Y157: Preventa | Z157: 88187436 | AA157: 1090387974 | AB157: TIENDA MIXTA GERARDO
A158: 45965 | B158: HHBU000696938 | C158: PBDESCREMA72H | D158: DESODORANTE COLAPSIBLE 40GR 72H | E158: PBDESCREMA72H - DESODORANTE COLAPSIBLE 40GR 72H | F158: 3 | G158: 3000 | H158: 0 | I158: 9000 | J158: CU02 | K158: 1 | L158: 211 | M158: Tuti Cúcuta | N158: ZONA SANTANDER | O158: TERCEROS | P158: 2025 SEM 45 | Q158: 1675 | R158: 409 | S158: martes | T158: PREBEL | U158: 1 | V158: 3 | W158: TAT | X158: GERARDO ROBAYO | Y158: Preventa | Z158: 88187436 | AA158: 1090387974 | AB158: TIENDA MIXTA GERARDO
A159: 45965 | B159: HHBU000696938 | C159: PBDESROLL | D159: DESODORANTE ROLL-ON 30ML | E159: PBDESROLL - DESODORANTE ROLL-ON 30ML | F159: 3 | G159: 3000 | H159: 0 | I159: 9000 | J159: CU02 | K159: 1 | L159: 211 | M159: Tuti Cúcuta | N159: ZONA SANTANDER | O159: TERCEROS | P159: 2025 SEM 45 | Q159: 1675 | R159: 409 | S159: martes | T159: PREBEL | U159: 1 | V159: 3 | W159: TAT | X159: GERARDO ROBAYO | Y159: Preventa | Z159: 88187436 | AA159: 1090387974 | AB159: TIENDA MIXTA GERARDO
A160: 45965 | B160: HHBU000696950 | C160: YALAPIZAMAX12 | D160: LAPIZ ESCOLAR AMARILLO X12 | E160: YALAPIZAMAX12 - LAPIZ ESCOLAR AMARILLO X12 | F160: 1 | G160: 4853 | H160: 0 | I160: 4853 | J160: CU02 | K160: 1 | L160: 211 | M160: Tuti Cúcuta | N160: ZONA SANTANDER | O160: TERCEROS | P160: 2025 SEM 45 | Q160: 1674 | R160: 409 | S160: martes | T160: 0 | U160: 1 | V160: 1 | W160: TAT | X160: REINALDO TRIANA MUÑOZ | Y160: Preventa | Z160: 91070681 | AA160: 1090387974 | AB160: TIENDA TONY
A161: 45965 | B161: HHBQ000722875 | C161: YALAPIZAMAX12 | D161: LAPIZ ESCOLAR AMARILLO X12 | E161: YALAPIZAMAX12 - LAPIZ ESCOLAR AMARILLO X12 | F161: 1 | G161: 4853 | H161: 0 | I161: 4853 | J161: BQ06 | K161: 1 | L161: 155 | M161: TUTI Barranquilla | N161: ZONA NORTE | O161: TERCEROS | P161: 2025 SEM 45 | Q161: 1937 | R161: 713 | S161: martes | T161: 0 | U161: 1 | V161: 1 | W161: TAT | X161: MARIA LIGIA LOPEZ TRUJILLO | Y161: Preventa | Z161: 22437532 | AA161: 8525463 | AB161: TIENDA DONDE LIGIA
A162: 45965 | B162: HHBQ000722875 | C162: YALAPIROX12 | D162: LAPIZ ROJO X12 UND | E162: YALAPIROX12 - LAPIZ ROJO X12 UND | F162: 1 | G162: 4882 | H162: 0 | I162: 4882 | J162: BQ06 | K162: 1 | L162: 155 | M162: TUTI Barranquilla | N162: ZONA NORTE | O162: TERCEROS | P162: 2025 SEM 45 | Q162: 1937 | R162: 713 | S162: martes | T162: YASS | U162: 1 | V162: 1 | W162: TAT | X162: MARIA LIGIA LOPEZ TRUJILLO | Y162: Preventa | Z162: 22437532 | AA162: 8525463 | AB162: TIENDA DONDE LIGIA
A163: 45965 | B163: HHBQ000722875 | C163: LYSUAV190DX1 | D163: LIMPIAYA SUAVIZANTE DOYPACK 190 ML X1 | E163: LYSUAV190DX1 - LIMPIAYA SUAVIZANTE DOYPACK 190 ML X1 | F163: 12 | G163: 977 | H163: 0 | I163: 11724 | J163: BQ06 | K163: 1 | L163: 155 | M163: TUTI Barranquilla | N163: ZONA NORTE | O163: TERCEROS | P163: 2025 SEM 45 | Q163: 1937 | R163: 713 | S163: martes | T163: ETERNA | U163: 1 | V163: 12 | W163: TAT | X163: MARIA LIGIA LOPEZ TRUJILLO | Y163: Preventa | Z163: 22437532 | AA163: 8525463 | AB163: TIENDA DONDE LIGIA
A164: 45965 | B164: HHBU000696966 | C164: YAPANIAZU | D164: PAÑITOS HUMEDOS DAMPY X 20 AZUL | E164: YAPANIAZU - PAÑITOS HUMEDOS DAMPY X 20 AZUL | F164: 6 | G164: 1344.54 | H164: 0 | I164: 8067.24 | J164: CU02 | K164: 1 | L164: 211 | M164: Tuti Cúcuta | N164: ZONA SANTANDER | O164: TERCEROS | P164: 2025 SEM 45 | Q164: 1678 | R164: 411 | S164: martes | T164: YASS | U164: 1 | V164: 6 | W164: TAT | X164: CRISOSTIMO BARAJAS SUAREZ | Y164: Preventa | Z164: 5455284 | AA164: 1093777438 | AB164: TEINDA MIXTA
A165: 45965 | B165: HHBU000696966 | C165: YAPANIAMA | D165: PAÑITOS HUMEDOS DAMPY AMARILLOS X 15 UND | E165: YAPANIAMA - PAÑITOS HUMEDOS DAMPY AMARILLOS X 15 UND | F165: 6 | G165: 1260.5 | H165: 0 | I165: 7563 | J165: CU02 | K165: 1 | L165: 211 | M165: Tuti Cúcuta | N165: ZONA SANTANDER | O165: TERCEROS | P165: 2025 SEM 45 | Q165: 1678 | R165: 411 | S165: martes | T165: YASS | U165: 1 | V165: 6 | W165: TAT | X165: CRISOSTIMO BARAJAS SUAREZ | Y165: Preventa | Z165: 5455284 | AA165: 1093777438 | AB165: TEINDA MIXTA
A166: 45965 | B166: HHBO001170667 | C166: PBELDES12X18 | D166: DES. EA DPL CLASS 12G X 18 | E166: PBELDES12X18 - DES. EA DPL CLASS 12G X 18 | F166: 1 | G166: 12500 | H166: 375 | I166: 12125 | J166: BG20 | K166: 1 | L166: 126 | M166: TUTI Bogota | N166: ZONA BOGOTA | O166: TERCEROS | P166: 2025 SEM 45 | Q166: 2149 | R166: 923 | S166: martes | T166: PREBEL | U166: 1 | V166: 1 | W166: TAT | X166: GLORIA ESPERANZA JOVEN MARIN | Y166: Preventa | Z166: 52194044 | AA166: 79986646 | AB166: TIENDA SURTITODO
A167: 45965 | B167: HHMO000623642 | C167: LYVIDR500X1 | D167: LIMPIAYA LIMPIAVIDRIOS MULTIUSOS 500ML X1 | E167: LYVIDR500X1 - LIMPIAYA LIMPIAVIDRIOS MULTIUSOS 500ML X1 | F167: 4 | G167: 2647.06 | H167: 0 | I167: 10588.24 | J167: MT11 | K167: 1 | L167: 156 | M167: TUTI Monteria | N167: ZONA CENTRO | O167: TERCEROS | P167: 2025 SEM 45 | Q167: 1737 | R167: 509 | S167: martes | T167: ETERNA | U167: 1 | V167: 4 | W167: TAT | X167: HILDA GOMEZ RAMOS | Y167: Preventa | Z167: 36376745 | AA167: 78716125 | AB167: TIENDA OPITA
A168: 45965 | B168: HHBO001170674 | C168: YAPANIAMA | D168: PAÑITOS HUMEDOS DAMPY AMARILLOS X 15 UND | E168: YAPANIAMA - PAÑITOS HUMEDOS DAMPY AMARILLOS X 15 UND | F168: 3 | G168: 1260.5 | H168: 0 | I168: 3781.5 | J168: BG13 | K168: 1 | L168: 126 | M168: TUTI Bogota | N168: ZONA BOGOTA | O168: TERCEROS | P168: 2025 SEM 45 | Q168: 2234 | R168: 945 | S168: martes | T168: YASS | U168: 1 | V168: 3 | W168: TAT | X168: JULIETH BLANDON ORTEGA | Y168: Preventa | Z168: 1030609043 | AA168: 52460170 | AB168: MINI MARKET LOS PAISAS
A169: 45965 | B169: HHBO001170694 | C169: YAPANIAMA | D169: PAÑITOS HUMEDOS DAMPY AMARILLOS X 15 UND | E169: YAPANIAMA - PAÑITOS HUMEDOS DAMPY AMARILLOS X 15 UND | F169: 3 | G169: 1260.5 | H169: 0 | I169: 3781.5 | J169: BG20 | K169: 1 | L169: 126 | M169: TUTI Bogota | N169: ZONA BOGOTA | O169: TERCEROS | P169: 2025 SEM 45 | Q169: 2149 | R169: 923 | S169: martes | T169: YASS | U169: 1 | V169: 3 | W169: TAT | X169: LINA MARIA NINO BASTO | Y169: Preventa | Z169: 1096957783 | AA169: 79986646 | AB169: MINIMERCADO DALY
A170: 45965 | B170: HHBO001170694 | C170: LYESPOOROX12 | D170: LIMPIAYA ESPONJA ORO/PLATA X12 | E170: LYESPOOROX12 - LIMPIAYA ESPONJA ORO/PLATA X12 | F170: 1 | G170: 8991.6 | H170: 449.58 | I170: 8542.02 | J170: BG20 | K170: 1 | L170: 126 | M170: TUTI Bogota | N170: ZONA BOGOTA | O170: TERCEROS | P170: 2025 SEM 45 | Q170: 2149 | R170: 923 | S170: martes | T170: ETERNA | U170: 1 | V170: 1 | W170: TAT | X170: LINA MARIA NINO BASTO | Y170: Preventa | Z170: 1096957783 | AA170: 79986646 | AB170: MINIMERCADO DALY
A171: 45965 | B171: HHBO001170694 | C171: LYLANAACEX6 | D171: LIMPIAYA LANA ACERO X6 | E171: LYLANAACEX6 - LIMPIAYA LANA ACERO X6 | F171: 1 | G171: 1180 | H171: 0 | I171: 1180 | J171: BG20 | K171: 1 | L171: 126 | M171: TUTI Bogota | N171: ZONA BOGOTA | O171: TERCEROS | P171: 2025 SEM 45 | Q171: 2149 | R171: 923 | S171: martes | T171: ETERNA | U171: 6 | V171: 6 | W171: TAT | X171: LINA MARIA NINO BASTO | Y171: Preventa | Z171: 1096957783 | AA171: 79986646 | AB171: MINIMERCADO DALY
A172: 45965 | B172: HHBO001170720 | C172: PBTALCO30 | D172: TALCO POLVO AFM 30 GR | E172: PBTALCO30 - TALCO POLVO AFM 30 GR | F172: 4 | G172: 2900.04 | H172: 0 | I172: 11600.16 | J172: BG20 | K172: 1 | L172: 126 | M172: TUTI Bogota | N172: ZONA BOGOTA | O172: TERCEROS | P172: 2025 SEM 45 | Q172: 2155 | R172: 925 | S172: martes | T172: PREBEL | U172: 1 | V172: 4 | W172: TAT | X172: STEFANY JAN SEN MENDEZ | Y172: Preventa | Z172: 1007407593 | AA172: 1000685156 | AB172: PAPELERIA EL SOL
A173: 45965 | B173: HHBO001170720 | C173: YAGOM30 | D173: GOMINA N17 EN SOBRE 30G | E173: YAGOM30 - GOMINA N17 EN SOBRE 30G | F173: 5 | G173: 672.27 | H173: 0 | I173: 3361.35 | J173: BG20 | K173: 1 | L173: 126 | M173: TUTI Bogota | N173: ZONA BOGOTA | O173: TERCEROS | P173: 2025 SEM 45 | Q173: 2155 | R173: 925 | S173: martes | T173: YASS | U173: 1 | V173: 5 | W173: TAT | X173: STEFANY JAN SEN MENDEZ | Y173: Preventa | Z173: 1007407593 | AA173: 1000685156 | AB173: PAPELERIA EL SOL
... A248: 45965 | B248: HHME001460048 | C248: LYLOZA500ML | D248: LAVALOZA LIQUIDO 500ML | E248: LYLOZA500ML - LAVALOZA LIQUIDO 500ML | F248: 3 | G248: 2475 | H248: 0 | I248: 7425 | J248: TT02 | K248: 1 | L248: 125 | M248: TUTI Medellin | N248: ZONA CENTRO | O248: TERCEROS | P248: 2025 SEM 45 | Q248: 1321 | R248: 107 | S248: martes | T248: ETERNA | U248: 1 | V248: 3 | W248: TAT | X248: LUZ DARY ATEHORTUA RESTREPO | Y248: Preventa | Z248: 43035531 | AA248: 1037949442 | AB248: CHARCUTERIA EL CARAJILLO
A249: 45965 | B249: HHBQ000722883 | C249: YALAPIZAMAX12 | D249: LAPIZ ESCOLAR AMARILLO X12 | E249: YALAPIZAMAX12 - LAPIZ ESCOLAR AMARILLO X12 | F249: 1 | G249: 4853 | H249: 0 | I249: 4853 | J249: BQ06 | K249: 1 | L249: 155 | M249: TUTI Barranquilla | N249: ZONA NORTE | O249: TERCEROS | P249: 2025 SEM 45 | Q249: 1945 | R249: 715 | S249: martes | T249: 0 | U249: 1 | V249: 1 | W249: TAT | X249: LUZ ALBA GONZALEZ RADA | Y249: Preventa | Z249: 32870930 | AA249: 1042436969 | AB249: MERCADITO LA ESTACION
A250: 45965 | B250: HHBQ000722883 | C250: YALAPIROX12 | D250: LAPIZ ROJO X12 UND | E250: YALAPIROX12 - LAPIZ ROJO X12 UND | F250: 1 | G250: 4882 | H250: 0 | I250: 4882 | J250: BQ06 | K250: 1 | L250: 155 | M250: TUTI Barranquilla | N250: ZONA NORTE | O250: TERCEROS | P250: 2025 SEM 45 | Q250: 1945 | R250: 715 | S250: martes | T250: YASS | U250: 1 | V250: 1 | W250: TAT | X250: LUZ ALBA GONZALEZ RADA | Y250: Preventa | Z250: 32870930 | AA250: 1042436969 | AB250: MERCADITO LA ESTACION
A251: 45965 | B251: HHBQ000722883 | C251: LYSUAV190DX1 | D251: LIMPIAYA SUAVIZANTE DOYPACK 190 ML X1 | E251: LYSUAV190DX1 - LIMPIAYA SUAVIZANTE DOYPACK 190 ML X1 | F251: 12 | G251: 977 | H251: 0 | I251: 11724 | J251: BQ06 | K251: 1 | L251: 155 | M251: TUTI Barranquilla | N251: ZONA NORTE | O251: TERCEROS | P251: 2025 SEM 45 | Q251: 1945 | R251: 715 | S251: martes | T251: ETERNA | U251: 1 | V251: 12 | W251: TAT | X251: LUZ ALBA GONZALEZ RADA | Y251: Preventa | Z251: 32870930 | AA251: 1042436969 | AB251: MERCADITO LA ESTACION
A252: 45965 | B252: HHBQ000722883 | C252: LYLIMPLAV200DX1 | D252: LIMPIAYA LIMPIADOR LAVANDA 200 ML X1 | E252: LYLIMPLAV200DX1 - LIMPIAYA LIMPIADOR LAVANDA 200 ML X1 | F252: 12 | G252: 1120 | H252: 0 | I252: 13440 | J252: BQ06 | K252: 1 | L252: 155 | M252: TUTI Barranquilla | N252: ZONA NORTE | O252: TERCEROS | P252: 2025 SEM 45 | Q252: 1945 | R252: 715 | S252: martes | T252: ETERNA | U252: 1 | V252: 12 | W252: TAT | X252: LUZ ALBA GONZALEZ RADA | Y252: Preventa | Z252: 32870930 | AA252: 1042436969 | AB252: MERCADITO LA ESTACION
A253: 45965 | B253: HHBQ000722906 | C253: LYGUANT8AMX2 | D253: LIMPIAYA GUANTE TALLA8 AMARILLO X2 | E253: LYGUANT8AMX2 - LIMPIAYA GUANTE TALLA8 AMARILLO X2 | F253: 3 | G253: 3025.21 | H253: 0 | I253: 9075.63 | J253: BQ06 | K253: 1 | L253: 155 | M253: TUTI Barranquilla | N253: ZONA NORTE | O253: TERCEROS | P253: 2025 SEM 45 | Q253: 1945 | R253: 715 | S253: martes | T253: ETERNA | U253: 1 | V253: 3 | W253: TAT | X253: YULEIMI PATRICIA PEREZ CABARCAS | Y253: Preventa | Z253: 1129523502 | AA253: 1042436969 | AB253: DROGUERIA JARMARY
A254: 45965 | B254: HHBQ000722906 | C254: LYGUANT9AMX2 | D254: LIMPIAYA GUANTE TALLA9 AMARILLO X2 | E254: LYGUANT9AMX2 - LIMPIAYA GUANTE TALLA9 AMARILLO X2 | F254: 1 | G254: 3025.21 | H254: 0 | I254: 3025.21 | J254: BQ06 | K254: 1 | L254: 155 | M254: TUTI Barranquilla | N254: ZONA NORTE | O254: TERCEROS | P254: 2025 SEM 45 | Q254: 1945 | R254: 715 | S254: martes | T254: ETERNA | U254: 1 | V254: 1 | W254: TAT | X254: YULEIMI PATRICIA PEREZ CABARCAS | Y254: Preventa | Z254: 1129523502 | AA254: 1042436969 | AB254: DROGUERIA JARMARY
A255: 45965 | B255: HHBQ000722906 | C255: DRSERUNSILISACHETX1 | D255: SERUM DE SILICONA DROMATIC EN SACHET X1 | E255: DRSERUNSILISACHETX1 - SERUM DE SILICONA DROMATIC EN SACHET X1 | F255: 4 | G255: 2227 | H255: 0 | I255: 8908 | J255: BQ06 | K255: 1 | L255: 155 | M255: TUTI Barranquilla | N255: ZONA NORTE | O255: TERCEROS | P255: 2025 SEM 45 | Q255: 1945 | R255: 715 | S255: martes | T255: DROMATIC | U255: 1 | V255: 4 | W255: TAT | X255: YULEIMI PATRICIA PEREZ CABARCAS | Y255: Preventa | Z255: 1129523502 | AA255: 1042436969 | AB255: DROGUERIA JARMARY
A256: 45965 | B256: HHBQ000722906 | C256: YAGOM90 | D256: GOMINA N17 EN SOBRE 90G | E256: YAGOM90 - GOMINA N17 EN SOBRE 90G | F256: 4 | G256: 1092.44 | H256: 0 | I256: 4369.76 | J256: BQ06 | K256: 1 | L256: 155 | M256: TUTI Barranquilla | N256: ZONA NORTE | O256: TERCEROS | P256: 2025 SEM 45 | Q256: 1945 | R256: 715 | S256: martes | T256: YASS | U256: 1 | V256: 4 | W256: TAT | X256: YULEIMI PATRICIA PEREZ CABARCAS | Y256: Preventa | Z256: 1129523502 | AA256: 1042436969 | AB256: DROGUERIA JARMARY
A257: 45965 | B257: HHBO001170665 | C257: LYCEETIPLANCHA | D257: CEPILLO ECOLOGICO TIPO PLANCHA | E257: LYCEETIPLANCHA - CEPILLO ECOLOGICO TIPO PLANCHA | F257: 1 | G257: 2700 | H257: 0 | I257: 2700 | J257: BG20 | K257: 1 | L257: 126 | M257: TUTI Bogota | N257: ZONA BOGOTA | O257: TERCEROS | P257: 2025 SEM 45 | Q257: 2149 | R257: 923 | S257: martes | T257: ETERNA | U257: 1 | V257: 1 | W257: TAT | X257: MARISOL ELVIRA HERNANDEZ GUZMAN | Y257: Preventa | Z257: 20586137 | AA257: 79986646 | AB257: MISCELANEA MARITA
A258: 45965 | B258: HHBO001170665 | C258: LYLOZA500ML | D258: LAVALOZA LIQUIDO 500ML | E258: LYLOZA500ML - LAVALOZA LIQUIDO 500ML | F258: 1 | G258: 2475 | H258: 0 | I258: 2475 | J258: BG20 | K258: 1 | L258: 126 | M258: TUTI Bogota | N258: ZONA BOGOTA | O258: TERCEROS | P258: 2025 SEM 45 | Q258: 2149 | R258: 923 | S258: martes | T258: ETERNA | U258: 1 | V258: 1 | W258: TAT | X258: MARISOL ELVIRA HERNANDEZ GUZMAN | Y258: Preventa | Z258: 20586137 | AA258: 79986646 | AB258: MISCELANEA MARITA
A259: 45965 | B259: HHBO001170665 | C259: LYLIMPLAV200DX1 | D259: LIMPIAYA LIMPIADOR LAVANDA 200 ML X1 | E259: LYLIMPLAV200DX1 - LIMPIAYA LIMPIADOR LAVANDA 200 ML X1 | F259: 3 | G259: 1120 | H259: 0 | I259: 3360 | J259: BG20 | K259: 1 | L259: 126 | M259: TUTI Bogota | N259: ZONA BOGOTA | O259: TERCEROS | P259: 2025 SEM 45 | Q259: 2149 | R259: 923 | S259: martes | T259: ETERNA | U259: 1 | V259: 3 | W259: TAT | X259: MARISOL ELVIRA HERNANDEZ GUZMAN | Y259: Preventa | Z259: 20586137 | AA259: 79986646 | AB259: MISCELANEA MARITA
A260: 45965 | B260: HHBO001170665 | C260: LYDETE200DX1 | D260: LIMPIAYA DETERGENTE DOYPACK 200 ML X1 | E260: LYDETE200DX1 - LIMPIAYA DETERGENTE DOYPACK 200 ML X1 | F260: 3 | G260: 1440 | H260: 0 | I260: 4320 | J260: BG20 | K260: 1 | L260: 126 | M260: TUTI Bogota | N260: ZONA BOGOTA | O260: TERCEROS | P260: 2025 SEM 45 | Q260: 2149 | R260: 923 | S260: martes | T260: ETERNA | U260: 1 | V260: 3 | W260: TAT | X260: MARISOL ELVIRA HERNANDEZ GUZMAN | Y260: Preventa | Z260: 20586137 | AA260: 79986646 | AB260: MISCELANEA MARITA
A261: 45965 | B261: HHBO001170665 | C261: LYSUAV190DX1 | D261: LIMPIAYA SUAVIZANTE DOYPACK 190 ML X1 | E261: LYSUAV190DX1 - LIMPIAYA SUAVIZANTE DOYPACK 190 ML X1 | F261: 3 | G261: 977 | H261: 0 | I261: 2931 | J261: BG20 | K261: 1 | L261: 126 | M261: TUTI Bogota | N261: ZONA BOGOTA | O261: TERCEROS | P261: 2025 SEM 45 | Q261: 2149 | R261: 923 | S261: martes | T261: ETERNA | U261: 1 | V261: 3 | W261: TAT | X261: MARISOL ELVIRA HERNANDEZ GUZMAN | Y261: Preventa | Z261: 20586137 | AA261: 79986646 | AB261: MISCELANEA MARITA
... A279: 45965 | B279: HHBU000697017 | C279: YAGELX1 | D279: GEL MENTHUS JUHNIOS VERDE 30GR X1 | E279: YAGELX1 - GEL MENTHUS JUHNIOS VERDE 30GR X1 | F279: 1 | G279: 1640 | H279: 0 | I279: 1640 | J279: CU02 | K279: 1 | L279: 211 | M279: Tuti Cúcuta | N279: ZONA SANTANDER | O279: TERCEROS | P279: 2025 SEM 45 | Q279: 1675 | R279: 409 | S279: martes | T279: YASS | U279: 1 | V279: 1 | W279: TAT | X279: LEIDY JOHANA RODRIGUEZ RODRIGUEZ | Y279: Preventa | Z279: 1090426901 | AA279: 1090387974 | AB279: LEIDY R
A280: 45965 | B280: HHBU000697017 | C280: YALAPIZAMAX12 | D280: LAPIZ ESCOLAR AMARILLO X12 | E280: YALAPIZAMAX12 - LAPIZ ESCOLAR AMARILLO X12 | F280: 1 | G280: 4853 | H280: 0 | I280: 4853 | J280: CU02 | K280: 1 | L280: 211 | M280: Tuti Cúcuta | N280: ZONA SANTANDER | O280: TERCEROS | P280: 2025 SEM 45 | Q280: 1675 | R280: 409 | S280: martes | T280: 0 | U280: 1 | V280: 1 | W280: TAT | X280: LEIDY JOHANA RODRIGUEZ RODRIGUEZ | Y280: Preventa | Z280: 1090426901 | AA280: 1090387974 | AB280: LEIDY R
A281: 45965 | B281: HHBU000697017 | C281: LYLOZA700DX1 | D281: LIMPIAYA LAVA LOZA DOYPACK 700 ML X1 | E281: LYLOZA700DX1 - LIMPIAYA LAVA LOZA DOYPACK 700 ML X1 | F281: 1 | G281: 3562.19 | H281: 0 | I281: 3562.19 | J281: CU02 | K281: 1 | L281: 211 | M281: Tuti Cúcuta | N281: ZONA SANTANDER | O281: TERCEROS | P281: 2025 SEM 45 | Q281: 1675 | R281: 409 | S281: martes | T281: ETERNA | U281: 1 | V281: 1 | W281: TAT | X281: LEIDY JOHANA RODRIGUEZ RODRIGUEZ | Y281: Preventa | Z281: 1090426901 | AA281: 1090387974 | AB281: LEIDY R
A282: 45965 | B282: HHBO001170826 | C282: PBDESCOJINX18 | D282: DES. AFM DPL ORIG 12G X18 | E282: PBDESCOJINX18 - DES. AFM DPL ORIG 12G X18 | F282: 1 | G282: 11900 | H282: 0 | I282: 11900 | J282: BG20 | K282: 1 | L282: 2 | M282: CIUDAD BOGOTA | N282: ZONA BOGOTA | O282: TERCEROS | P282: 2025 SEM 45 | Q282: 2158 | R282: 926 | S282: martes | T282: PREBEL | U282: 1 | V282: 1 | W282: TAT | X282: MARIA EUGENIA PINZON SUAREZ | Y282: Preventa | Z282: 24178752 | AA282: 11223739 | AB282: TIENDA ESQUINA
A283: 45965 | B283: HHBO001170826 | C283: PBDESCLIROLL | D283: DESODORANTE CLINICAL ROLL-ON 30ML | E283: PBDESCLIROLL - DESODORANTE CLINICAL ROLL-ON 30ML | F283: 3 | G283: 3000 | H283: 0 | I283: 9000 | J283: BG20 | K283: 1 | L283: 2 | M283: CIUDAD BOGOTA | N283: ZONA BOGOTA | O283: TERCEROS | P283: 2025 SEM 45 | Q283: 2158 | R283: 926 | S283: martes | T283: PREBEL | U283: 1 | V283: 3 | W283: TAT | X283: MARIA EUGENIA PINZON SUAREZ | Y283: Preventa | Z283: 24178752 | AA283: 11223739 | AB283: TIENDA ESQUINA
A284: 45965 | B284: HHBO001170826 | C284: PBELDESMIN30 | D284: EA CLASSIC MINI ROLL ON 30ML | E284: PBELDESMIN30 - EA CLASSIC MINI ROLL ON 30ML | F284: 2 | G284: 3000 | H284: 0 | I284: 6000 | J284: BG20 | K284: 1 | L284: 2 | M284: CIUDAD BOGOTA | N284: ZONA BOGOTA | O284: TERCEROS | P284: 2025 SEM 45 | Q284: 2158 | R284: 926 | S284: martes | T284: PREBEL | U284: 1 | V284: 2 | W284: TAT | X284: MARIA EUGENIA PINZON SUAREZ | Y284: Preventa | Z284: 24178752 | AA284: 11223739 | AB284: TIENDA ESQUINA
A285: 45965 | B285: HHBO001170834 | C285: LYDESEN500 | D285: DESENGRASANTE CITRICO 500ML | E285: LYDESEN500 - DESENGRASANTE CITRICO 500ML | F285: 3 | G285: 2645.48 | H285: 0 | I285: 7936.44 | J285: BG11 | K285: 1 | L285: 126 | M285: TUTI Bogota | N285: ZONA BOGOTA | O285: TERCEROS | P285: 2025 SEM 45 | Q285: 2199 | R285: 935 | S285: martes | T285: ETERNA | U285: 1 | V285: 3 | W285: TAT | X285: LUIS ORLANDO LUQUE RIAÑO | Y285: Preventa | Z285: 80266801 | AA285: 1129520020 | AB285: SALSAMENTARIA LA LLANURA
A286: 45965 | B286: HHBO001170861 | C286: YAPANIAMA | D286: PAÑITOS HUMEDOS DAMPY AMARILLOS X 15 UND | E286: YAPANIAMA - PAÑITOS HUMEDOS DAMPY AMARILLOS X 15 UND | F286: 6 | G286: 1260.5 | H286: 0 | I286: 7563 | J286: BG25 | K286: 1 | L286: 126 | M286: TUTI Bogota | N286: ZONA BOGOTA | O286: TERCEROS | P286: 2025 SEM 45 | Q286: 2133 | R286: 919 | S286: martes | T286: YASS | U286: 1 | V286: 6 | W286: TAT | X286: DIANA JUDITH HERNANDEZ ROMERO | Y286: Preventa | Z286: 53043459 | AA286: 52290464 | AB286: CIGARRERIA LA AVENIDA
A287: 45965 | B287: HHBO001170861 | C287: LYESPOOROX12 | D287: LIMPIAYA ESPONJA ORO/PLATA X12 | E287: LYESPOOROX12 - LIMPIAYA ESPONJA ORO/PLATA X12 | F287: 1 | G287: 8991.6 | H287: 449.58 | I287: 8542.02 | J287: BG25 | K287: 1 | L287: 126 | M287: TUTI Bogota | N287: ZONA BOGOTA | O287: TERCEROS | P287: 2025 SEM 45 | Q287: 2133 | R287: 919 | S287: martes | T287: ETERNA | U287: 1 | V287: 1 | W287: TAT | X287: DIANA JUDITH HERNANDEZ ROMERO | Y287: Preventa | Z287: 53043459 | AA287: 52290464 | AB287: CIGARRERIA LA AVENIDA
A288: 45965 | B288: HHBO001170977 | C288: LYGUANT8NGX2 | D288: LIMPIAYA GUANTE NEGRO TALLA8 X2 | E288: LYGUANT8NGX2 - LIMPIAYA GUANTE NEGRO TALLA8 X2 | F288: 1 | G288: 3180 | H288: 0 | I288: 3180 | J288: BG25 | K288: 1 | L288: 2 | M288: CIUDAD BOGOTA | N288: ZONA BOGOTA | O288: TERCEROS | P288: 2025 SEM 45 | Q288: 2139 | R288: 921 | S288: martes | T288: ETERNA | U288: 1 | V288: 1 | W288: TAT | X288: WILMAR HERNANDO DURAN RAMIREZ | Y288: Preventa | Z288: 1024554969 | AA288: 1024507708 | AB288: LUXURY CARS
A289: 45965 | B289: HHME001460319 | C289: YAGOM90 | D289: GOMINA N17 EN SOBRE 90G | E289: YAGOM90 - GOMINA N17 EN SOBRE 90G | F289: 12 | G289: 1092.44 | H289: 0 | I289: 13109.28 | J289: TT02 | K289: 1 | L289: 125 | M289: TUTI Medellin | N289: ZONA CENTRO | O289: TERCEROS | P289: 2025 SEM 45 | Q289: 1321 | R289: 107 | S289: martes | T289: YASS | U289: 1 | V289: 12 | W289: TAT | X289: NANCY DEL SOCORRO RIOS HOYOS | Y289: Preventa | Z289: 42778189 | AA289: 1037949442 | AB289: EL PORTON
A290: 45965 | B290: HHME001460319 | C290: YAPANIAMA | D290: PAÑITOS HUMEDOS DAMPY AMARILLOS X 15 UND | E290: YAPANIAMA - PAÑITOS HUMEDOS DAMPY AMARILLOS X 15 UND | F290: 6 | G290: 1260.5 | H290: 0 | I290: 7563 | J290: TT02 | K290: 1 | L290: 125 | M290: TUTI Medellin | N290: ZONA CENTRO | O290: TERCEROS | P290: 2025 SEM 45 | Q290: 1321 | R290: 107 | S290: martes | T290: YASS | U290: 1 | V290: 6 | W290: TAT | X290: NANCY DEL SOCORRO RIOS HOYOS | Y290: Preventa | Z290: 42778189 | AA290: 1037949442 | AB290: EL PORTON
A291: 45965 | B291: HHBO001170988 | C291: LYDETE3X1800 | D291: COMBO DETERGENTE ETERNA 3.000+1.800 OFERTA | E291: LYDETE3X1800 - COMBO DETERGENTE ETERNA 3.000+1.800 OFERTA | F291: 1 | G291: 28655.46 | H291: 0 | I291: 28655.46 | J291: BG25 | K291: 1 | L291: 126 | M291: TUTI Bogota | N291: ZONA BOGOTA | O291: TERCEROS | P291: 2025 SEM 45 | Q291: 2139 | R291: 921 | S291: martes | T291: ETERNA | U291: 1 | V291: 1 | W291: TAT | X291: EDILBERTO BUESAQUILLO SACANAMBOY | Y291: Preventa | Z291: 12167006 | AA291: 1024507708 | AB291: FERRE ARON
A292: 45965 | B292: HHME001460336 | C292: KNLIMTEN | D292: LIMPIADOR DE TENNIS KNIGHT | E292: KNLIMTEN - LIMPIADOR DE TENNIS KNIGHT | F292: 3 | G292: 6350 | H292: 1905 | I292: 17145 | J292: MD04 | K292: 1 | L292: 125 | M292: TUTI Medellin | N292: ZONA CENTRO | O292: TERCEROS | P292: 2025 SEM 45 | Q292: 1310 | R292: 104 | S292: martes | T292: KNIGHT | U292: 1 | V292: 3 | W292: TAT | X292: DAYANA GONZALEZ CARDENAS | Y292: Preventa | Z292: 1037628075 | AA292: 71296053 | AB292: PAPELERIA SOL Y LUNA
... A396: 45966 | B396: HHME001460547 | C396: LYDESEN500 | D396: DESENGRASANTE CITRICO 500ML | E396: LYDESEN500 - DESENGRASANTE CITRICO 500ML | F396: 1 | G396: 2645.48 | H396: 0 | I396: 2645.48 | J396: MD04 | K396: 1 | L396: 125 | M396: TUTI Medellin | N396: ZONA CENTRO | O396: TERCEROS | P396: 2025 SEM 45 | Q396: 1310 | R396: 104 | S396: miércoles | T396: ETERNA | U396: 1 | V396: 1 | W396: TAT | X396: IMPORTACIONES Y FERRETERIA CONCREADOS SAS | Y396: Preventa | Z396: 901954979 | AA396: 71296053 | AB396: FERRETERIA CONCREADOS SAS
A397: 45966 | B397: HHME001460547 | C397: YALAPIZAMAX12 | D397: LAPIZ ESCOLAR AMARILLO X12 | E397: YALAPIZAMAX12 - LAPIZ ESCOLAR AMARILLO X12 | F397: 1 | G397: 4853 | H397: 0 | I397: 4853 | J397: MD04 | K397: 1 | L397: 125 | M397: TUTI Medellin | N397: ZONA CENTRO | O397: TERCEROS | P397: 2025 SEM 45 | Q397: 1310 | R397: 104 | S397: miércoles | T397: 0 | U397: 1 | V397: 1 | W397: TAT | X397: IMPORTACIONES Y FERRETERIA CONCREADOS SAS | Y397: Preventa | Z397: 901954979 | AA397: 71296053 | AB397: FERRETERIA CONCREADOS SAS
A398: 45966 | B398: HHME001460547 | C398: YALAPIROX12 | D398: LAPIZ ROJO X12 UND | E398: YALAPIROX12 - LAPIZ ROJO X12 UND | F398: 6 | G398: 4882 | H398: 0 | I398: 29292 | J398: MD04 | K398: 1 | L398: 125 | M398: TUTI Medellin | N398: ZONA CENTRO | O398: TERCEROS | P398: 2025 SEM 45 | Q398: 1310 | R398: 104 | S398: miércoles | T398: YASS | U398: 1 | V398: 6 | W398: TAT | X398: IMPORTACIONES Y FERRETERIA CONCREADOS SAS | Y398: Preventa | Z398: 901954979 | AA398: 71296053 | AB398: FERRETERIA CONCREADOS SAS
A399: 45966 | B399: HHME001460547 | C399: LYVIDR500X1 | D399: LIMPIAYA LIMPIAVIDRIOS MULTIUSOS 500ML X1 | E399: LYVIDR500X1 - LIMPIAYA LIMPIAVIDRIOS MULTIUSOS 500ML X1 | F399: 1 | G399: 2647.06 | H399: 0 | I399: 2647.06 | J399: MD04 | K399: 1 | L399: 125 | M399: TUTI Medellin | N399: ZONA CENTRO | O399: TERCEROS | P399: 2025 SEM 45 | Q399: 1310 | R399: 104 | S399: miércoles | T399: ETERNA | U399: 1 | V399: 1 | W399: TAT | X399: IMPORTACIONES Y FERRETERIA CONCREADOS SAS | Y399: Preventa | Z399: 901954979 | AA399: 71296053 | AB399: FERRETERIA CONCREADOS SAS
A400: 45966 | B400: HHBO001171208 | C400: LYGUANT7AMX2 | D400: LIMPIAYA GUATE TALLA7 AMARILLO X2 | E400: LYGUANT7AMX2 - LIMPIAYA GUATE TALLA7 AMARILLO X2 | F400: 12 | G400: 3025.21 | H400: 0 | I400: 36302.52 | J400: BG19 | K400: 1 | L400: 126 | M400: TUTI Bogota | N400: ZONA BOGOTA | O400: TERCEROS | P400: 2025 SEM 45 | Q400: 2190 | R400: 933 | S400: miércoles | T400: ETERNA | U400: 1 | V400: 12 | W400: TAT | X400: DEIBER TRIANA MONTAÑO | Y400: Preventa | Z400: 80739067 | AA400: 9902 | AB400: DEIVER TRIANA
A401: 45966 | B401: HHBO001171208 | C401: LYGUANT7.5AMX2 | D401: LIMPIAYA GUATE TALLA7.5 AMARILLO X2 | E401: LYGUANT7.5AMX2 - LIMPIAYA GUATE TALLA7.5 AMARILLO X2 | F401: 12 | G401: 3025.21 | H401: 0 | I401: 36302.52 | J401: BG19 | K401: 1 | L401: 126 | M401: TUTI Bogota | N401: ZONA BOGOTA | O401: TERCEROS | P401: 2025 SEM 45 | Q401: 2190 | R401: 933 | S401: miércoles | T401: ETERNA | U401: 1 | V401: 12 | W401: TAT | X401: DEIBER TRIANA MONTAÑO | Y401: Preventa | Z401: 80739067 | AA401: 9902 | AB401: DEIVER TRIANA
A402: 45966 | B402: HHBO001171208 | C402: LYGUANT8AMX2 | D402: LIMPIAYA GUANTE TALLA8 AMARILLO X2 | E402: LYGUANT8AMX2 - LIMPIAYA GUANTE TALLA8 AMARILLO X2 | F402: 12 | G402: 3025.21 | H402: 0 | I402: 36302.52 | J402: BG19 | K402: 1 | L402: 126 | M402: TUTI Bogota | N402: ZONA BOGOTA | O402: TERCEROS | P402: 2025 SEM 45 | Q402: 2190 | R402: 933 | S402: miércoles | T402: ETERNA | U402: 1 | V402: 12 | W402: TAT | X402: DEIBER TRIANA MONTAÑO | Y402: Preventa | Z402: 80739067 | AA402: 9902 | AB402: DEIVER TRIANA
A403: 45966 | B403: HHBO001171208 | C403: LYGUANT9AMX2 | D403: LIMPIAYA GUANTE TALLA9 AMARILLO X2 | E403: LYGUANT9AMX2 - LIMPIAYA GUANTE TALLA9 AMARILLO X2 | F403: 12 | G403: 3025.21 | H403: 0 | I403: 36302.52 | J403: BG19 | K403: 1 | L403: 126 | M403: TUTI Bogota | N403: ZONA BOGOTA | O403: TERCEROS | P403: 2025 SEM 45 | Q403: 2190 | R403: 933 | S403: miércoles | T403: ETERNA | U403: 1 | V403: 12 | W403: TAT | X403: DEIBER TRIANA MONTAÑO | Y403: Preventa | Z403: 80739067 | AA403: 9902 | AB403: DEIVER TRIANA
A404: 45966 | B404: HHBO001171208 | C404: LYGUANT8NGX2 | D404: LIMPIAYA GUANTE NEGRO TALLA8 X2 | E404: LYGUANT8NGX2 - LIMPIAYA GUANTE NEGRO TALLA8 X2 | F404: 6 | G404: 3180 | H404: 0 | I404: 19080 | J404: BG19 | K404: 1 | L404: 126 | M404: TUTI Bogota | N404: ZONA BOGOTA | O404: TERCEROS | P404: 2025 SEM 45 | Q404: 2190 | R404: 933 | S404: miércoles | T404: ETERNA | U404: 1 | V404: 6 | W404: TAT | X404: DEIBER TRIANA MONTAÑO | Y404: Preventa | Z404: 80739067 | AA404: 9902 | AB404: DEIVER TRIANA
A405: 45966 | B405: HHBO001171208 | C405: LYGUANT9NGX2 | D405: LIMPIAYA GUANTE NEGRO TALLA9 X2 | E405: LYGUANT9NGX2 - LIMPIAYA GUANTE NEGRO TALLA9 X2 | F405: 6 | G405: 3180 | H405: 0 | I405: 19080 | J405: BG19 | K405: 1 | L405: 126 | M405: TUTI Bogota | N405: ZONA BOGOTA | O405: TERCEROS | P405: 2025 SEM 45 | Q405: 2190 | R405: 933 | S405: miércoles | T405: ETERNA | U405: 1 | V405: 6 | W405: TAT | X405: DEIBER TRIANA MONTAÑO | Y405: Preventa | Z405: 80739067 | AA405: 9902 | AB405: DEIVER TRIANA
...

Sheet VENTA TERCEROS
A3: Etiquetas de fila | B3: Suma de Importe
A4: 102 | B4: 2196758.4
A5: 103 | B5: 2353365.8
A6: 104 | B6: 1157973.4
A7: 105 | B7: 1222388.4
A8: 107 | B8: 2368929.1
A9: 110 | B9: 1481362.1
A10: 111 | B10: 1123178
A11: 113 | B11: 1107858.1
A12: 114 | B12: 2319419.4
A13: 115 | B13: 918062.58
A14: 116 | B14: 381605.35
A15: 117 | B15: 1407771.9
... A58: 964 | B58: 259924.96
A59: (en blanco)
A60: 962 | B60: 27226.89
A61: 717 | B61: 83047.56
A62: 963 | B62: 18151.26
A63: NA | B63: 31890.058
A64: NA393 | B64: 4459632
A65: Total general | B65: 59126134

Sheet VENTAS DIARIAS
A3: Etiquetas de fila | B3: Suma de VALOR
A4: BARRANQUILLA | B4: 8477446
A5: BOGOTA | B5: 1.0471416e+08
A6: BUCARAMANGA | B6: 5520242.7
A7: CARTAGENA | B7: 9518644.9
A8: CUCUTA | B8: 6133455
A9: MEDELLIN | B9: 39305972
A10: MONTERIA | B10: 9597948.8
A11: PEREIRA | B11: 4385013.7
A12: VALLEDUPAR | B12: 5841956.6
A13: VILLAVICENCIO | B13: 42613562
A14: (en blanco)
A15: CALI | B15: 3220678.5
A16: Total general | B16: 2.3932908e+08

Sheet VENTAS POR VENDEDOR
A3: Etiquetas de fila | B3: Suma de VALOR
A4: 102 | B4: 2488032.7
A5: 103 | B5: 2817486.2
A6: 104 | B6: 12603370
A7: 105 | B7: 1956639.5
A8: 107 | B8: 6018575.7
A9: 110 | B9: 31932.916
A10: 111 | B10: 4359844.1
A11: 113 | B11: 1530633.1
A12: 114 | B12: 3095342.5
A13: 115 | B13: 1435139.7
A14: 116 | B14: 961643.3
A15: 117 | B15: 2007332.3
... A58: 964 | B58: 12882190
A59: (en blanco)
A60: 711 | B60: 33475.63
A61: 621 | B61: 26722.681
A62: Total general | B62: 2.3932908e+08

Sheet PEDIDOS POR VENDEDOR
D2: Etiquetas de fila | E2: Cuenta de PEDIDO TUTI
D3: 102 | E3: 91
D4: 103 | E4: 91
D5: 104 | E5: 139
D6: 105 | E6: 63
D7: 107 | E7: 140
D8: 110 | E8: 1
D9: 111 | E9: 68
B10: Etiquetas de fila | C10: Cuenta de VENDEDOR | D10: 113 | E10: 58
B11: BARRANQUILLA | C11: 158 | D11: 114 | E11: 81
B12: BOGOTA | C12: 1991 | D12: 115 | E12: 44
B13: BUCARAMANGA | C13: 126 | D13: 116 | E13: 32
B14: CARTAGENA | C14: 165 | D14: 117 | E14: 75
B15: CUCUTA | C15: 237 | D15: 405 | E15: 65
B16: MEDELLIN | C16: 881 | D16: 407 | E16: 29
B17: MONTERIA | C17: 172 | D17: 409 | E17: 89
B18: PEREIRA | C18: 69 | D18: 410 | E18: 27
B19: VALLEDUPAR | C19: 143 | D19: 411 | E19: 72
B20: VILLAVICENCIO | C20: 483 | D20: 413 | E20: 76
B21: (en blanco) | D21: 415 | E21: 9
B22: CALI | C22: 49 | D22: 509 | E22: 79
B23: Total general | C23: 4474 | D23: 510 | E23: 65
D24: 605 | E24: 55
D25: 612 | E25: 42
D26: 620 | E26: 48
D27: 705 | E27: 97
D28: 706 | E28: 46
D29: 712 | E29: 12
D30: 713 | E30: 46
D31: 714 | E31: 10
D32: 715 | E32: 25
D33: 717 | E33: 18
D34: 718 | E34: 147
D35: 720 | E35: 64
... D57: 964 | E57: 143
D58: (en blanco)
D59: 711 | E59: 1
D60: 621 | E60: 1
D61: Total general | E61: 4480

Sheet ENERO-25
A1: EJECUCIÓN MES
B3: DIAS CALENDARIO TRONEX | C3: DIAS TRANSCURRIDOS
A4: DIAS HABILES MES | B4: 15 | C4: 15
A6: GENERALES | B6: META MES | C6: ACUMULADO | D6: CUMPLIMIENTO | E6: VAR
A7: VENTAS | B7: 377404375 | C7: =407518760.260001/1.19 -> 3.4245274e+08 | D7: =+C7/B7 -> 0.90738943 | E7: =+C7/B7-1 -> -0.092610573
A8: PEDIDOS | B8: 6506.972 | C8: 6359 | D8: =+C8/B8 -> 0.97725947 | E8: =+C8/B8-1 -> -0.022740529
A9: TICKET PROMEDIO | B9: 58000 | C9: 64085.353 | D9: =+C9/B9 -> 1.1049199 | E9: =+C9/B9-1 -> 0.10491988
A10: CLIENTE | B10: 4972 | C10: 6099 | D10: =+C10/B10 -> 1.2266693 | E10: =+C10/B10-1 -> 0.22666935
A11: FRECUENCIA DE COMPRA | B11: 1.3 | C11: 1.0426299 | D11: =+C11/B11 -> 0.80202303 | E11: =+C11/B11-1 -> -0.19797697
B13: 2024 | C13: 2025 ACUMULADO ENERO/31 | D13: Var
A14: Ventas | B14: 280184625 | C14: 4.0751876e+08 | D14: 0.45446511
A15: Pedidos | B15: 4701 | C15: 6359 | D15: 0.35269092
A16: Ticket promedio | B16: 59601.069 | C16: 64085.353 | D16: 0.075238318
A17: Clientes | B17: 4446 | C17: 6099 | D17: 0.37179487
A18: Frecuencia de compra promedio | B18: 1.0573549 | C18: 1.0426299 | D18: -0.013926248
A20: EJECUCIÓN MES REGIONAL
B22: VENDEDORES | C22: % VENTA | D22: VENTA MES | E22: VENTAS X VENDEDOR | F22: VENTA ACUMULADA MES | G22: % VENTA MES | H22: PEDIDOS MES | I22: PEDIDOS X VENDEDOR | J22: PEDIDOS ACUMULADOS MES | K22: % PEDIDOS MES | L22: TICKET PROMEDIO ACUMULADO
A23: BOGOTA | B23: 19 | C23: 0.38 | D23: =+C23*$B$7 -> 1.4341366e+08 | E23: =+D23/B23 -> 7548087.5 | F23: 1.204757e+08 | G23: =+F23/$F$36 -> 0.29563228 | H23: 2472.6494 | I23: =+H23/B23 -> 130.13944 | J23: 2568 | K23: =+J23/$J$36 -> 0.40383708 | L23: =+F23/J23 -> 46914.214 | M23: 8.6759626
A24: MEDELLIN TAT | B24: 12 | C24: 0.265 | D24: =+C24*$B$7 -> 1.0001216e+08 | E24: =+D24/B24 -> 8334346.6 | F24: 96302922 | G24: =+F24/$F$36 -> 0.23631531 | H24: 1724.3476 | I24: =+H24/B24 -> 143.69563 | J24: 1010 | K24: =+J24/$J$36 -> 0.15883 | L24: =+F24/J24 -> 95349.428 | M24: 9.5797088
A25: MEDELLIN TUTI | B25: 2 | C25: 0.045 | D25: =+C25*$B$7 -> 16983197 | E25: =+D25/B25 -> 8491598.4 | F25: 30072320 | G25: =+F25/$F$36 -> 0.073793707 | H25: 292.81374 | I25: =+H25/B25 -> 146.40687 | J25: 486 | K25: =+J25/$J$36 -> 0.076427111 | L25: =+F25/J25 -> 61877.202 | M25: 9.760458
A26: VILLAVICENCIO | B26: 2 | C26: 0.04 | D26: =+C26*$B$7 -> 15096175 | E26: =+D26/B26 -> 7548087.5 | F26: 36059753 | G26: =+F26/$F$36 -> 0.088486119 | H26: 260.27888 | I26: =+H26/B26 -> 130.13944 | J26: 504 | K26: =+J26/$J$36 -> 0.079257745 | L26: =+F26/J26 -> 71547.13 | M26: 8.6759626
A27: CALI | B27: 2 | C27: 0.04 | D27: =+C27*$B$7 -> 15096175 | E27: =+D27/B27 -> 7548087.5 | F27: 31900625 | G27: =+F27/$F$36 -> 0.078280138 | H27: 260.27888 | I27: =+H27/B27 -> 130.13944 | J27: 412 | K27: =+J27/$J$36 -> 0.064790061 | L27: =+F27/J27 -> 77428.701 | M27: 8.6759626
A28: PEREIRA | B28: 2 | C28: 0.04 | D28: =+C28*$B$7 -> 15096175 | E28: =+D28/B28 -> 7548087.5 | F28: 4937720.1 | G28: =+F28/$F$36 -> 0.012116547 | H28: 260.27888 | I28: =+H28/B28 -> 130.13944 | J28: 55 | K28: =+J28/$J$36 -> 0.0086491587 | L28: =+F28/J28 -> 89776.729 | M28: 8.6759626
A29: BARRANQUILLA | B29: 6 | C29: 0.04 | D29: =+C29*$B$7 -> 15096175 | E29: =+D29/B29 -> 2516029.2 | F29: 9752581.3 | G29: =+F29/$F$36 -> 0.023931613 | H29: 260.27888 | I29: =+H29/B29 -> 43.379813 | J29: 98 | K29: =+J29/$J$36 -> 0.015411228 | L29: =+F29/J29 -> 99516.136 | M29: 2.8919875
A30: BUCARAMANGA | B30: 5 | C30: 0.04 | D30: =+C30*$B$7 -> 15096175 | E30: =+D30/B30 -> 3019235 | F30: 15350097 | G30: =+F30/$F$36 -> 0.037667215 | H30: 260.27888 | I30: =+H30/B30 -> 52.055776 | J30: 294 | K30: =+J30/$J$36 -> 0.046233685 | L30: =+F30/J30 -> 52211.214 | M30: 3.4703851
A31: CARTAGENA | B31: 2 | C31: 0.025 | D31: =+C31*$B$7 -> 9435109.4 | E31: =+D31/B31 -> 4717554.7 | F31: 15783374 | G31: =+F31/$F$36 -> 0.038730423 | H31: 162.6743 | I31: =+H31/B31 -> 81.33715 | J31: 229 | K31: =+J31/$J$36 -> 0.036011952 | L31: =+F31/J31 -> 68923.03 | M31: 5.4224767
A32: VALLEDUPAR | B32: 2 | C32: 0.02 | D32: =+C32*$B$7 -> 7548087.5 | E32: =+D32/B32 -> 3774043.8 | F32: 25830913 | G32: =+F32/$F$36 -> 0.063385825 | H32: 130.13944 | I32: =+H32/B32 -> 65.06972 | J32: 380 | K32: =+J32/$J$36 -> 0.059757824 | L32: =+F32/J32 -> 67976.087 | M32: 4.3379813
A33: CUCUTA | B33: 4 | C33: 0.03 | D33: =+C33*$B$7 -> 11322131 | E33: =+D33/B33 -> 2830532.8 | F33: 9227676.9 | G33: =+F33/$F$36 -> 0.022643563 | H33: 195.20916 | I33: =+H33/B33 -> 48.80229 | J33: 219 | K33: =+J33/$J$36 -> 0.034439377 | L33: =+F33/J33 -> 42135.511 | M33: 3.253486
A34: MONTERIA | B34: 2 | C34: 0.025 | D34: =+C34*$B$7 -> 9435109.4 | E34: =+D34/B34 -> 4717554.7 | F34: 10543105 | G34: =+F34/$F$36 -> 0.025871458 | H34: 162.6743 | I34: =+H34/B34 -> 81.33715 | J34: 84 | K34: =+J34/$J$36 -> 0.013209624 | L34: =+F34/J34 -> 125513.15 | M34: 5.4224767
A35: CLIENTE | B35: 0 | C35: 0.01 | D35: =+C35*$B$7 -> 3774043.8 | E35: =+D35/B35 -> #DIV/0! | F35: 1281972.4 | G35: =+F35/$F$36 -> 0.0031457996 | H35: 65.06972 | J35: 20 | K35: =+J35/$J$36 -> 0.0031451486 | L35: =+F35/J35 -> 64098.618 | M35: 0
A36: TOTAL | B36: =+B23+B24+B25+B26+B27+B28+B29+B30+B31+B32+B33+B34+B35 -> 60 | C36: =+C23+C24+C25+C26+C27+C28+C29+C30+C31+C32+C33+C34+C35 -> 1 | D36: =+D23+D24+D25+D26+D27+D28+D29+D30+D31+D32+D33+D34+D35 -> 377404375 | E36: =+D36/B36 -> 6290072.9 | F36: =+F23+F24+F25+F26+F27+F28+F29+F30+F31+F32+F33+F34+F35 -> 4.0751876e+08 | G36: 1 | H36: =+H23+H24+H25+H26+H27+H28+H29+H30+H31+H32+H33+H34+H35 -> 6506.972 | I36: =+I23+I24+I25+I26+I27+I28+I29+I30+I31+I32+I33+I34+I35 -> 1182.6422 | J36: =+J23+J24+J25+J26+J27+J28+J29+J30+J31+J32+J33+J34+J35 -> 6359 | K36: 1 | L36: =+F36/J36 -> 64085.353
B38: VENTA ENERO | C38: % VENTA | D38: CUMPL VENTA ENERO | E38: PEDIDO ENERO | F38: % PEDIDOS | G38: CUMPL PEDIDOS ENERO | H38: TICKET PROMEDIO
A39: MEDELLIN TAT | B39: =96302922/1.19 -> 80926825 | C39: =+B39/$B$52 -> 0.23631531 | D39: =+B39/D24 -> 0.80916986 | E39: =+J24 -> 1010 | F39: =+E39/$E$52 -> 0.15883 | G39: =+E39/H24 -> 0.58572878 | H39: =+B39/E39 -> 80125.57
A40: MEDELLIN TUTI | B40: =30072320/1.19 -> 25270857 | C40: =+B40/$B$52 -> 0.073793707 | D40: =+B40/D25 -> 1.4879918 | E40: =+J25 -> 486 | F40: =+E40/$E$52 -> 0.076427111 | G40: =+E40/H25 -> 1.6597582 | H40: =+B40/E40 -> 51997.648
A41: BOGOTA | B41: =120475701/1.19 -> 1.0124008e+08 | C41: =+B41/$B$52 -> 0.29563228 | D41: =+B41/D23 -> 0.70593054 | E41: =+J23 -> 2568 | F41: =+E41/$E$52 -> 0.40383708 | G41: =+E41/H23 -> 1.0385621 | H41: =+B41/E41 -> 39423.709
A42: VILLAVICENCIO | B42: =36059753/1.19 -> 30302313 | C42: =+B42/$B$52 -> 0.088486118 | D42: =+B42/D26 -> 2.0072842 | E42: =+J26 -> 504 | F42: =+E42/$E$52 -> 0.079257745 | G42: =+E42/H26 -> 1.9363845 | H42: =+B42/E42 -> 60123.638
A43: CALI | B43: =31900625/1.19 -> 26807248 | C43: =+B43/$B$52 -> 0.078280139 | D43: =+B43/D27 -> 1.7757643 | E43: =+J27 -> 412 | F43: =+E43/$E$52 -> 0.064790061 | G43: =+E43/H27 -> 1.5829175 | H43: =+B43/E43 -> 65066.136
A44: PEREIRA | B44: =+F28/1.19 -> 4149344.6 | C44: =+B44/$B$52 -> 0.012116547 | D44: =+B44/D28 -> 0.27486066 | E44: =+J28 -> 55 | F44: =+E44/$E$52 -> 0.0086491587 | G44: =+E44/H28 -> 0.21131181 | H44: =+B44/E44 -> 75442.63
A45: BARRANQUILLA | B45: =+F29/1.19 -> 8195446.5 | C45: =+B45/$B$52 -> 0.023931613 | D45: =+B45/D29 -> 0.54288232 | E45: =+J29 -> 98 | F45: =+E45/$E$52 -> 0.015411228 | G45: =+E45/H29 -> 0.37651922 | H45: =+B45/E45 -> 83627.005
A46: CARTAGENA | B46: =+F31/1.19 -> 13263339 | C46: =+B46/$B$52 -> 0.038730423 | D46: =+B46/D31 -> 1.405743 | E46: =+J31 -> 229 | F46: =+E46/$E$52 -> 0.036011952 | G46: =+E46/H31 -> 1.4077208 | H46: =+B46/E46 -> 57918.513
A47: VALLEDUPAR | B47: =+F32/1.19 -> 21706649 | C47: =+B47/$B$52 -> 0.063385825 | D47: =+B47/D32 -> 2.8757814 | E47: =+J32 -> 380 | F47: =+E47/$E$52 -> 0.059757824 | G47: =+E47/H32 -> 2.919945 | H47: =+B47/E47 -> 57122.762
A48: BUCARAMANGA | B48: =+F30/1.19 -> 12899241 | C48: =+B48/$B$52 -> 0.037667215 | D48: =+B48/D30 -> 0.85447082 | E48: =+J30 -> 294 | F48: =+E48/$E$52 -> 0.046233685 | G48: =+E48/H30 -> 1.1295577 | H48: =+B48/E48 -> 43874.97
A49: CUCUTA | B49: =+F33/1.19 -> 7754350.3 | C49: =+B49/$B$52 -> 0.022643563 | D49: =+B49/D33 -> 0.68488434 | E49: =+J33 -> 219 | F49: =+E49/$E$52 -> 0.034439377 | G49: =+E49/H33 -> 1.1218736 | H49: =+B49/E49 -> 35407.992
A50: MONTERIA | B50: =+F34/1.19 -> 8859751.8 | C50: =+B50/$B$52 -> 0.025871458 | D50: =+B50/D34 -> 0.93901951 | E50: =+J34 -> 84 | F50: =+E50/$E$52 -> 0.013209624 | G50: =+E50/H34 -> 0.51636921 | H50: =+B50/E50 -> 105473.24
A51: CLIENTE | B51: =+F35/1.19 -> 1077287.7 | C51: =+B51/$B$52 -> 0.0031457996 | D51: =+B51/D35 -> 0.28544653 | E51: =+J35 -> 20 | F51: =+E51/$E$52 -> 0.0031451486 | G51: =+E51/H35 -> 0.30736263 | H51: =+B51/E51 -> 53864.385
A52: TOTAL | B52: =+SUM(B39:B51) -> 3.4245274e+08 | C52: =+B52/$B$52 -> 1 | D52: =+B52/D36 -> 0.90738943 | E52: 6359 | F52: =+E52/$E$52 -> 1 | G52: =+E52/H36 -> 0.97725947 | H52: =+B52/E52 -> 53853.238
A54: EJECUCIÓN MES X VENDEDOR
A56: SUPERVISOR | B56: REGIONAL | C56: VENDEDOR | D56: META PEDIDOS MES | E56: PEDIDOS ACUMULADOS MES | F56: CUMPL PROY | G56: PEDIDOS DIARIOS
B57: VALLEDUPAR | C57: LILIANA BLANCO LOPEZ 705 VALLEDUPAR | D57: 65 | E57: 192 | F57: 2.9538462 | G57: 12.8 | H57: 12.8
B58: CARTAGENA | C58: NEIL TORRES 718 CARTAGENA | D58: 81 | E58: 192 | F58: 2.3703704 | G58: 12.8 | H58: 12.8
B59: VILLAVICENCIO | C59: CRISTIAN CAMILO HERRERA GUTIERREZ 906 | D59: 130 | E59: 306 | F59: 2.3538462 | G59: 20.4 | H59: 20.4
B60: BUCARAMANGA | C60: SANDRA PRADA 405 BUCARAMANGA | D60: 52 | E60: 121 | F60: 2.3269231 | G60: 8.0666667 | H60: 8.0666667
B61: VALLEDUPAR | C61: LILIANA MARCELA GONZALEZ PLATA 706 VALLEDUPAR | D61: 65 | E61: 151 | F61: 2.3230769 | G61: 10.066667 | H61: 10.066667
B62: MEDELLIN TUTI | C62: JULIAN ANDRES RIOS PEREZ (tuti) | D62: 146 | E62: 282 | F62: 1.9315068 | G62: 18.8 | H62: 18.8
B63: CUCUTA | C63: MAIRA TORRES 411 CUCUTA | D63: 49 | E63: 92 | F63: 1.877551 | G63: 6.1333333 | H63: 6.1333333
B64: BOGOTA | C64: MARIA NANCY GUARIN VIRGUEZ 937 | D64: 130 | E64: 239 | F64: 1.8384615 | G64: 15.933333 | H64: 15.933333
B65: CALI | C65: KATHERINE LOZANO MONTES 620 | D65: 130 | E65: 224 | F65: 1.7230769 | G65: 14.933333 | H65: 14.933333
B66: BOGOTA | C66: SANDRA PATRICIA ORTIZ ROMERO 919 | D66: 130 | E66: 202 | F66: 1.5538462 | G66: 13.466667 | H66: 13.466667
B67: VILLAVICENCIO | C67: ANGELICA CALVO 905 | D67: 130 | E67: 197 | F67: 1.5153846 | G67: 13.133333 | H67: 13.133333
B68: BOGOTA | C68: ANDRES CARPETA 936 | D68: 130 | E68: 196 | F68: 1.5076923 | G68: 13.066667 | H68: 13.066667
... B115: BARRANQUILLA | C115: JHON WILLIAM JIMENEZ CADENA 711 BARRANQUILLA | D115: 43 | E115: 0 | F115: 0 | G115: 0 | H115: 0

Sheet FEBRERO-25
A1: EJECUCIÓN MES
B3: DIAS CALENDARIO TRONEX | C3: DIAS TRANSCURRIDOS
A4: DIAS HABILES MES | B4: 20 | C4: 20
A6: GENERALES | B6: 2024 | C6: META MES | D6: ACUMULADO | E6: CUMPLIMIENTO | F6: CUMPL PROY | G6: Var
A7: VENTAS | B7: 364874472 | C7: 409705313 | D7: =583061587.720001/1.19 -> 4.8996772e+08 | E7: =+D7/C7 -> 1.1959028 | F7: =+D7/C7 -> 1.1959028 | G7: =+D7/B7-1 -> 0.34283914
A8: PEDIDOS | B8: 6379 | C8: 6303.1587 | D8: 10009 | E8: =+D8/C8 -> 1.587934 | F8: =+D8/C8 -> 1.587934 | G8: =+D8/B8-1 -> 0.56905471
A9: TICKET PROMEDIO | B9: 57199.322 | C9: 65000 | D9: 58253.73 | E9: =+D9/C9 -> 0.89621124 | F9: =+D9/C9 -> 0.89621124 | G9: =+D9/B9-1 -> 0.018433941
A10: CLIENTE | B10: 5790 | C10: 8194.1063 | D10: 8921 | E10: =+D10/C10 -> 1.0887093 | F10: =+D10/C10 -> 1.0887093 | G10: =+D10/B10-1 -> 0.54075993
A11: FRECUENCIA DE COMPRA | B11: =+B8/B10 -> 1.1017271 | C11: 1.3 | D11: 1.1219594 | E11: =+D11/C11 -> 0.86304571 | F11: =+D11/C11 -> 0.86304571 | G11: =+D11/B11-1 -> 0.018364172
A14: EJECUCIÓN MES REGIONAL
B16: VENDEDORES | C16: % VENTA | D16: VENTA MES | E16: VENTAS X VENDEDOR | F16: VENTA ACUMULADA MES | G16: % VENTA MES | H16: PEDIDOS MES | I16: PEDIDOS X VENDEDOR | J16: PEDIDOS ACUMULADOS MES | K16: % PEDIDOS MES | L16: TICKET PROMEDIO ACUMULADO
A17: BOGOTA | B17: 19 | C17: 0.38 | D17: 1.5568802e+08 | E17: 8194106.3 | F17: 1.9658891e+08 | G17: 0.33716662 | H17: =+C17*$C$8 -> 2395.2003 | I17: 126.06317 | J17: 4159 | K17: 0.41552603 | L17: 47268.311 | M17: 6.3031587 | O17: 33264304 | P17: =+O17/F17 -> 0.16920743
A18: MEDELLIN TAT | B18: 12 | C18: 0.265 | D18: 1.0857191e+08 | E18: 9047659 | F18: 1.3699651e+08 | G18: 0.23496061 | H18: =+C18*$C$8 -> 1670.337 | I18: 139.19475 | J18: 1955 | K18: 0.19532421 | L18: 70074.94 | M18: 6.9597377
A19: MEDELLIN TUTI | B19: 2 | C19: 0.045 | D19: 18436739 | E19: 9218369.5 | F19: 17911213 | G19: 0.030719247 | H19: =+C19*$C$8 -> 283.64214 | I19: 141.82107 | J19: 403 | K19: 0.040263763 | L19: 44444.697 | M19: 7.0910535
A20: VILLAVICENCIO | B20: 2 | C20: 0.04 | D20: 16388213 | E20: 8194106.3 | F20: 43508200 | G20: 0.074620248 | H20: =+C20*$C$8 -> 252.12635 | I20: 126.06317 | J20: 644 | K20: 0.064342092 | L20: 67559.317 | M20: 6.3031587
A21: CALI | B21: 2 | C21: 0.04 | D21: 16388213 | E21: 8194106.3 | F21: 35606134 | G21: 0.061067535 | H21: =+C21*$C$8 -> 252.12635 | I21: 126.06317 | J21: 552 | K21: 0.055150365 | L21: 64503.866 | M21: 6.3031587
A22: PEREIRA | B22: 2 | C22: 0.04 | D22: 16388213 | E22: 8194106.3 | F22: 8757058.7 | G22: 0.015019097 | H22: =+C22*$C$8 -> 252.12635 | I22: 126.06317 | J22: 117 | K22: 0.011689479 | L22: 74846.655 | M22: 6.3031587
A23: BARRANQUILLA | B23: 6 | C23: 0.04 | D23: 16388213 | E23: 2731368.8 | F23: 24975223 | G23: 0.042834622 | H23: =+C23*$C$8 -> 252.12635 | I23: 42.021058 | J23: 278 | K23: 0.027775002 | L23: 89838.93 | M23: 2.1010529
A24: CUCUTA | B24: 3 | C24: 0.03 | D24: 12291159 | E24: 4097053.1 | F24: 8569209.1 | G24: 0.014696919 | H24: =+C24*$C$8 -> 189.09476 | I24: 63.031587 | J24: 186 | K24: 0.018583275 | L24: 46071.017 | M24: 3.1515793
A25: CARTAGENA | B25: 2 | C25: 0.025 | D25: 10242633 | E25: 5121316.4 | F25: 27698596 | G25: 0.047505437 | H25: =+C25*$C$8 -> 157.57897 | I25: 78.789483 | J25: 422 | K25: 0.042162054 | L25: 65636.483 | M25: 3.9394742
A26: VALLEDUPAR | B26: 2 | C26: 0.02 | D26: 8194106.3 | E26: 4097053.1 | F26: 36861189 | G26: 0.063220061 | H26: =+C26*$C$8 -> 126.06317 | I26: 63.031587 | J26: 632 | K26: 0.063143171 | L26: 58324.667 | M26: 3.1515793
A27: BUCARAMANGA | B27: 4 | C27: 0.04 | D27: 16388213 | E27: 4097053.1 | F27: 26855651 | G27: 0.046059716 | H27: =+C27*$C$8 -> 252.12635 | I27: 63.031587 | J27: 486 | K27: 0.048556299 | L27: 55258.542 | M27: 3.1515793
A28: MONTERIA | B28: 2 | C28: 0.025 | D28: 10242633 | E28: 5121316.4 | F28: 17190575 | G28: 0.029483291 | H28: =+C28*$C$8 -> 157.57897 | I28: 78.789483 | J28: 162 | K28: 0.016185433 | L28: 106114.66 | M28: 3.9394742
A29: CLIENTE | B29: 0 | C29: 0.01 | D29: 4097053.1 | F29: 1543124.2 | G29: =+F29/F30 -> 0.0026465887 | H29: =+C29*$C$8 -> 63.031587 | I29: 0 | J29: 13 | K29: 0.0012988311 | L29: 118701.86 | M29: 0
A30: TOTAL | B30: =+B17+B18+B19+B20+B21+B22+B23+B24+B25+B26+B27+B28+B29 -> 58 | C30: =+C17+C18+C19+C20+C21+C22+C23+C24+C25+C26+C27+C28+C29 -> 1 | D30: 4.0970531e+08 | E30: 76307615 | F30: 5.8306159e+08 | G30: 1 | H30: 6303.1587 | I30: 1173.9633 | J30: 10009 | K30: 1 | L30: 58253.73
B32: VENTA FEBRERO | C32: % | D32: CUMPLIMIENTO | E32: PEDIDOS FEBRERO | F32: %PEDIDOS | G32: CUMPLIMIENTO PEDIDOS | H32: TICKET PROMEDIO
A33: MEDELLIN TAT | B33: =136996508.43/1.19 -> 1.1512312e+08 | C33: 0.23496061 | D33: 1.2618044 | E33: 1955 | F33: 0.19532421 | G33: 1.1704225 | H33: 70074.94
A34: MEDELLIN TUTI | B34: =17911212.86/1.19 -> 15051439 | C34: 0.030719247 | D34: 0.97149571 | E34: 403 | F34: 0.040263763 | G34: 1.4208044 | H34: 44444.697
A35: BOGOTA | B35: =196588906.45/1.19 -> 1.6520076e+08 | C35: 0.33716662 | D35: 1.2627106 | E35: 4159 | F35: 0.41552603 | G35: 1.7363892 | H35: 47268.311
A36: VILLAVICENCIO | B36: =43508200.0400001/1.19 -> 36561513 | C36: 0.074620248 | D36: 2.6548472 | E36: 644 | F36: 0.064342092 | G36: 2.5542749 | H36: 67559.317
A37: CALI | B37: =35606134.03/1.19 -> 29921121 | C37: 0.061067535 | D37: 2.1726673 | E37: 552 | F37: 0.055150365 | G37: 2.1893785 | H37: 64503.866
A38: PEREIRA | B38: =8757058.65/1.19 -> 7358872.8 | C38: 0.015019097 | D38: 0.53435106 | E38: 117 | F38: 0.011689479 | G38: 0.46405305 | H38: 74846.655
A39: BARRANQUILLA | B39: =24975222.6000001/1.19 -> 20987582 | C39: 0.042834622 | D39: 1.5239748 | E39: 278 | F39: 0.027775002 | G39: 1.1026218 | H39: 89838.93
A40: CARTAGENA | B40: =27698595.7600001/1.19 -> 23276131 | C40: 0.047505437 | D40: 2.7042457 | E40: 422 | F40: 0.042162054 | G40: 2.6780224 | H40: 65636.483
A41: VALLEDUPAR | B41: =36861189.4300001/1.19 -> 30975789 | C41: 0.063220061 | D41: 4.4985003 | E41: 632 | F41: 0.063143171 | G41: 5.0133594 | H41: 58324.667
A42: BUCARAMANGA | B42: =26855651.37/1.19 -> 22567774 | C42: 0.046059716 | D42: 1.6387175 | E42: 486 | F42: 0.048556299 | G42: 1.927605 | H42: 55258.542
A43: CUCUTA | B43: =8569209.15/1.19 -> 7201016.1 | C43: 0.014696919 | D43: 0.69718477 | E43: 186 | F43: 0.018583275 | G43: 0.98363381 | H43: 46071.017
A44: MONTERIA | B44: =17190574.73/1.19 -> 14445861 | C44: 0.029483291 | D44: 1.6783355 | E44: 162 | F44: 0.016185433 | G44: 1.028056 | H44: 106114.66
A45: CLIENTE | B45: =1543124.22/1.19 -> 1296743 | C45: 0.0026465887 | D45: 0.37664247 | E45: 13 | F45: 0.0012988311 | G45: 0.2062458 | H45: 118701.86
A46: TOTAL | B46: =583061587.720001/1.19 -> 4.8996772e+08 | C46: 1 | D46: 1.4231243 | E46: 10009 | F46: 1 | G46: 1.587934 | H46: 58253.73
A48: EJECUCIÓN MES X VENDEDOR
A50: SUPERVISOR | B50: REGIONAL | C50: VENDEDOR | D50: META PEDIDOS MES | E50: PEDIDOS ACUMULADOS MES | F50: CUMPL PROY | G50: PEDIDOS DIARIOS | H50: >
B51: BOGOTA | C51: SANDRA PATRICIA ORTIZ ROMERO 919 | D51: 126 | E51: 386 | F51: 3.0634921 | G51: 19.3 | H51: 19.3
B52: VILLAVICENCIO | C52: CRISTIAN CAMILO HERRERA GUTIERREZ 906 | D52: 126 | E52: 384 | F52: 3.047619 | G52: 19.2 | H52: 19.2
B53: BOGOTA | C53: MONICA RODRIGUEZ RONCANCIO 946 | D53: 126 | E53: 350 | F53: 2.7777778 | G53: 17.5 | H53: 17.5
B54: BOGOTA | C54: DIANA MARCELA DIAZ TORRES 938 | D54: 126 | E54: 341 | F54: 2.7063492 | G54: 17.05 | H54: 17.05
B55: VALLEDUPAR | C55: LILIANA MARCELA GONZALEZ PLATA 706 VALLEDUPAR | D55: 63 | E55: 330 | F55: 5.2380952 | G55: 16.5 | H55: 16.5
B56: CARTAGENA | C56: NEIL TORRES 718 CARTAGENA | D56: 79 | E56: 310 | F56: 3.9240506 | G56: 15.5 | H56: 15.5
B57: VALLEDUPAR | C57: LILIANA BLANCO LOPEZ 705 VALLEDUPAR | D57: 63 | E57: 302 | F57: 4.7936508 | G57: 15.1 | H57: 15.1
B58: BOGOTA | C58: MARIBEL REDONDO 918 | D58: 126 | E58: 289 | F58: 2.2936508 | G58: 14.45 | H58: 14.45
B59: BOGOTA | C59: MARIA NANCY GUARIN VIRGUEZ 937 | D59: 126 | E59: 289 | F59: 2.2936508 | G59: 14.45 | H59: 14.45
B60: CALI | C60: KATHERINE MAYA DELGADO 621 | D60: 126 | E60: 278 | F60: 2.2063492 | G60: 13.9 | H60: 13.9
B61: CALI | C61: KATHERINE LOZANO MONTES 620 | D61: 126 | E61: 274 | F61: 2.1746032 | G61: 13.7 | H61: 13.7
B62: VILLAVICENCIO | C62: ANGELICA CALVO 905 | D62: 126 | E62: 260 | F62: 2.0634921 | G62: 13 | H62: 13
... B108: BARRANQUILLA | C108: STHEFANY OJITO BARRANQUILLA 712 | D108: 42 | E108: 5 | F108: 0.11904762 | G108: 0.25 | H108: 0.25

Sheet MARZO-25
A1: EJECUCIÓN MES
B3: DIAS CALENDARIO TRONEX | C3: DIAS TRANSCURRIDOS
A4: DIAS HABILES MES | B4: 19 | C4: 19
A6: GENERALES | B6: 2024 | C6: META MES | D6: ACUMULADO | E6: CUMPLIMIENTO | F6: CUMPL PROY | G6: Var
A7: VENTAS | B7: 269027773 | C7: 385605000 | D7: =520044549.87/1.19 -> 4.3701223e+08 | E7: =+D7/C7 -> 1.1333158 | F7: =+D7/C7 -> 1.1333158 | G7: =+D7/B7-1 -> 0.62441306
A8: PEDIDOS | B8: 4924 | C8: 6426.75 | D8: 8927 | E8: =+D8/C8 -> 1.389038 | F8: =+D8/C8 -> 1.389038 | G8: =+D8/B8-1 -> 0.81295695
A9: TICKET PROMEDIO | B9: 54636.022 | C9: 60000 | D9: 58255.243 | E9: =+D9/C9 -> 0.97092071 | F9: =+D9/C9 -> 0.97092071 | G9: =+D9/B9-1 -> 0.066242384
A10: CLIENTE | B10: 4646 | C10: 7069.425 | D10: 7743 | E10: =+D10/C10 -> 1.09528 | F10: =+D10/C10 -> 1.09528 | G10: =+D10/B10-1 -> 0.66659492
A11: FRECUENCIA DE COMPRA | B11: =+B8/B10 -> 1.0598364 | C11: 1.1 | D11: 1.1 | E11: =+D11/C11 -> 1 | F11: =+D11/C11 -> 1 | G11: =+D11/B11-1 -> 0.037896019
A14: EJECUCIÓN MES REGIONAL
B16: VENDEDORES | C16: % VENTA | D16: VENTA MES | E16: VENTAS X VENDEDOR | F16: VENTA ACUMULADA MES | G16: % VENTA MES | H16: PEDIDOS MES | I16: PEDIDOS X VENDEDOR | J16: PEDIDOS ACUMULADOS MES | K16: % PEDIDOS MES | L16: TICKET PROMEDIO ACUMULADO
A17: BOGOTA | B17: 19 | C17: 0.38 | D17: 146529900 | E17: 7712100 | F17: 1.7776194e+08 | G17: 0.3418206 | H17: 2442.165 | I17: 128.535 | J17: 3830 | K17: 0.42903551 | L17: 46413.039 | N17: 6.765
A18: MEDELLIN | B18: 13 | C18: 0.31 | D18: 119537550 | E18: 9195196.2 | F18: 1.1387617e+08 | G18: 0.21897387 | H18: 1992.2925 | I18: 153.25327 | J18: 1530 | K18: 0.17139016 | L18: 74428.867 | N18: 8.0659615
A19: BARRANQUILLA | B19: 6 | C19: 0.04 | D19: 15424200 | E19: 2570700 | F19: 30213155 | G19: 0.058097244 | H19: 257.07 | I19: 42.845 | J19: 389 | K19: 0.043575669 | L19: 77668.78 | N19: 2.255
A20: BUCARAMANGA | B20: 4 | C20: 0.04 | D20: 15424200 | E20: 3856050 | F20: 32735315 | G20: 0.062947136 | H20: 257.07 | I20: 64.2675 | J20: 537 | K20: 0.060154587 | L20: 60959.619 | N20: 3.3825
A21: CUCUTA | B21: 3 | C21: 0.03 | D21: 11568150 | E21: 3856050 | F21: 8175163.2 | G21: 0.015720121 | H21: 192.8025 | I21: 64.2675 | J21: 197 | K21: 0.022067884 | L21: 41498.29 | N21: 3.3825
A22: VILLAVICENCIO | B22: 2 | C22: 0.04 | D22: 15424200 | E22: 7712100 | F22: 36953245 | G22: 0.071057844 | H22: 257.07 | I22: 128.535 | J22: 524 | K22: 0.058698331 | L22: 70521.459 | N22: 6.765
A23: CALI | B23: 2 | C23: 0.04 | D23: 15424200 | E23: 7712100 | F23: 48153699 | G23: 0.092595335 | H23: 257.07 | I23: 128.535 | J23: 704 | K23: 0.07886188 | L23: 68400.141 | N23: 6.765
A24: PEREIRA | B24: 2 | C24: 0.04 | D24: 15424200 | E24: 7712100 | F24: 13106506 | G24: 0.02520266 | H24: 257.07 | I24: 128.535 | J24: 226 | K24: 0.025316456 | L24: 57993.39 | N24: 6.765
A25: CARTAGENA | B25: 2 | C25: 0.025 | D25: 9640125 | E25: 4820062.5 | F25: 21306567 | G25: 0.040970657 | H25: 160.66875 | I25: 80.334375 | J25: 355 | K25: 0.039766999 | L25: 60018.498 | N25: 4.228125
A26: VALLEDUPAR | B26: 2 | C26: 0.02 | D26: 7712100 | E26: 3856050 | F26: 26692430 | G26: 0.051327198 | H26: 128.535 | I26: 64.2675 | J26: 503 | K26: 0.056345917 | L26: 53066.46 | N26: 3.3825
A27: MONTERIA | B27: 2 | C27: 0.025 | D27: 9640125 | E27: 4820062.5 | F27: 10104600 | G27: 0.019430259 | H27: 160.66875 | I27: 80.334375 | J27: 117 | K27: 0.013106307 | L27: 86364.106 | N27: 4.228125
A28: CLIENTE | B28: 0 | C28: 0.01 | D28: 3856050 | F28: 965764.17 | G28: 0.0018570797 | H28: 64.2675 | J28: 15 | K28: 0.0016802957 | L28: 64384.278 | N28: 0
A29: TOTAL | B29: 57 | C29: 1 | D29: 385605000 | E29: 63822571 | F29: 5.2004455e+08 | G29: 1 | H29: 6426.75 | I29: 1063.7095 | J29: 8927 | K29: 1 | L29: 58255.243
B31: VENTA MARZO | C31: % | D31: CUMPLIMIENTO PROYECTADO | E31: PEDIDOS PROYECTADOS | F31: %PEDIDOS | G31: CUMPLIMIENTO PROYECTADO | H31: TICKET PROMEDIO
A32: BOGOTA | B32: =177761938.27/1.19 -> 1.4937978e+08 | C32: 0.3418206 | D32: 1.2131445 | E32: 3830 | F32: 0.42903551 | G32: 1.5682806 | H32: 46413.039
A33: MEDELLIN | B33: =113876167.15/1.19 -> 95694258 | C33: 0.21897387 | D33: 0.95263929 | E33: 1530 | F33: 0.17139016 | G33: 0.76795952 | H33: 74428.867
A34: BARRANQUILLA | B34: =30213155.2800001/1.19 -> 25389206 | C34: 0.058097244 | D34: 1.9588151 | E34: 389 | F34: 0.043575669 | G34: 1.5132065 | H34: 77668.78
A35: BUCARAMANGA | B35: =32735315.25/1.19 -> 27508668 | C35: 0.062947136 | D35: 2.1223347 | E35: 537 | F35: 0.060154587 | G35: 2.0889252 | H35: 60959.619
A36: CUCUTA | B36: =8175163.19/1.19 -> 6869885 | C36: 0.015720121 | D36: 0.70669581 | E36: 197 | F36: 0.022067884 | G36: 1.021771 | H36: 41498.29
A37: VILLAVICENCIO | B37: =36953244.68/1.19 -> 31053147 | C37: 0.071057844 | D37: 2.3957965 | E37: 524 | F37: 0.058698331 | G37: 2.0383553 | H37: 70521.459
A38: CALI | B38: =48153699.24/1.19 -> 40465293 | C38: 0.092595335 | D38: 3.1219577 | E38: 704 | F38: 0.07886188 | G38: 2.7385537 | H38: 68400.141
A39: PEREIRA | B39: =13106506.05/1.19 -> 11013871 | C39: 0.02520266 | D39: 0.84973652 | E39: 226 | F39: 0.025316456 | G39: 0.87913798 | H39: 57993.39
A40: CARTAGENA | B40: =21306566.63/1.19 -> 17904678 | C40: 0.040970657 | D40: 2.2101961 | E40: 355 | F40: 0.039766999 | G40: 2.2095149 | H40: 60018.498
A41: VALLEDUPAR | B41: =26692429.5/1.19 -> 22430613 | C41: 0.051327198 | D41: 3.4611104 | E41: 503 | F41: 0.056345917 | G41: 3.913331 | H41: 53066.46
A42: MONTERIA | B42: =10104600.46/1.19 -> 8491260.9 | C42: 0.019430259 | D42: 1.0481815 | E42: 117 | F42: 0.013106307 | G42: 0.72820633 | H42: 86364.106
A43: CLIENTE | B43: =965764.17/1.19 -> 811566.53 | C43: 0.0018570797 | D43: 0.25045427 | E43: 15 | F43: 0.0016802957 | G43: 0.23339946 | H43: 64384.278
A44: TOTAL | B44: =+SUM(B32:B43) -> 4.3701223e+08 | C44: 1 | D44: 1.3486458 | E44: 8927 | F44: 1 | G44: 1.389038 | H44: 58255.243
A46: EJECUCIÓN MES X VENDEDOR
A48: SUPERVISOR | B48: REGIONAL | C48: VENDEDOR | D48: META PEDIDOS MES | E48: PEDIDOS ACUMULADOS MES | F48: VENTA ACUMULADA | G48: CUMPL PEDIDOS | H48: PEDIDOS DIARIOS | I48: >
B49: VALLEDUPAR | C49: LILIANA BLANCO LOPEZ 705 VALLEDUPAR | D49: 64.2675 | E49: 297 | F49: 15231215 | G49: 4.6213094 | H49: 15.631579 | I49: 15.631579
B50: VALLEDUPAR | C50: LILIANA MARCELA GONZALEZ PLATA 706 VALLEDUPAR | D50: 64.2675 | E50: 243 | F50: 13465133 | G50: 3.7810713 | H50: 12.789474 | I50: 12.789474
B51: BARRANQUILLA | C51: YOANY SARMIENTO PEREZ 713 BARRANQUILLA | D51: 42.845 | E51: 162 | F51: 12303134 | G51: 3.7810713 | H51: 8.5263158 | I51: 8.5263158
B52: CARTAGENA | C52: NEIL TORRES 718 CARTAGENA | D52: 80.334375 | E52: 288 | F52: 17414561 | G52: 3.5850158 | H52: 15.157895 | I52: 15.157895
B53: CALI | C53: KATHERINE LOZANO MONTES 620 | D53: 128.535 | E53: 420 | F53: 28881330 | G53: 3.2675925 | H53: 22.105263 | I53: 22.105263
B54: BOGOTA | C54: MONICA RODRIGUEZ RONCANCIO 946 | D54: 128.535 | E54: 404 | F54: 17119070 | G54: 3.1431128 | H54: 21.263158 | I54: 21.263158
B55: BUCARAMANGA | C55: YOHAN PITA 407 BUCARAMANGA | D55: 64.2675 | E55: 197 | F55: 12906216 | G55: 3.0653129 | H55: 10.368421 | I55: 10.368421
B56: BOGOTA | C56: SANDRA PATRICIA ORTIZ ROMERO 919 | D56: 128.535 | E56: 344 | F56: 15592274 | G56: 2.6763138 | H56: 18.105263 | I56: 18.105263
B57: VILLAVICENCIO | C57: CRISTIAN CAMILO HERRERA GUTIERREZ 906 | D57: 128.535 | E57: 330 | F57: 20761652 | G57: 2.5673941 | H57: 17.368421 | I57: 17.368421
B58: BARRANQUILLA | C58: JUAN RODRIGUEZ MURILLO 714 BARRANQUILLA | D58: 42.845 | E58: 98 | F58: 5392892.1 | G58: 2.2873147 | H58: 5.1578947 | I58: 5.1578947
B59: BOGOTA | C59: DIANA MARCELA DIAZ TORRES 938 | D59: 128.535 | E59: 293 | F59: 13954838 | G59: 2.2795348 | H59: 15.421053 | I59: 15.421053
B60: BOGOTA | C60: MARIBEL REDONDO 918 | D60: 128.535 | E60: 288 | F60: 15424097 | G60: 2.2406348 | H60: 15.157895 | I60: 15.157895
... B105: BARRANQUILLA | C105: JHON WILLIAM JIMENEZ CADENA 711 BARRANQUILLA | D105: 42.845 | E105: 3 | F105: 307191.07 | G105: 0.070019839 | H105: 0.15789474 | I105: 0.15789474

Sheet ABRIL-25 
A1: EJECUCIÓN MES
B3: DIAS CALENDARIO TRONEX | C3: DIAS TRANSCURRIDOS
A4: DIAS HABILES MES | B4: 18 | C4: 18
A6: GENERALES | B6: 2024 | C6: META MES | D6: ACUMULADO | E6: CUMPLIMIENTO | F6: CUMPL PROY | G6: Var
A7: VENTAS | B7: 280184624 | C7: 337404375 | D7: =455785325.390001/1.19 -> 3.8301288e+08 | E7: =+D7/C7 -> 1.1351746 | F7: =+D7/C7 -> 1.1351746 | G7: =+D7/C7-1 -> 0.13517461
A8: PEDIDOS | B8: 4701.0054 | C8: 5623.4062 | D8: 7740 | E8: =+D8/C8 -> 1.37639 | F8: =+D8/C8 -> 1.37639 | G8: =+D8/C8-1 -> 0.37638998
A9: TICKET PROMEDIO | B9: 59601 | C9: 60000 | D9: 58886.993 | E9: =+D9/C9 -> 0.98144988 | F9: =+D9/C9 -> 0.98144988 | G9: =+D9/C9-1 -> -0.018550118
A10: CLIENTE | B10: 4708 | C10: 6185.7469 | D10: 7007 | E10: =+D10/C10 -> 1.1327654 | F10: =+D10/C10 -> 1.1327654 | G10: =+D10/C10-1 -> 0.13276539
A11: FRECUENCIA DE COMPRA | B11: =+B8/B10 -> 0.99851432 | C11: 1.1 | D11: 1.1 | E11: =+D11/C11 -> 1 | F11: =+D11/C11 -> 1 | G11: =+D11/C11-1 -> 0
A14: EJECUCIÓN MES REGIONAL
B16: VENDEDORES | C16: % VENTA | D16: VENTA MES | E16: VENTAS X VENDEDOR | F16: VENTA ACUMULADA MES | G16: % VENTA MES | H16: PEDIDOS MES | I16: PEDIDOS X VENDEDOR | J16: PEDIDOS ACUMULADOS MES | K16: % PEDIDOS MES | L16: TICKET PROMEDIO ACUMULADO
A17: BOGOTA | B17: 19 | C17: 0.38 | D17: 1.2821366e+08 | E17: 6748087.5 | F17: 1.7002817e+08 | G17: 0.37304442 | H17: 2136.8944 | I17: 112.46812 | J17: 3512 | K17: 0.45374677 | L17: 48413.488 | N17: 6.2482292
A18: MEDELLIN | B18: 13 | C18: 0.31 | D18: 1.0459536e+08 | E18: 8045796.6 | F18: 84592031 | G18: 0.18559621 | H18: 1743.2559 | I18: 134.09661 | J18: 1423 | K18: 0.18385013 | L18: 59446.262 | N18: 7.4498117
A19: BARRANQUILLA | B19: 6 | C19: 0.055 | D19: 18557241 | E19: 3092873.4 | F19: 38831692 | G19: 0.085197328 | H19: 309.28734 | I19: 51.547891 | J19: 585 | K19: 0.075581395 | L19: 66378.96 | N19: 2.8637717
A20: BUCARAMANGA | B20: 4 | C20: 0.04 | D20: 13496175 | E20: 3374043.8 | F20: 23790737 | G20: 0.052197242 | H20: 224.93625 | I20: 56.234063 | J20: 405 | K20: 0.052325581 | L20: 58742.56 | N20: 3.1241146
A21: CUCUTA | B21: 3 | C21: 0.03 | D21: 10122131 | E21: 3374043.8 | F21: 5825686.6 | G21: 0.012781646 | H21: 168.70219 | I21: 56.234063 | J21: 149 | K21: 0.019250646 | L21: 39098.568 | N21: 3.1241146
A22: VILLAVICENCIO | B22: 2 | C22: 0.04 | D22: 13496175 | E22: 6748087.5 | F22: 57774110 | G22: 0.12675728 | H22: 224.93625 | I22: 112.46813 | J22: 657 | K22: 0.084883721 | L22: 87936.24 | N22: 6.2482292
A23: CALI | B23: 2 | C23: 0.04 | D23: 13496175 | E23: 6748087.5 | F23: 21742874 | G23: 0.047704199 | H23: 224.93625 | I23: 112.46813 | J23: 261 | K23: 0.03372093 | L23: 83306.03 | N23: 6.2482292
A24: PEREIRA | B24: 2 | C24: 0.04 | D24: 13496175 | E24: 6748087.5 | F24: 12875931 | G24: 0.028249989 | H24: 224.93625 | I24: 112.46813 | J24: 174 | K24: 0.02248062 | L24: 73999.601 | N24: 6.2482292
A25: CARTAGENA | B25: 2 | C25: 0.02 | D25: 6748087.5 | E25: 3374043.8 | F25: 14865351 | G25: 0.032614808 | H25: 112.46813 | I25: 56.234063 | J25: 174 | K25: 0.02248062 | L25: 85433.05 | N25: 3.1241146
A26: VALLEDUPAR | B26: 2 | C26: 0.02 | D26: 6748087.5 | E26: 3374043.8 | F26: 16627458 | G26: 0.036480899 | H26: 112.46813 | I26: 56.234063 | J26: 317 | K26: 0.040956072 | L26: 52452.55 | N26: 3.1241146
A27: MONTERIA | B27: 2 | C27: 0.015 | D27: 5061065.6 | E27: 2530532.8 | F27: 8002092.5 | G27: 0.017556714 | H27: 84.351094 | I27: 42.175547 | J27: 73 | K27: 0.0094315245 | L27: 109617.71 | N27: 2.3430859
A28: CLIENTE | B28: 0 | C28: 0.01 | D28: 3374043.8 | F28: 829192.35 | G28: 0.0018192607 | H28: 56.234063 | J28: 10 | K28: 0.0012919897 | L28: 82919.235 | N28: 0
A29: TOTAL | B29: 57 | C29: 1 | D29: 337404375 | E29: 54157728 | F29: 4.5578533e+08 | G29: 1 | H29: 5623.4062 | I29: 902.6288 | J29: 7740 | K29: 1 | L29: 58886.993
B31: VENTA ABRIL | C31: % | D31: CUMPLIMIENTO PROYECTADO | E31: PEDIDOS PROYECTADOS | F31: %PEDIDOS | G31: CUMPLIMIENTO PROYECTADO | H31: TICKET PROMEDIO
A32: BOGOTA | B32: =170028171.07/1.19 -> 1.4288082e+08 | C32: 0.37304442 | D32: 1.3261315 | E32: 3512 | F32: 0.45374677 | G32: 1.6435066 | H32: 48413.488
A33: MEDELLIN | B33: =84592031.01/1.19 -> 71085740 | C33: 0.18559621 | D33: 0.80875513 | E33: 1423 | F33: 0.18385013 | G33: 0.81628863 | H33: 59446.262
A34: BARRANQUILLA | B34: =38831691.6400002/1.19 -> 32631674 | C34: 0.085197328 | D34: 2.0925359 | E34: 585 | F34: 0.075581395 | G34: 1.891445 | H34: 66378.96
A35: BUCARAMANGA | B35: =23790736.98/1.19 -> 19992216 | C35: 0.052197242 | D35: 1.7627763 | E35: 405 | F35: 0.052325581 | G35: 1.8005101 | H35: 58742.56
A36: CUCUTA | B36: =5825686.64/1.19 -> 4895535 | C36: 0.012781646 | D36: 0.57553953 | E36: 149 | F36: 0.019250646 | G36: 0.88321321 | H36: 39098.568
A37: VILLAVICENCIO | B37: =57774109.7/1.19 -> 48549672 | C37: 0.12675728 | D37: 4.2807766 | E37: 657 | F37: 0.084883721 | G37: 2.9208276 | H37: 87936.24
A38: CALI | B38: =21742873.89/1.19 -> 18271323 | C38: 0.047704199 | D38: 1.6110397 | E38: 261 | F38: 0.03372093 | G38: 1.1603288 | H38: 83306.03
A39: PEREIRA | B39: =12875930.52/1.19 -> 10820110 | C39: 0.028249989 | D39: 0.95404294 | E39: 174 | F39: 0.02248062 | G39: 0.77355251 | H39: 73999.601
A40: CARTAGENA | B40: =14865350.69/1.19 -> 12491891 | C40: 0.032614808 | D40: 2.2028983 | E40: 174 | F40: 0.02248062 | G40: 1.547105 | H40: 85433.05
A41: VALLEDUPAR | B41: =16627458.42/1.19 -> 13972654 | C41: 0.036480899 | D41: 2.4640253 | E41: 317 | F41: 0.040956072 | G41: 2.8185764 | H41: 52452.55
A42: MONTERIA | B42: =8002092.48/1.19 -> 6724447.5 | C42: 0.017556714 | D42: 1.5811082 | E42: 73 | F42: 0.0094315245 | G42: 0.86543039 | H42: 109617.71
A43: CLIENTE | B43: =829192.35/1.19 -> 696800.29 | C43: 0.0018192607 | D43: 0.24575625 | E43: 10 | F43: 0.0012919897 | G43: 0.17782816 | H43: 82919.235
A44: TOTAL | B44: =+SUM(B32:B43) -> 3.8301288e+08 | C44: 1 | D44: 1.3508578 | E44: 7740 | F44: 1 | G44: 1.37639 | H44: 58886.993
A46: EJECUCIÓN MES X VENDEDOR
A48: SUPERVISOR | B48: REGIONAL | C48: VENDEDOR | D48: META PEDIDOS MES | E48: PEDIDOS ACUMULADOS MES | F48: VENTA ACUMULADA | G48: CUMPL PROY | H48: PEDIDOS DIARIOS | I48: >
B49: CARTAGENA | C49: NEIL TORRES 718 CARTAGENA | D49: 56.234063 | E49: 167 | F49: 13962898 | G49: 2.9697303 | H49: 9.2777778 | I49: 9.2777778
B50: BUCARAMANGA | C50: SANDRA PRADA 405 BUCARAMANGA | D50: 56.234063 | E50: 187 | F50: 11849337 | G50: 3.3253866 | H50: 10.388889 | I50: 10.388889
B51: BARRANQUILLA | C51: YOANY SARMIENTO PEREZ 713 BARRANQUILLA | D51: 51.547891 | E51: 153 | F51: 10975342 | G51: 2.9681137 | H51: 8.5 | I51: 8.5
B52: VILLAVICENCIO | C52: ANGELICA CALVO 905 | D52: 112.46813 | E52: 318 | F52: 31821943 | G52: 2.8274678 | H52: 17.666667 | I52: 17.666667
B53: VILLAVICENCIO | C53: CRISTIAN CAMILO HERRERA GUTIERREZ 906 | D53: 112.46813 | E53: 358 | F53: 27097044 | G53: 3.1831241 | H53: 19.888889 | I53: 19.888889
B54: BOGOTA | C54: DIANA MARCELA DIAZ TORRES 938 | D54: 112.46812 | E54: 318 | F54: 15101797 | G54: 2.8274678 | H54: 17.666667 | I54: 17.666667
B55: BOGOTA | C55: CRISTINA QUINTERO RUDAS 945 | D55: 112.46812 | E55: 274 | F55: 14569316 | G55: 2.4362458 | H55: 15.222222 | I55: 15.222222
B56: BUCARAMANGA | C56: YOHAN PITA 407 BUCARAMANGA | D56: 56.234063 | E56: 139 | F56: 7451876.7 | G56: 2.4718115 | H56: 7.7222222 | I56: 7.7222222
B57: BOGOTA | C57: MARIA NANCY GUARIN VIRGUEZ 937 | D57: 112.46812 | E57: 254 | F57: 14553981 | G57: 2.2584177 | H57: 14.111111 | I57: 14.111111
B58: CALI | C58: KATHERINE LOZANO MONTES 620 | D58: 112.46813 | E58: 261 | F58: 21742874 | G58: 2.3206575 | H58: 14.5 | I58: 14.5
B59: VALLEDUPAR | C59: LILIANA BLANCO LOPEZ 705 VALLEDUPAR | D59: 56.234063 | E59: 198 | F59: 10311371 | G59: 3.5209976 | H59: 11 | I59: 11
B60: BOGOTA | C60: LEYDY YURLEY MUNEVAR ESPITIA 921 | D60: 112.46812 | E60: 223 | F60: 13653637 | G60: 1.982784 | H60: 12.388889 | I60: 12.388889
... B104: MEDELLIN | C104: ALEJANDRA MONTOYA DAVID (tuti) | D104: 153 | E104: 9 | F104: 386375.15 | G104: 0.058823529 | H104: 0.5 | I104: 0.5

Sheet MAYO-25
A1: EJECUCIÓN MES
B3: DIAS CALENDARIO TRONEX | C3: DIAS TRANSCURRIDOS
A4: DIAS HABILES MES | B4: 20 | C4: 20
A6: GENERALES | B6: 2023 | C6: META MES | D6: ACUMULADO | E6: CUMPLIMIENTO | F6: CUMPLIMIENTO | G6: Var
A7: VENTAS | B7: 402585958 | C7: 409705313 | D7: =531266043.210001/1.19 -> 4.4644205e+08 | E7: =+D7/C7 -> 1.0896663 | F7: =+D7/C7 -> 1.0896663 | G7: =+D7/C7-1 -> 0.089666253
A8: PEDIDOS | B8: 7319.7447 | C8: 6828.4219 | D8: 8767 | E8: =+D8/C8 -> 1.2838984 | F8: =+D8/C8 -> 1.2838984 | G8: =+D8/C8-1 -> 0.28389841
A9: TICKET PROMEDIO | B9: 55000 | C9: 60000 | D9: 60598.385 | E9: =+D9/C9 -> 1.0099731 | F9: =+D9/C9 -> 1.0099731 | G9: =+D9/C9-1 -> 0.009973087
A10: CLIENTE | B10: 6476 | C10: 7511.2641 | D10: 7703 | E10: =+D10/C10 -> 1.0255265 | F10: =+D10/C10 -> 1.0255265 | G10: =+D10/C10-1 -> 0.025526453
A11: FRECUENCIA DE COMPRA | B11: =+B8/B10 -> 1.1302879 | C11: 1.1 | D11: 1.1 | E11: =+D11/C11 -> 1 | F11: =+D11/C11 -> 1 | G11: =+D11/C11-1 -> 0
A14: EJECUCIÓN MES REGIONAL
B16: VENDEDORES | C16: % VENTA | D16: VENTA MES | E16: VENTAS X VENDEDOR | F16: VENTA ACUMULADA MES | G16: % VENTA MES | H16: PEDIDOS MES | I16: PEDIDOS X VENDEDOR | J16: PEDIDOS ACUMULADOS MES | K16: % PEDIDOS MES | L16: TICKET PROMEDIO ACUMULADO
A17: BOGOTA | B17: 19 | C17: 0.38 | D17: 1.5568802e+08 | E17: 8194106.3 | F17: 1.9501207e+08 | G17: 0.36707046 | H17: 2594.8003 | I17: 136.56844 | J17: 3840 | K17: 0.43800616 | L17: 50784.393 | N17: 6.8284219
A18: MEDELLIN | B18: 13 | C18: 0.31 | D18: 1.2700865e+08 | E18: 9769895.9 | F18: 1.1957372e+08 | G18: 0.22507315 | H18: 2116.8108 | I18: 162.8316 | J18: 1688 | K18: 0.19254021 | L18: 70837.513 | N18: 8.1415799
A19: BARRANQUILLA | B19: 6 | C19: 0.055 | D19: 22533792 | E19: 3755632 | F19: 58433778 | G19: 0.10998967 | H19: 375.5632 | I19: 62.593867 | J19: 784 | K19: 0.089426258 | L19: 74532.88 | N19: 3.1296934
A20: BUCARAMANGA | B20: 4 | C20: 0.04 | D20: 16388213 | E20: 4097053.1 | F20: 21039349 | G20: 0.039602284 | H20: 273.13688 | I20: 68.284219 | J20: 387 | K20: 0.044142808 | L20: 54365.242 | N20: 3.4142109
A21: CUCUTA | B21: 3 | C21: 0.03 | D21: 12291159 | E21: 4097053.1 | F21: 7517020.8 | G21: 0.014149259 | H21: 204.85266 | I21: 68.284219 | J21: 179 | K21: 0.020417475 | L21: 41994.529 | N21: 3.4142109
A22: VILLAVICENCIO | B22: 2 | C22: 0.04 | D22: 16388213 | E22: 8194106.3 | F22: 51767733 | G22: 0.097442201 | H22: 273.13688 | I22: 136.56844 | J22: 725 | K22: 0.082696475 | L22: 71403.769 | N22: 6.8284219
A23: CALI | B23: 2 | C23: 0.04 | D23: 16388213 | E23: 8194106.3 | F23: 15439083 | G23: 0.029060926 | H23: 273.13688 | I23: 136.56844 | J23: 202 | K23: 0.023040949 | L23: 76431.104 | N23: 6.8284219
A24: PEREIRA | B24: 2 | C24: 0.04 | D24: 16388213 | E24: 8194106.3 | F24: 13804010 | G24: 0.025983234 | H24: 273.13688 | I24: 136.56844 | J24: 210 | K24: 0.023953462 | L24: 65733.381 | N24: 6.8284219
A25: CARTAGENA | B25: 2 | C25: 0.02 | D25: 8194106.3 | E25: 4097053.1 | F25: 11016383 | G25: 0.020736095 | H25: 136.56844 | I25: 68.284219 | J25: 182 | K25: 0.020759667 | L25: 60529.577 | N25: 3.4142109
A26: VALLEDUPAR | B26: 2 | C26: 0.02 | D26: 8194106.3 | E26: 4097053.1 | F26: 22895353 | G26: 0.043095833 | H26: 136.56844 | I26: 68.284219 | J26: 417 | K26: 0.047564731 | L26: 54904.923 | N26: 3.4142109
A27: MONTERIA | B27: 2 | C27: 0.015 | D27: 6145579.7 | E27: 3072789.8 | F27: 13542406 | G27: 0.025490817 | H27: 102.42633 | I27: 51.213164 | J27: 142 | K27: 0.016197103 | L27: 95369.054 | N27: 2.5606582
A28: CLIENTE | B28: 0 | C28: 0.01 | D28: 4097053.1 | F28: 1225136.6 | G28: 0.0023060698 | H28: 68.284219 | J28: 11 | K28: 0.0012547051 | L28: 111376.05 | N28: 0
A29: TOTAL | B29: 57 | C29: 1 | D29: 4.0970531e+08 | E29: 65762955 | F29: 5.3126604e+08 | G29: 1 | H29: 6828.4219 | I29: 1096.0493 | J29: 8767 | K29: 1 | L29: 60598.385
B31: VENTA MAYO | C31: % | D31: CUMPLIMIENTO | E31: PEDIDOS PROYECTADOS | F31: %PEDIDOS | G31: CUMPLIMIENTO PROYECTADO | H31: TICKET PROMEDIO
A32: BOGOTA | B32: =195012070.280001/1.19 -> 1.6387569e+08 | C32: 0.36707046 | D32: 1.2525824 | E32: 3840 | F32: 0.43800616 | G32: 1.4798827 | H32: 50784.393
A33: MEDELLIN | B33: =119573721.9/1.19 -> 1.0048212e+08 | C33: 0.22507315 | D33: 0.94146127 | E33: 1688 | F33: 0.19254021 | G33: 0.79742602 | H33: 70837.513
A34: BARRANQUILLA | B34: =58433778.09/1.19 -> 49104015 | C34: 0.10998967 | D34: 2.5931622 | E34: 784 | F34: 0.089426258 | G34: 2.0875315 | H34: 74532.88
A35: BUCARAMANGA | B35: =21039348.52/1.19 -> 17680125 | C35: 0.039602284 | D35: 1.2838098 | E35: 387 | F35: 0.044142808 | G35: 1.416872 | H35: 54365.242
A36: CUCUTA | B36: =7517020.76/1.19 -> 6316824.2 | C36: 0.014149259 | D36: 0.61157947 | E36: 179 | F36: 0.020417475 | G36: 0.87379877 | H36: 41994.529
A37: VILLAVICENCIO | B37: =51767732.59/1.19 -> 43502296 | C37: 0.097442201 | D37: 3.1588395 | E37: 725 | F37: 0.082696475 | G37: 2.6543468 | H37: 71403.769
A38: CALI | B38: =15439083.08/1.19 -> 12974019 | C38: 0.029060926 | D38: 0.94208463 | E38: 202 | F38: 0.023040949 | G38: 0.73955595 | H38: 76431.104
A39: PEREIRA | B39: =13804010.02/1.19 -> 11600008 | C39: 0.025983234 | D39: 0.84231334 | E39: 210 | F39: 0.023953462 | G39: 0.76884529 | H39: 65733.381
A40: CARTAGENA | B40: =11016382.97/1.19 -> 9257464.7 | C40: 0.020736095 | D40: 1.3444276 | E40: 182 | F40: 0.020759667 | G40: 1.3326652 | H40: 60529.577
A41: VALLEDUPAR | B41: =22895352.7300001/1.19 -> 19239792 | C41: 0.043095833 | D41: 2.7941245 | E41: 417 | F41: 0.047564731 | G41: 3.0534141 | H41: 54904.923
A42: MONTERIA | B42: =13542405.71/1.19 -> 11380173 | C42: 0.025490817 | D42: 2.203601 | E42: 142 | F42: 0.016197103 | G42: 1.3863623 | H42: 95369.054
A43: CLIENTE | B43: =1225136.56/1.19 -> 1029526.5 | C43: 0.0023060698 | D43: 0.29902872 | E43: 11 | F43: 0.0012547051 | G43: 0.16109139 | H43: 111376.05
A44: TOTAL | B44: =+SUM(B32:B43) -> 4.4644205e+08 | C44: 1 | D44: 1.2967028 | E44: 8767 | F44: 1 | G44: 1.2838984 | H44: 60598.385
A46: EJECUCIÓN MES X VENDEDOR
A48: SUPERVISOR | B48: REGIONAL | C48: VENDEDOR | D48: META PEDIDOS MES | E48: PEDIDO MAYO | F48: VENTA MAYO | G48: CUMPL PEDIDOS MAYO | H48: CUMPL PROY VENTAS
B49: CARTAGENA | C49: CESAR EDUARDO ATENCIO BERMUDEZ 717 CARTAGENA | D49: 68.284219 | E49: #N/A | F49: #N/A | G49: #N/A
B50: BARRANQUILLA | C50: YOANY SARMIENTO PEREZ 713 BARRANQUILLA | D50: 62.593867 | E50: 224 | F50: 17692256 | G50: 3.5786253
B51: BARRANQUILLA | C51: ALVARO ENRIQUE CASTAÑEDA MANJARRES 715 BARRANQUILLA | D51: 62.593867 | E51: 104 | F51: 13151021 | G51: 1.6615046
B52: BUCARAMANGA | C52: SANDRA PRADA 405 BUCARAMANGA | D52: 68.284219 | E52: 144 | F52: 8991670.6 | G52: 2.1088328
B53: VILLAVICENCIO | C53: ANGELICA CALVO 905 | D53: 136.56844 | E53: 339 | F53: 28842269 | G53: 2.4822719
B54: VILLAVICENCIO | C54: CRISTIAN CAMILO HERRERA GUTIERREZ 906 | D54: 136.56844 | E54: 386 | F54: 22925464 | G54: 2.8264217
B55: VALLEDUPAR | C55: LILIANA BLANCO LOPEZ 705 VALLEDUPAR | D55: 68.284219 | E55: 251 | F55: 13060113 | G55: 3.6758127
B56: BARRANQUILLA | C56: WILLIAM ALFONSO SARMIENTO ARROYO 720 BARRANQUILLA | D56: 62.593867 | E56: 183 | F56: 11021787 | G56: 2.9236091
B57: CARTAGENA | C57: NEIL TORRES 718 CARTAGENA | D57: 68.284219 | E57: 182 | F57: 11016383 | G57: 2.6653303
B58: BOGOTA | C58: LEYDY YURLEY MUNEVAR ESPITIA 921 | D58: 136.56844 | E58: 230 | F58: 14519893 | G58: 1.6841373
B59: BOGOTA | C59: SANDRA PATRICIA ORTIZ ROMERO 919 | D59: 136.56844 | E59: 332 | F59: 14390662 | G59: 2.4310156
B60: VALLEDUPAR | C60: LILIANA MARCELA GONZALEZ PLATA 706 VALLEDUPAR | D60: 68.284219 | E60: 180 | F60: 10580040 | G60: 2.636041
B61: BOGOTA | C61: DIANA MARCELA DIAZ TORRES 938 | D61: 136.56844 | E61: 295 | F61: 14018604 | G61: 2.1600891
... B104: BARRANQUILLA | C104: JHON WILLIAM JIMENEZ CADENA 711 BARRANQUILLA | D104: 62.593867 | E104: 3 | F104: 332575.69 | G104: 0.047928018

Sheet JUNIO-25
A1: EJECUCIÓN MES
B3: DIAS CALENDARIO TRONEX | C3: DIAS TRANSCURRIDOS
A4: DIAS HABILES MES | B4: 18 | C4: 18
A6: GENERALES | B6: 2023 | C6: META MES | D6: ACUMULADO | E6: CUMPLIMIENTO | F6: CUMPL | G6: Var
A7: VENTAS | B7: 351424111 | C7: 485605000 | D7: =+F29 -> 3.6271586e+08 | E7: =+D7/C7 -> 0.74693601 | F7: =+D7/C7 -> 0.74693601 | G7: =+D7/B7-1 -> 0.032131403
A8: PEDIDOS | B8: 6083 | C8: 8093.4167 | D8: 7690 | E8: =+D8/C8 -> 0.95015496 | F8: =+D8/C8 -> 0.95015496 | G8: =+D8/B8-1 -> 0.26417886
A9: TICKET PROMEDIO | B9: 57771.513 | C9: 60000 | D9: 56128.982 | E9: =+D9/C9 -> 0.93548304 | F9: =+D9/C9 -> 0.93548304 | G9: =+D9/B9-1 -> -0.028431491
A10: CLIENTE | B10: 5486 | C10: 8902.7583 | D10: 6792 | E10: =+D10/C10 -> 0.76290962 | F10: =+D10/C10 -> 0.76290962 | G10: =+D10/B10-1 -> 0.23806052
A11: FRECUENCIA DE COMPRA | B11: =+B8/B10 -> 1.1088225 | C11: 1.1 | D11: 1.1 | E11: =+D11/C11 -> 1 | F11: =+D11/C11 -> 1 | G11: =+D11/B11-1 -> -0.0079566004
A14: EJECUCIÓN MES REGIONAL
F15: 1.19
B16: VENDEDORES | C16: % VENTA | D16: VENTA MES | E16: VENTAS X VENDEDOR | F16: VENTA ACUMULADA MES | G16: % VENTA MES | H16: PEDIDOS MES | I16: PEDIDOS X VENDEDOR | J16: PEDIDOS ACUMULADOS MES | K16: % PEDIDOS MES
A17: BOGOTA | B17: 19 | C17: 0.39 | D17: 189385950 | E17: 9967681.6 | F17: =162113860.31/1.19 -> 1.3623013e+08 | G17: 0.37558362 | H17: 3156.4325 | I17: 166.12803 | J17: 3412 | K17: 0.44369311
A18: MEDELLIN | B18: 12 | C18: 0.3 | D18: 145681500 | E18: 12140125 | F18: =87653035.89/1.19 -> 73658013 | G18: 0.20307359 | H18: 2428.025 | I18: 202.33542 | J18: 1473 | K18: 0.19154746
A19: BARRANQUILLA | B19: 6 | C19: 0.06 | D19: 29136300 | E19: 4856050 | F19: =54471448.94/1.19 -> 45774327 | G19: 0.12619886 | H19: 485.605 | I19: 80.934167 | J19: 735 | K19: 0.095578674
A20: BUCARAMANGA | B20: 4 | C20: 0.05 | D20: 24280250 | E20: 6070062.5 | F20: =15996274.72/1.19 -> 13442248 | G20: 0.037059994 | H20: 404.67083 | I20: 101.16771 | J20: 352 | K20: 0.045773732
A21: CUCUTA | B21: 3 | C21: 0.03 | D21: 14568150 | E21: 4856050 | F21: =7579890/1.19 -> 6369655.5 | G21: 0.017561006 | H21: 242.8025 | I21: 80.934167 | J21: 175 | K21: 0.022756827
A22: VILLAVICENCIO | B22: 2 | C22: 0.06 | D22: 29136300 | E22: 14568150 | F22: =53554081.07/1.19 -> 45003429 | G22: 0.12407351 | H22: 485.605 | I22: 242.8025 | J22: 743 | K22: 0.096618986
A23: CALI | B23: 1 | C23: 0.01 | D23: 4856050 | E23: 4856050 | F23: =4135544.12/1.19 -> 3475247.2 | G23: 0.0095811833 | H23: 80.934167 | I23: 80.934167 | J23: 56 | K23: 0.0072821847
A24: PEREIRA | B24: 2 | C24: 0.03 | D24: 14568150 | E24: 7284075 | F24: =12411460.05/1.19 -> 10429798 | G24: 0.028754735 | H24: 242.8025 | I24: 121.40125 | J24: 187 | K24: 0.024317295
A25: CARTAGENA | B25: 1 | C25: 0.01 | D25: 4856050 | E25: 4856050 | F25: =8105034.43999999/1.19 -> 6810953.3 | G25: 0.018777655 | H25: 80.934167 | I25: 80.934167 | J25: 142 | K25: 0.01846554
A26: VALLEDUPAR | B26: 2 | C26: 0.03 | D26: 14568150 | E26: 7284075 | F26: =11740197.57/1.19 -> 9865712.2 | G26: 0.027199561 | H26: 242.8025 | I26: 121.40125 | J26: 243 | K26: 0.03159948
A27: MONTERIA | B27: 2 | C27: 0.02 | D27: 9712100 | E27: 4856050 | F27: =13036238.27/1.19 -> 10954822 | G27: 0.030202214 | H27: 161.86833 | I27: 80.934167 | J27: 163 | K27: 0.021196359
A28: CLIENTE | B28: 0 | C28: 0.01 | D28: 4856050 | F28: =834808.91/1.19 -> 701520.09 | G28: 0.0019340761 | H28: 80.934167 | J28: 9 | K28: 0.0011703511
A29: TOTAL | B29: 54 | C29: 1 | D29: 485605000 | E29: 81594419 | F29: =+SUM(F17:F28) -> 3.6271586e+08 | G29: 1 | H29: 8093.4167 | I29: 1359.907 | J29: 7690 | K29: 1
B31: VENTA | C31: % | D31: CUMPL VENTA | E31: PEDIDOS JUNIO | F31: %PEDIDOS | G31: CUMPLPEDIDOS | H31: TICKET PROMEDIO
A32: BOGOTA | B32: =162113860.31/1.19 -> 1.3623013e+08 | C32: 0.37558362 | D32: 0.85599729 | E32: 3412 | F32: 0.44369311 | G32: 1.0809672 | H32: 47512.855
A33: MEDELLIN | B33: =87653035.89/1.19 -> 73658013 | C33: 0.20307359 | D33: 0.60167582 | E33: 1473 | F33: 0.19154746 | G33: 0.60666591 | H33: 59506.474
A34: BARRANQUILLA | B34: =54471448.94/1.19 -> 45774327 | C34: 0.12619886 | D34: 1.869539 | E34: 735 | F34: 0.095578674 | G34: 1.5135758 | H34: 74110.815
A35: BUCARAMANGA | B35: =15996274.72/1.19 -> 13442248 | C35: 0.037059994 | D35: 0.65881837 | E35: 352 | F35: 0.045773732 | G35: 0.86984277 | H35: 45443.962
A36: CUCUTA | B36: =7579890/1.19 -> 6369655.5 | C36: 0.017561006 | D36: 0.5203056 | E36: 175 | F36: 0.022756827 | G36: 0.7207504 | H36: 43313.657
A37: VILLAVICENCIO | B37: =53554081.07/1.19 -> 45003429 | C37: 0.12407351 | D37: 1.8380536 | E37: 743 | F37: 0.096618986 | G37: 1.5300501 | H37: 72078.171
A38: CALI | B38: =4135544.12/1.19 -> 3475247.2 | C38: 0.0095811833 | D38: 0.85162717 | E38: 56 | F38: 0.0072821847 | G38: 0.69192039 | H38: 73849.002
A39: PEREIRA | B39: =12411460.05/1.19 -> 10429798 | C39: 0.028754735 | D39: 0.85195856 | E39: 187 | F39: 0.024317295 | G39: 0.77017329 | H39: 66371.444
A40: CARTAGENA | B40: =8105034.44/1.19 -> 6810953.3 | C40: 0.018777655 | D40: 1.6690591 | E40: 142 | F40: 0.01846554 | G40: 1.7545124 | H40: 57077.707
A41: VALLEDUPAR | B41: =11740197.57/1.19 -> 9865712.2 | C41: 0.027199561 | D41: 0.80588116 | E41: 243 | F41: 0.03159948 | G41: 1.0008134 | H41: 48313.57
A42: MONTERIA | B42: =13036238.27/1.19 -> 10954822 | C42: 0.030202214 | D42: 1.3422677 | E42: 163 | F42: 0.021196359 | G42: 1.0069913 | H42: 79976.922
A43: CLIENTE | B43: =834808.91/1.19 -> 701520.09 | C43: 0.0019340761 | D43: 0.1719111 | E43: 9 | F43: 0.0011703511 | G43: 0.11120149 | H43: 92756.546
A44: TOTAL | B44: =+SUM(B32:B43) -> 3.6271586e+08 | C44: 1 | D44: 0.88885385 | E44: 7690 | F44: 1 | G44: 0.95015496 | H44: 56128.982
A46: EJECUCIÓN MES X VENDEDOR
A48: SUPERVISOR | B48: REGIONAL | C48: VENDEDOR | D48: META PEDIDOS MES | E48: PEDIDOS JUNIO | F48: VENTA JUNIO | G48: CUMPL PEDIDOS JUNIO | H48: CUMPL PROY VENTAS
B49: BARRANQUILLA | C49: STHEFANY OJITO BARRANQUILLA 712 | D49: 80.934167 | E49: 156 | F49: 11694880 | G49: 1.9274925
B50: BARRANQUILLA | C50: YOANY SARMIENTO PEREZ 713 BARRANQUILLA | D50: 80.934167 | E50: 152 | F50: 10237645 | G50: 1.8780696
B51: BUCARAMANGA | C51: YOHAN PITA 407 BUCARAMANGA | D51: 101.16771 | E51: 178 | F51: 6716817 | G51: 1.7594547
B52: CARTAGENA | C52: NEIL TORRES 718 CARTAGENA | D52: 80.934167 | E52: 142 | F52: 8105034.4 | G52: 1.7545124
B53: BOGOTA | C53: CRISTINA QUINTERO RUDAS 945 | D53: 166.12803 | E53: 284 | F53: 15283163 | G53: 1.7095249
B54: BARRANQUILLA | C54: ALVARO ENRIQUE CASTAÑEDA MANJARRES 715 BARRANQUILLA | D54: 80.934167 | E54: 137 | F54: 12485307 | G54: 1.6927338
B55: VILLAVICENCIO | C55: CRISTIAN CAMILO HERRERA GUTIERREZ 906 | D55: 242.8025 | E55: 397 | F55: 26029946 | G55: 1.6350738
B56: VILLAVICENCIO | C56: ANGELICA CALVO 905 | D56: 242.8025 | E56: 346 | F56: 27524135 | G56: 1.4250265
B57: VALLEDUPAR | C57: LILIANA BLANCO LOPEZ 705 VALLEDUPAR | D57: 121.40125 | E57: 172 | F57: 7717938 | G57: 1.4167894
B58: BOGOTA | C58: SANDRA PATRICIA ORTIZ ROMERO 919 | D58: 166.12803 | E58: 229 | F58: 8817503.8 | G58: 1.3784549
B59: MONTERIA | C59: JOSE GREGORIO OSTEN MERCADO 509 | D59: 80.934167 | E59: 111 | F59: 7836761.6 | G59: 1.3714851
B60: BOGOTA | C60: LEYDY YURLEY MUNEVAR ESPITIA 921 | D60: 166.12803 | E60: 226 | F60: 13086663 | G60: 1.3603966
... B100: MEDELLIN | C100: MIGUEL ANGEL HIDALGO SANTOS 113 | D100: 202.33542 | E100: 87 | F100: 3077427.4 | G100: 0.4299791

Sheet JULIO-25  
A1: EJECUCIÓN MES
B3: DIAS CALENDARIO TRONEX | C3: DIAS TRANSCURRIDOS
A4: DIAS HABILES MES | B4: 24 | C4: 24
A6: GENERALES | B6: 2023 | C6: META MES | D6: ACUMULADO | E6: CUMPLIMIENTO | F6: CUMPLIMIENTO | G6: Var
A7: VENTAS | B7: 363499363 | C7: 485605000 | D7: =F29 -> 4.3482194e+08 | E7: =+D7/C7 -> 0.89542311 | F7: =+D7/C7 -> 0.89542311 | G7: =+D7/B7-1 -> 0.196211 | J7: 80597000
A8: PEDIDOS | B8: 6083 | C8: =+C7/C9 -> 8093.4167 | D8: =J29 -> 8256 | E8: =+D8/C8 -> 1.0200883 | F8: =+D8/C8 -> 1.0200883 | G8: =+D8/B8-1 -> 0.35722505 | J8: =+J7/I7 -> #DIV/0!
A9: TICKET PROMEDIO | B9: =+B7/B8 -> 59756.594 | C9: 60000 | D9: =+D7/D8 -> 52667.386 | E9: =+D9/C9 -> 0.87778976 | F9: =+D9/C9 -> 0.87778976 | G9: =+D9/B9-1 -> -0.11863475
A10: CLIENTE | B10: 5373 | C10: =+C8*C11 -> 8902.7583 | D10: 6927 | E10: =+D10/C10 -> 0.77807346 | F10: =+D10/C10 -> 0.77807346 | G10: =+D10/B10-1 -> 0.2892239
A11: FRECUENCIA DE COMPRA | B11: =+B8/B10 -> 1.1321422 | C11: 1.1 | D11: 1.1 | E11: =+D11/C11 -> 1 | F11: =+D11/C11 -> 1 | G11: =+D11/B11-1 -> -0.028390597
A14: EJECUCIÓN MES REGIONAL
B16: VENDEDORES | C16: % VENTA | D16: VENTA MES | E16: VENTAS X VENDEDOR | F16: VENTA ACUMULADA MES | G16: % VENTA MES | H16: PEDIDOS MES | I16: PEDIDOS X VENDEDOR | J16: PEDIDOS ACUMULADOS MES | K16: % PEDIDOS MES | L16: TICKET PROMEDIO ACUMULADO
A17: BOGOTA | B17: 19 | C17: 0.39 | D17: 189385950 | E17: 9967681.6 | F17: 1.5587221e+08 | G17: 0.35847366 | H17: 3156.4325 | I17: 166.12803 | J17: 3505 | K17: 0.42453973 | L17: 44471.387 | M17: =+J17/H17*100% -> 1.1104308 | N17: =+I17/$B$4 -> 6.9220011
A18: MEDELLIN | B18: 12 | C18: 0.3 | D18: 145681500 | E18: 12140125 | F18: 95952672 | G18: 0.22067119 | H18: 2428.025 | I18: 202.33542 | J18: 1716 | K18: 0.20784884 | L18: 55916.476 | M18: =+J18/H18*100% -> 0.70674725 | N18: =+I18/$B$4 -> 8.4306424
A19: BARRANQUILLA | B19: 6 | C19: 0.06 | D19: 29136300 | E19: 4856050 | F19: 41895679 | G19: 0.096351347 | H19: 485.605 | I19: 80.934167 | J19: 627 | K19: 0.075944767 | L19: 66819.265 | M19: =+J19/H19*100% -> 1.2911729 | N19: =+I19/$B$4 -> 3.3722569
A20: BUCARAMANGA | B20: 4 | C20: 0.05 | D20: 24280250 | E20: 6070062.5 | F20: 6716084.8 | G20: 0.015445598 | H20: 404.67083 | I20: 101.16771 | J20: 152 | K20: 0.018410853 | L20: 44184.768 | M20: =+J20/H20*100% -> 0.37561392 | N20: =+I20/$B$4 -> 4.2153212
A21: CUCUTA | B21: 3 | C21: 0.03 | D21: 14568150 | E21: 4856050 | F21: 11955084 | G21: 0.027494206 | H21: 242.8025 | I21: 80.934167 | J21: 323 | K21: 0.039123062 | L21: 37012.644 | M21: =+J21/H21*100% -> 1.3302993 | N21: =+I21/$B$4 -> 3.3722569
A22: VILLAVICENCIO | B22: 2 | C22: 0.06 | D22: 29136300 | E22: 14568150 | F22: 58658508 | G22: 0.13490236 | H22: 485.605 | I22: 242.8025 | J22: 844 | K22: 0.10222868 | L22: 69500.601 | M22: =+J22/H22*100% -> 1.7380381 | N22: =+I22/$B$4 -> 10.116771
A23: CALI | B23: 1 | C23: 0.01 | D23: 4856050 | E23: 4856050 | F23: 0 | G23: 0 | H23: 80.934167 | I23: 80.934167 | K23: 0 | M23: =+J23/H23*100% -> 0 | N23: =+I23/$B$4 -> 3.3722569
A24: PEREIRA | B24: 2 | C24: 0.03 | D24: 14568150 | E24: 7284075 | F24: 9542503.3 | G24: 0.021945772 | H24: 242.8025 | I24: 121.40125 | J24: 141 | K24: 0.017078488 | L24: 67677.328 | M24: =+J24/H24*100% -> 0.5807189 | N24: =+I24/$B$4 -> 5.0583854
A25: CARTAGENA | B25: 1 | C25: 0.01 | D25: 4856050 | E25: 4856050 | F25: 14342624 | G25: 0.032985051 | H25: 80.934167 | I25: 80.934167 | J25: 292 | K25: 0.035368217 | L25: 49118.574 | M25: =+J25/H25*100% -> 3.6078706 | N25: =+I25/$B$4 -> 3.3722569
A26: VALLEDUPAR | B26: 2 | C26: 0.03 | D26: 14568150 | E26: 7284075 | F26: 26199116 | G26: 0.060252517 | H26: 242.8025 | I26: 121.40125 | J26: 501 | K26: 0.06068314 | L26: 52293.645 | M26: =+J26/H26*100% -> 2.0634054 | N26: =+I26/$B$4 -> 5.0583854
A27: MONTERIA | B27: 2 | C27: 0.02 | D27: 9712100 | E27: 4856050 | F27: 13171922 | G27: 0.030292681 | H27: 161.86833 | I27: 80.934167 | J27: 147 | K27: 0.017805233 | L27: 89604.915 | M27: =+J27/H27*100% -> 0.90814551 | N27: =+I27/$B$4 -> 3.3722569
A28: CLIENTE | B28: 0 | C28: 0.01 | D28: 4856050 | F28: 515532.26 | G28: 0.001185617 | H28: 80.934167 | J28: 8 | K28: 0.00096899225 | L28: 64441.533 | M28: =+J28/H28*100% -> 0.09884577 | N28: =+I28/$B$4 -> 0
A29: TOTAL | B29: 54 | C29: 1 | D29: 485605000 | E29: 81594419 | F29: 4.3482194e+08 | G29: 1 | H29: 8093.4167 | I29: 1359.907 | J29: 8256 | K29: 1 | L29: 52667.386 | M29: =+J29/H29*100% -> 1.0200883
B31: VENTA | C31: % VENTA | D31: CUMPLIMIENTO VENTA | E31: PEDIDOS | F31: %PEDIDOS | G31: CUMPLIMIENTO PEDIDOS | H31: TICKET PROMEDIO
A32: BOGOTA | B32: 1.5587221e+08 | C32: 0.35847366 | D32: 0.82304 | E32: 3505 | F32: 0.42453973 | G32: 1.1104308 | H32: 44471.387
A33: MEDELLIN | B33: 95952672 | C33: 0.22067119 | D33: 0.65864693 | E33: 1716 | F33: 0.20784884 | G33: 0.70674725 | H33: 55916.476
A34: BARRANQUILLA | B34: 41895679 | C34: 0.096351347 | D34: 1.4379204 | E34: 627 | F34: 0.075944767 | G34: 1.2911729 | H34: 66819.265
A35: BUCARAMANGA | B35: 6716084.8 | C35: 0.015445598 | D35: 0.2766069 | E35: 152 | F35: 0.018410853 | G35: 0.37561392 | H35: 44184.768
A36: CUCUTA | B36: 11955084 | C36: 0.027494206 | D36: 0.82063157 | E36: 323 | F36: 0.039123062 | G36: 1.3302993 | H36: 37012.644
A37: VILLAVICENCIO | B37: 58658508 | C37: 0.13490236 | D37: 2.0132449 | E37: 844 | F37: 0.10222868 | G37: 1.7380381 | H37: 69500.601
A38: CALI | B38: 0 | C38: 0 | D38: 0 | E38: 0 | F38: 0 | G38: 0
A39: PEREIRA | B39: 9542503.3 | C39: 0.021945772 | D39: 0.65502506 | E39: 141 | F39: 0.017078488 | G39: 0.5807189 | H39: 67677.328
A40: CARTAGENA | B40: 14342624 | C40: 0.032985051 | D40: 2.9535577 | E40: 292 | F40: 0.035368217 | G40: 3.6078706 | H40: 49118.574
A41: VALLEDUPAR | B41: 26199116 | C41: 0.060252517 | D41: 1.7983832 | E41: 501 | F41: 0.06068314 | G41: 2.0634054 | H41: 52293.645
A42: MONTERIA | B42: 13171922 | C42: 0.030292681 | D42: 1.3562383 | E42: 147 | F42: 0.017805233 | G42: 0.90814551 | H42: 89604.915
A43: CLIENTE | B43: 515532.26 | C43: 0.001185617 | D43: 0.10616288 | E43: 8 | F43: 0.00096899225 | G43: 0.09884577 | H43: 64441.533
A44: TOTAL | B44: 4.3482194e+08 | C44: 1 | D44: 0.89542311 | E44: 8256 | F44: 1 | G44: 1.0200883 | H44: 52667.386
A46: EJECUCIÓN MES X VENDEDOR
A48: ZONA | B48: REGIONAL | C48: VENDEDOR | D48: META PEDIDOS MES | E48: PEDIDOS ACUMULADOS MES | F48: VENTA ACUMULADA | G48: CUMPL PEDIDOS | H48: ETERNA | I48: PREBEL | J48: YASS | K48: DROMATIC | L48: SENSE | M48: KNIGTH
A49: 720 | B49: BARRANQUILLA | C49: WILLIAM ALFONSO SARMIENTO ARROYO 720 BARRANQUILLA | D49: 80.934167 | E49: #N/A | F49: #N/A | G49: #N/A
A50: 620 | B50: CALI | C50: KATHERINE LOZANO MONTES 620 | D50: 80.934167 | E50: #N/A | F50: #N/A | G50: #N/A
A51: 905 | B51: VILLAVICENCIO | C51: ANGELICA CALVO 905 | D51: 242.8025 | E51: 446 | F51: 36783800 | G51: 1.8368839
A52: 906 | B52: VILLAVICENCIO | C52: CRISTIAN CAMILO HERRERA GUTIERREZ 906 | D52: 242.8025 | E52: 398 | F52: 33019824 | G52: 1.6391923
A53: 107 | B53: MEDELLIN | C53: ELIANA GOMEZ 107 | D53: 202.33542 | E53: 259 | F53: 10752778 | G53: 1.2800527
A54: 918 | B54: BOGOTA | C54: MARIBEL REDONDO 918 | D54: 166.12803 | E54: 298 | F54: 17532192 | G54: 1.7937973
A55: 104 | B55: MEDELLIN | C55: ANDRES GRACIANO SERNA 104 | D55: 202.33542 | E55: 220 | F55: 25260186 | G55: 1.0873035
B56: BOGOTA | C56: YULIETH HERNANDEZ | D56: 166.12803 | E56: 249 | F56: 17221004 | G56: 1.498844
A57: 718 | B57: CARTAGENA | C57: NEIL TORRES 718 CARTAGENA | D57: 80.934167 | E57: 273 | F57: 16275663 | G57: 3.3731119
A58: 938 | B58: BOGOTA | C58: DIANA MARCELA DIAZ TORRES 938 | D58: 166.12803 | E58: 281 | F58: 16144622 | G58: 1.6914666
A59: 102 | B59: MEDELLIN | C59: DUBY YARLENY BEDOYA FLOREZ 102 | D59: 202.33542 | E59: 187 | F59: 7644098.5 | G59: 0.92420795
A60: 705 | B60: VALLEDUPAR | C60: LILIANA BLANCO LOPEZ 705 VALLEDUPAR | D60: 121.40125 | E60: 268 | F60: 15734974 | G60: 2.2075555
A61: 706 | B61: VALLEDUPAR | C61: LILIANA MARCELA GONZALEZ PLATA 706 VALLEDUPAR | D61: 121.40125 | E61: 233 | F61: 15441974 | G61: 1.9192554
A62: 713 | B62: BARRANQUILLA | C62: YOANY SARMIENTO PEREZ 713 BARRANQUILLA | D62: 80.934167 | E62: 196 | F62: 15084158 | G62: 2.4217214
A63: 945 | B63: BOGOTA | C63: CRISTINA QUINTERO RUDAS 945 | D63: 166.12803 | E63: 237 | F63: 13159339 | G63: 1.4266106
A64: 117 | B64: MEDELLIN | C64: GEORLAN GARCIA PANIAGUA 117 | D64: 202.33542 | E64: 179 | F64: 17327052 | G64: 0.88466964
A65: 907 | B65: BOGOTA | C65: SOL KATHERINE BERNAL MONTANO 907 | D65: 166.12803 | E65: 204 | F65: 11636951 | G65: 1.2279686
A66: 921 | B66: BOGOTA | C66: LEYDY YURLEY MUNEVAR ESPITIA 921 | D66: 166.12803 | E66: 192 | F66: 11347488 | G66: 1.1557352
A67: 714 | B67: BARRANQUILLA | C67: JESUS ENRIQUE GIRALDO SOTO 714 BARRANQUILLA | D67: 80.934167 | E67: 155 | F67: 11205756 | G67: 1.9151368
A68: 920 | B68: BOGOTA | C68: WILLIAM ALBERTO VELASQUEZ BERNAL 920 | D68: 166.12803 | E68: 203 | F68: 10853524 | G68: 1.2219491
... A103: 415 | B103: BUCARAMANGA | C103: IVONNE RAMIREZ 415 BUCARAMANGA | D103: 101.16771 | E103: 24 | F103: 992344.64 | G103: 0.23722985

Sheet AGOSTO-25
A1: EJECUCIÓN MES
B3: DIAS CALENDARIO TRONEX | C3: DIAS TRANSCURRIDOS
A4: DIAS HABILES MES | B4: 19 | C4: 19
A6: GENERALES | B6: 2023 | C6: META MES | D6: VENTA MES | E6: CUMPLIMIENTO | F6: CUMPL | G6: Var
A7: VENTAS | B7: 357657385 | C7: 400000000 | D7: 3.4754472e+08 | E7: 0.8688618 | F7: 0.8688618 | G7: -0.028274728
A8: PEDIDOS | B8: 5958 | C8: 6666.6667 | D8: 6764 | E8: 1.0146 | F8: 1.0146 | G8: 0.1352803
A9: TICKET PROMEDIO | B9: 60029.773 | C9: 60000 | D9: 51381.538 | E9: 0.85635896 | F9: 0.85635896 | G9: -0.14406576
A10: CLIENTE | B10: 5266 | C10: 5899.705 | D10: 5651 | E10: 0.9578445 | F10: 0.9578445 | G10: 0.07311052
A11: FRECUENCIA DE COMPRA | B11: 1.131409 | C11: 1.13 | D11: 1.13 | E11: 1 | F11: 1 | G11: -0.0012453844
A14: EJECUCIÓN MES REGIONAL
B16: VENDEDORES | C16: % VENTA | D16: VENTA MES | E16: VENTAS X VENDEDOR | F16: VENTA ACUMULADA MES | G16: % VENTA MES | H16: PEDIDOS MES | I16: PEDIDOS X VENDEDOR | J16: PEDIDOS ACUMULADOS MES | K16: % PEDIDOS MES | L16: TICKET PROMEDIO ACUMULADO
A17: BOGOTA | B17: 19 | C17: 0.34 | D17: 136000000 | E17: 7157894.7 | F17: 1.1778168e+08 | G17: 0.33889648 | H17: 2266.6667 | I17: 119.29825 | J17: 2914 | K17: 0.43081017 | L17: 40419.246
A18: MEDELLIN | B18: 12 | C18: 0.245 | D18: 98000000 | E18: 8166666.7 | F18: 84683377 | G18: 0.24366181 | H18: 1633.3333 | I18: 136.11111 | J18: 1523 | K18: 0.22516263 | L18: 55603.005
A19: BARRANQUILLA | B19: 6 | C19: 0.06 | D19: 24000000 | E19: 4000000 | F19: 27982952 | G19: 0.080516119 | H19: 400 | I19: 66.666667 | J19: 432 | K19: 0.063867534 | L19: 64775.352
A20: BUCARAMANGA | B20: 4 | C20: 0.05 | D20: 20000000 | E20: 5000000 | F20: 5989191.6 | G20: 0.017232866 | H20: 333.33333 | I20: 83.333333 | J20: 109 | K20: 0.016114725 | L20: 54946.712
A21: CUCUTA | B21: 3 | C21: 0.03 | D21: 12000000 | E21: 4000000 | F21: 7454538.2 | G21: 0.021449148 | H21: 200 | I21: 66.666667 | J21: 212 | K21: 0.031342401 | L21: 35162.916
A22: VILLAVICENCIO | B22: 2 | C22: 0.13 | D22: 52000000 | E22: 26000000 | F22: 54273102 | G22: 0.15616149 | H22: 866.66667 | I22: 433.33333 | J22: 710 | K22: 0.10496747 | L22: 76440.989
A23: CALI | B23: 1 | C23: 0.01 | D23: 4000000 | E23: 4000000 | F23: 3108596.7 | G23: 0.0089444508 | H23: 66.666667 | I23: 66.666667 | J23: 35 | K23: 0.005174453
A24: PEREIRA | B24: 2 | C24: 0.02 | D24: 8000000 | E24: 4000000 | F24: 5775200.4 | G24: 0.016617143 | H24: 133.33333 | I24: 66.666667 | J24: 84 | K24: 0.012418687 | L24: 68752.386
A25: CARTAGENA | B25: 1 | C25: 0.025 | D25: 10000000 | E25: 10000000 | F25: 7227044.6 | G25: 0.020794574 | H25: 166.66667 | I25: 166.66667 | J25: 135 | K25: 0.019958604 | L25: 53533.663
A26: VALLEDUPAR | B26: 2 | C26: 0.05 | D26: 20000000 | E26: 10000000 | F26: 20799177 | G26: 0.059846046 | H26: 333.33333 | I26: 166.66667 | J26: 408 | K26: 0.060319338 | L26: 50978.376
A27: MONTERIA | B27: 2 | C27: 0.03 | D27: 12000000 | E27: 6000000 | F27: 12469856 | G27: 0.035879861 | H27: 200 | I27: 100 | J27: 202 | K27: 0.029863986 | L27: 61731.961
A28: CLIENTE | B28: 0 | C28: 0.01 | D28: 4000000 | F28: 0 | G28: 0 | H28: 66.666667 | J28: 0 | K28: 0 | L28: #DIV/0!
A29: TOTAL | B29: 54 | C29: 1 | D29: 400000000 | E29: 88324561 | F29: 3.4754472e+08 | G29: 1 | H29: 6666.6667 | I29: 1472.076 | J29: 6764 | K29: 1 | L29: 51381.538
B31: VENTA MES | C31: % | D31: CUMPL VENTA | E31: PEDIDOS MES | F31: %PEDIDOS | G31: CUMPL PEDIDOS | H31: TICKET PROMEDIO
A32: BOGOTA | B32: 1.1778168e+08 | C32: 0.33889648 | D32: 0.86604179 | E32: 2914 | F32: 0.43081017 | G32: 1.2855882 | H32: 40419.246
A33: MEDELLIN | B33: 84683377 | C33: 0.24366181 | D33: 0.86411609 | E33: 1523 | F33: 0.22516263 | G33: 0.93244898 | H33: 55603.005
A34: BARRANQUILLA | B34: 27982952 | C34: 0.080516119 | D34: 1.1659563 | E34: 432 | F34: 0.063867534 | G34: 1.08 | H34: 64775.352
A35: BUCARAMANGA | B35: 5989191.6 | C35: 0.017232866 | D35: 0.29945958 | E35: 109 | F35: 0.016114725 | G35: 0.327 | H35: 54946.712
A36: CUCUTA | B36: 7454538.2 | C36: 0.021449148 | D36: 0.62121152 | E36: 212 | F36: 0.031342401 | G36: 1.06 | H36: 35162.916
A37: VILLAVICENCIO | B37: 54273102 | C37: 0.15616149 | D37: 1.0437135 | E37: 710 | F37: 0.10496747 | G37: 0.81923077 | H37: 76440.989
A38: CALI | B38: 3108596.7 | C38: 0.0089444508 | D38: 0.77714916 | E38: 35 | F38: 0.005174453 | G38: 0.525 | H38: 88817.047
A39: PEREIRA | B39: 5775200.4 | C39: 0.016617143 | D39: 0.72190006 | E39: 84 | F39: 0.012418687 | G39: 0.63 | H39: 68752.386
A40: CARTAGENA | B40: 7227044.6 | C40: 0.020794574 | D40: 0.72270446 | E40: 135 | F40: 0.019958604 | G40: 0.81 | H40: 53533.663
A41: VALLEDUPAR | B41: 20799177 | C41: 0.059846046 | D41: 1.0399589 | E41: 408 | F41: 0.060319338 | G41: 1.224 | H41: 50978.376
A42: MONTERIA | B42: 12469856 | C42: 0.035879861 | D42: 1.0391547 | E42: 202 | F42: 0.029863986 | G42: 1.01 | H42: 61731.961
A43: CLIENTE | B43: 0 | C43: 0 | D43: 0 | E43: 0 | F43: 0 | G43: 0 | H43: #DIV/0!
A44: TOTAL | B44: 3.4754472e+08 | C44: 1 | D44: 0.8688618 | E44: 6764 | F44: 1 | G44: 1.0146 | H44: 51381.538
A46: EJECUCIÓN MES X VENDEDOR
A48: ZONA | B48: REGIONAL | C48: VENDEDOR | D48: META PEDIDOS MES | E48: PEDIDOS ACUMULADOS MES | F48: VENTA ACUMULADA | G48: CUMPL PEDIDOS | H48: ETERNA | I48: PREBEL | J48: YASS | K48: DROMATIC | L48: SENSE | M48: KNIGTH
A49: 713 | B49: BARRANQUILLA | C49: YOANY SARMIENTO PEREZ 713 BARRANQUILLA | D49: 66.666667 | E49: 213 | F49: 12740326 | G49: 3.195
A50: 620 | B50: CALI | C50: KATHERINE LOZANO MONTES 620 | D50: 66.666667 | E50: 35 | F50: 3108596.7 | G50: 0.525
A51: 715 | B51: BARRANQUILLA | C51: ALVARO ENRIQUE CASTAÑEDA MANJARRES 715 BARRANQUILLA | D51: 66.666667 | E51: 87 | F51: 6823637.1 | G51: 1.305
A52: 705 | B52: VALLEDUPAR | C52: LILIANA BLANCO LOPEZ 705 VALLEDUPAR | D52: 166.66667 | E52: 255 | F52: 12591521 | G52: 1.53
A53: 714 | B53: BARRANQUILLA | C53: JESUS ENRIQUE GIRALDO SOTO 714 BARRANQUILLA | D53: 66.666667 | E53: 81 | F53: 3294262.8 | G53: 1.215
A54: 509 | B54: MONTERIA | C54: JOSE GREGORIO OSTEN MERCADO 509 | D54: 100 | E54: 131 | F54: 6868096.1 | G54: 1.31
A55: 918 | B55: BOGOTA | C55: MARIBEL REDONDO 918 | D55: 119.29825 | E55: 243 | F55: 10199931 | G55: 2.0369118
B56: BOGOTA | C56: YULIETH HERNANDEZ | D56: 119.29825 | E56: 209 | F56: 10037230 | G56: 1.7519118
A57: 938 | B57: BOGOTA | C57: DIANA MARCELA DIAZ TORRES 938 | D57: 119.29825 | E57: 204 | F57: 8713456.9 | G57: 1.71
A58: 945 | B58: BOGOTA | C58: CRISTINA QUINTERO RUDAS 945 | D58: 119.29825 | E58: 190 | F58: 7188391.4 | G58: 1.5926471
A59: 706 | B59: VALLEDUPAR | C59: LILIANA MARCELA GONZALEZ PLATA 706 VALLEDUPAR | D59: 166.66667 | E59: 153 | F59: 8207656.2 | G59: 0.918
A60: 921 | B60: BOGOTA | C60: LEYDY YURLEY MUNEVAR ESPITIA 921 | D60: 119.29825 | E60: 188 | F60: 9202083.5 | G60: 1.5758824
A61: 919 | B61: BOGOTA | C61: SANDRA PATRICIA ORTIZ ROMERO 919 | D61: 119.29825 | E61: 183 | F61: 6225931.9 | G61: 1.5339706
A62: 718 | B62: CARTAGENA | C62: NEIL TORRES 718 CARTAGENA | D62: 166.66667 | E62: 131 | F62: 7103824.1 | G62: 0.786
A63: 712 | B63: BARRANQUILLA | C63: STHEFANY OJITO BARRANQUILLA 712 | D63: 66.666667 | E63: 51 | F63: 5124726.5 | G63: 0.765
A64: 946 | B64: BOGOTA | C64: MONICA RODRIGUEZ RONCANCIO 946 | D64: 119.29825 | E64: 176 | F64: 6168530.4 | G64: 1.4752941
A65: 104 | B65: MEDELLIN | C65: ANDRES GRACIANO SERNA 104 | D65: 136.11111 | E65: 235 | F65: 19524381 | G65: 1.7265306
A66: 926 | B66: BOGOTA | C66: LEONARDO MANCERA BOLAÑOS 926 | D66: 119.29825 | E66: 167 | F66: 6675376.1 | G66: 1.3998529
A67: 920 | B67: BOGOTA | C67: WILLIAM ALBERTO VELASQUEZ BERNAL 920 | D67: 119.29825 | E67: 156 | F67: 6119284.2 | G67: 1.3076471
A68: 117 | B68: MEDELLIN | C68: GEORLAN GARCIA PANIAGUA 117 | D68: 136.11111 | E68: 201 | F68: 18478425 | G68: 1.4767347
... A103: 711 | B103: BARRANQUILLA | C103: JHON WILLIAM JIMENEZ CADENA 711 BARRANQUILLA | D103: 66.666667 | E103: 0 | F103: 0 | G103: 0

Sheet SEPTIEMBRE-25
A1: EJECUCIÓN MES
B3: DIAS CALENDARIO TRONEX | C3: DIAS TRANSCURRIDOS
A4: DIAS HABILES MES | B4: 20 | C4: 20
A6: GENERALES | B6: 2023 | C6: META MES | D6: VENTA MES | E6: CUMPLIMIENTO | F6: CUMPLIMIENTO | G6: Var
A7: VENTAS | B7: 318164072 | C7: 465000000 | D7: 3.1306489e+08 | E7: 0.67325783 | F7: 0.67325783 | G7: -0.016026898
A8: PEDIDOS | B8: 5106 | C8: 7750 | D8: 6559 | E8: 0.84632258 | F8: 0.84632258 | G8: 0.28456718
A9: TICKET PROMEDIO | B9: 62311.804 | C9: 60000 | D9: 47730.582 | E9: 0.7955097 | F9: 0.7955097 | G9: -0.23400417
A10: CLIENTE | B10: 5267 | C10: 0 | D10: 6029 | E10: 0.39863484 | F10: 0.9965871 | G10: 0.14467439
A11: FRECUENCIA DE COMPRA | B11: 0.96943231 | C11: 0.96943231 | D11: 1.0879084 | E11: 1 | F11: 1 | G11: 0.12221186
A14: EJECUCIÓN MES REGIONAL
B16: VENDEDORES | C16: % VENTA | D16: % PEDIDOS | E16: VENTA MES | F16: VENTAS X VENDEDOR | G16: VENTA ACUMULADA MES | H16: % VENTA MES | I16: PEDIDOS MES | J16: PEDIDOS X VENDEDOR | K16: PEDIDOS ACUMULADOS MES | L16: % PEDIDOS MES | M16: TICKET PROMEDIO ACUMULADO
A17: BOGOTA | B17: 19 | C17: 0.33 | D17: 0.42 | E17: 153450000 | F17: 8076315.8 | G17: 1.2397704e+08 | H17: 0.3960107 | I17: 3255 | J17: 171.31579 | K17: 3097 | L17: 0.47217564 | M17: 40031.335
A18: MEDELLIN | B18: 12 | C18: 0.23 | D18: 0.2 | E18: 106950000 | F18: 8912500 | G18: 63602355 | H18: 0.20316029 | I18: 1550 | J18: 129.16667 | K18: 1382 | L18: 0.21070285 | M18: 46021.964
A19: BARRANQUILLA | B19: 6 | C19: 0.085 | D19: 0.06 | E19: 39525000 | F19: 6587500 | G19: 29877210 | H19: 0.095434561 | I19: 465 | J19: 77.5 | K19: 479 | L19: 0.073029425 | M19: 62374.134
A20: BUCARAMANGA | B20: 4 | C20: 0.045 | D20: 0.05 | E20: 20925000 | F20: 5231250 | G20: 4839335.5 | H20: 0.015457931 | I20: 387.5 | J20: 96.875 | K20: 100 | L20: 0.015246227 | M20: 48393.355
A21: CUCUTA | B21: 3 | C21: 0.025 | D21: 0.03 | E21: 11625000 | F21: 3875000 | G21: 5394099.5 | H21: 0.017229973 | I21: 232.5 | J21: 77.5 | K21: 171 | L21: 0.026071047 | M21: 31544.442
A22: VILLAVICENCIO | B22: 2 | C22: 0.11 | D22: 0.08 | E22: 51150000 | F22: 25575000 | G22: 47563126 | H22: 0.15192737 | I22: 620 | J22: 310 | K22: 698 | L22: 0.10641866 | M22: 68142.014
A23: CALI | B23: 1 | C23: 0.02 | D23: 0.04 | E23: 9300000 | F23: 9300000 | G23: 0 | H23: 0 | I23: 310 | J23: 310 | K23: 0 | L23: 0
A24: PEREIRA | B24: 2 | C24: 0.02 | D24: 0.02 | E24: 9300000 | F24: 4650000 | G24: 7687189.6 | H24: 0.024554621 | I24: 155 | J24: 77.5 | K24: 112 | L24: 0.017075774 | M24: 68635.622
A25: CARTAGENA | B25: 1 | C25: 0.03 | D25: 0.03 | E25: 13950000 | F25: 13950000 | G25: 3549635.8 | H25: 0.011338339 | I25: 232.5 | J25: 232.5 | K25: 78 | L25: 0.011892057 | M25: 45508.151
A26: VALLEDUPAR | B26: 2 | C26: 0.05 | D26: 0.05 | E26: 23250000 | F26: 11625000 | G26: 17108839 | H26: 0.054649499 | I26: 387.5 | J26: 193.75 | K26: 319 | L26: 0.048635463 | M26: 53632.725
A27: MONTERIA | B27: 2 | C27: 0.035 | D27: 0.02 | E27: 16275000 | F27: 8137500 | G27: 9466054 | H27: 0.030236716 | I27: 155 | J27: 77.5 | K27: 123 | L27: 0.018752859 | M27: 76959.788
A28: CLIENTE | B28: 0 | C28: 0.02 | D28: 0 | E28: 9300000 | G28: 0 | H28: 0 | I28: 0 | K28: 0 | L28: 0 | M28: #DIV/0!
A29: TOTAL | B29: 54 | C29: 1 | D29: 1 | E29: 465000000 | F29: 1.0592007e+08 | G29: 3.1306489e+08 | H29: 1 | I29: 7750 | J29: 1753.6075 | K29: 6559 | L29: 1 | M29: 47730.582
B31: PROY VENTA MES | C31: % | D31: CUMPL PROY VENTA | E31: PEDIDOS MES | F31: %PEDIDOS | G31: CUMPL PEDIDOS | H31: TICKET PROMEDIO
A32: BOGOTA | B32: 1.2397704e+08 | C32: 0.3960107 | D32: 0.80793122 | E32: 3097 | F32: 0.47217564 | G32: 0.95145929 | H32: 40031.335
A33: MEDELLIN | B33: 63602355 | C33: 0.20316029 | D33: 0.59469242 | E33: 1382 | F33: 0.21070285 | G33: 0.8916129 | H33: 46021.964
A34: BARRANQUILLA | B34: 29877210 | C34: 0.095434561 | D34: 0.75590665 | E34: 479 | F34: 0.073029425 | G34: 1.0301075 | H34: 62374.134
A35: BUCARAMANGA | B35: 4839335.5 | C35: 0.015457931 | D35: 0.23127051 | E35: 100 | F35: 0.015246227 | G35: 0.25806452 | H35: 48393.355
A36: CUCUTA | B36: 5394099.5 | C36: 0.017229973 | D36: 0.46400856 | E36: 171 | F36: 0.026071047 | G36: 0.73548387 | H36: 31544.442
A37: VILLAVICENCIO | B37: 47563126 | C37: 0.15192737 | D37: 0.92987538 | E37: 698 | F37: 0.10641866 | G37: 1.1258065 | H37: 68142.014
A38: CALI | B38: 0 | C38: 0 | D38: 0 | E38: 0 | F38: 0 | G38: 0 | H38: #DIV/0!
A39: PEREIRA | B39: 7687189.6 | C39: 0.024554621 | D39: 0.82657953 | E39: 112 | F39: 0.017075774 | G39: 0.72258065 | H39: 68635.622
A40: CARTAGENA | B40: 3549635.8 | C40: 0.011338339 | D40: 0.25445418 | E40: 78 | F40: 0.011892057 | G40: 0.33548387 | H40: 45508.151
A41: VALLEDUPAR | B41: 17108839 | C41: 0.054649499 | D41: 0.73586405 | E41: 319 | F41: 0.048635463 | G41: 0.82322581 | H41: 53632.725
A42: MONTERIA | B42: 9466054 | C42: 0.030236716 | D42: 0.58163158 | E42: 123 | F42: 0.018752859 | G42: 0.79354839 | H42: 76959.788
A43: CLIENTE | B43: 0 | C43: 0 | D43: 0 | E43: 0 | F43: 0 | G43: #DIV/0! | H43: #DIV/0!
A44: TOTAL | B44: 3.1306489e+08 | C44: 1 | D44: 0.67325783 | E44: 6559 | F44: 1 | G44: 0.84632258 | H44: 47730.582
A46: EJECUCIÓN MES X VENDEDOR
A48: ZONA | B48: REGIONAL | C48: VENDEDOR | D48: META PEDIDOS MES | E48: PEDIDOS ACUMULADOS MES | F48: VENTA ACUMULADA | G48: VENTA TERCEROS | H48: CUMPL PEDIDOS
A49: 107 | B49: MEDELLIN | C49: ELIANA GOMEZ 107 | D49: 129.16667 | E49: 206 | F49: 7401312.3 | G49: 4544080 | H49: 1.5948387
A50: 945 | B50: BOGOTA | C50: CRISTINA QUINTERO RUDAS 945 | D50: 171.31579 | E50: 223 | F50: 9266282.8 | G50: 3555139.7 | H50: 1.3016897
A51: 114 | B51: MEDELLIN | C51: MARIA ELENA JARAMILLO GALEANO 114 | D51: 129.16667 | E51: 141 | F51: 4920729.2 | G51: 3307579.2 | H51: 1.0916129
A52: 918 | B52: BOGOTA | C52: MARIBEL REDONDO 918 | D52: 171.31579 | E52: 221 | F52: 9226267.3 | G52: 1718669.1 | H52: 1.2900154
A53: 921 | B53: BOGOTA | C53: LEYDY YURLEY MUNEVAR ESPITIA 921 | D53: 171.31579 | E53: 210 | F53: 9227381.6 | G53: 3193694.8 | H53: 1.2258065
A54: 102 | B54: MEDELLIN | C54: DUBY YARLENY BEDOYA FLOREZ 102 | D54: 129.16667 | E54: 133 | F54: 3304770.1 | G54: 3069675.6 | H54: 1.0296774
A55: 938 | B55: BOGOTA | C55: DIANA MARCELA DIAZ TORRES 938 | D55: 171.31579 | E55: 207 | F55: 9412660.1 | G55: 2671238.5 | H55: 1.2082949
A56: 103 | B56: MEDELLIN | C56: KATHERINE GAVIRIA MAZO 103 | D56: 129.16667 | E56: 140 | F56: 5220302.6 | G56: 2621241.8 | H56: 1.083871
A57: 905 | B57: VILLAVICENCIO | C57: CESAR BERMUDEZ 905 | D57: 310 | E57: 361 | F57: 24994930 | G57: 872451.38 | H57: 1.1645161
A58: 113 | B58: MEDELLIN | C58: MIGUEL ANGEL HIDALGO SANTOS 113 | D58: 129.16667 | E58: 113 | F58: 3131159.2 | G58: 2404564.7 | H58: 0.87483871
A59: 920 | B59: BOGOTA | C59: WILLIAM ALBERTO VELASQUEZ BERNAL 920 | D59: 171.31579 | E59: 192 | F59: 8233485.3 | G59: 2187511.4 | H59: 1.1207373
A60: 919 | B60: BOGOTA | C60: SANDRA PATRICIA ORTIZ ROMERO 919 | D60: 171.31579 | E60: 191 | F60: 5752689.3 | G60: 2260313.9 | H60: 1.1149002
... A78: 937 | B78: BOGOTA | C78: MARIA NANCY GUARIN VIRGUEZ 937 | D78: 171.31579 | E78: 141 | F78: 5891942.6 | G78: 2532474.2 | H78: 0.82304147
A79: 711 | B79: BARRANQUILLA | C79: JHON WILLIAM JIMENEZ CADENA 711 BARRANQUILLA | D79: 77.5 | E79: #N/A | F79: 0 | G79: 0 | H79: #N/A
A80: 407 | B80: BUCARAMANGA | C80: YOHAN PITA 407 BUCARAMANGA | D80: 96.875 | E80: 3 | F80: 34947.345 | G80: 1104663.5 | H80: 0.030967742
A81: 713 | B81: BARRANQUILLA | C81: YOANY SARMIENTO PEREZ 713 BARRANQUILLA | D81: 77.5 | E81: 140 | F81: 9682143.8 | G81: 1211275.8 | H81: 1.8064516
A82: 908 | B82: BOGOTA | C82: ANGIE JOHANA BEDOYA HERRENO 908 | D82: 171.31579 | E82: 137 | F82: 5532364.1 | G82: 2125827.1 | H82: 0.79969278
A83: 409 | B83: CUCUTA | C83: FREDY ESTEPA 409 CUCUTA | D83: 77.5 | E83: 151 | F83: 5119529.4 | G83: 1579509.3 | H83: 1.9483871
A84: 116 | B84: MEDELLIN | C84: EDISON ALBERTO SALAZAR YEPES 116 | D84: 129.16667 | E84: 42 | F84: 1370820.7 | G84: 1135572.4 | H84: 0.32516129
A85: 410 | B85: BUCARAMANGA | C85: CAROLINA RUEDA 410 BUCARAMANGA | D85: 96.875 | E85: 52 | F85: 2336745.7 | G85: 789204.06 | H85: 0.53677419
A86: 933 | B86: BOGOTA | C86: NAIR JAEL VARGAS TALERO 933 | D86: 171.31579 | E86: 131 | F86: 4808364.8 | G86: 1686080.1 | H86: 0.76466974
A87: 934 | B87: BOGOTA | C87: CARLOS EDUARDO ROMERO 934 | D87: 171.31579 | E87: 118 | F87: 4092421.2 | G87: 870044.37 | H87: 0.68878648
A88: 714 | B88: BARRANQUILLA | C88: JESUS ENRIQUE GIRALDO SOTO 714 BARRANQUILLA | D88: 77.5 | E88: 140 | F88: 6978892.8 | G88: 368590.52 | H88: 1.8064516
A89: 411 | B89: CUCUTA | C89: MAIRA TORRES 411 CUCUTA | D89: 77.5 | E89: 20 | F89: 274570.15 | G89: 1141919.2 | H89: 0.25806452
A90: 715 | B90: BARRANQUILLA | C90: ALVARO ENRIQUE CASTAÑEDA MANJARRES 715 BARRANQUILLA | D90: 77.5 | E90: 80 | F90: 6986226.5 | G90: 364180.48 | H90: 1.0322581
A91: 509 | B91: MONTERIA | C91: JOSE GREGORIO OSTEN MERCADO 509 | D91: 77.5 | E91: 76 | F91: 5274914.2 | G91: 753518.11 | H91: 0.98064516
... A95: 706 | B95: VALLEDUPAR | C95: LILIANA MARCELA GONZALEZ PLATA 706 VALLEDUPAR | D95: 193.75 | E95: 154 | F95: 8471767.6 | G95: 1255660.8 | H95: 0.79483871
A96: 413 | B96: CUCUTA | C96: ZULY RANGEL GARCIA 413 CUCUTA | D96: 77.5 | E96: #N/A | F96: 0 | G96: 213811.1 | H96: #N/A
A97: 510 | B97: MONTERIA | C97: NELSON ENRIQUE LOPEZ GONZALEZ 510 | D97: 77.5 | E97: 47 | F97: 4191139.8 | G97: 256879.62 | H97: 0.60645161
A98: 415 | B98: BUCARAMANGA | C98: IVONNE RAMIREZ 415 BUCARAMANGA | D98: 96.875 | E98: 13 | F98: 199299.33 | G98: 297471.79 | H98: 0.13419355
A99: 932 | B99: BOGOTA | C99: OSCAR GIOVANNY NASAYO BLANCO 932 | D99: 171.31579 | E99: 99 | F99: 4619118.8 | G99: 1619162.8 | H99: 0.57788018
A100: 720 | B100: BARRANQUILLA | C100: MARIELA ESTER DE LEON 720 BARRANQUILLA | D100: 77.5 | E100: 39 | F100: 1474555.4 | G100: 810226.36 | H100: 0.50322581
A101: 718 | B101: CARTAGENA | C101: NEIL TORRES 718 CARTAGENA | D101: 232.5 | E101: 60 | F101: 3095273.9 | G101: 774793.91 | H101: 0.25806452
A102: 717 | B102: CARTAGENA | C102: YAFER JESUS CORDOBA BERRIO 717 CARTAGENA | D102: 232.5 | E102: 18 | F102: 454361.82 | G102: 133575.99 | H102: 0.077419355

Sheet OCTUBRE-25 
A1: EJECUCIÓN MES
B3: DIAS CALENDARIO TRONEX | C3: DIAS TRANSCURRIDOS
A4: DIAS HABILES MES | B4: 24 | C4: 24
A6: GENERALES | B6: 2023 | C6: META MES | D6: VENTA MES | E6: CUMPLIMIENTO | F6: CUMPLIMIENTO | G6: Var
A7: VENTAS | B7: 344061968 | C7: 409705313 | D7: 3.5929574e+08 | E7: 0.8769614 | F7: 0.8769614 | G7: 0.044276255
A8: PEDIDOS | B8: 5788 | C8: 6828.4219 | D8: 6419 | E8: 0.94004151 | F8: 0.94004151 | G8: 0.10901866
A9: TICKET PROMEDIO | B9: 59444.017 | C9: 60000 | D9: 55973.788 | E9: 0.93289646 | F9: 0.93289646 | G9: -0.058378102
A10: CLIENTE | B10: 6000 | C10: 7000 | D10: 6449 | E10: 0.92128571 | F10: 0.92128571 | G10: 0.074833333
A11: FRECUENCIA DE COMPRA | B11: 0.96466667 | C11: 0.97548884 | D11: 0.99534812 | E11: 1.0203583 | F11: 1.0203583 | G11: 0.031805234
A14: EJECUCIÓN MES REGIONAL
B16: VENDEDORES | C16: % VENTA | D16: % PEDIDOS | E16: VENTA MES | F16: VENTAS X VENDEDOR | G16: VENTA ACUMULADA MES | H16: % VENTA MES | I16: PEDIDOS MES | J16: PEDIDOS X VENDEDOR | K16: PEDIDOS ACUMULADOS MES | L16: % PEDIDOS MES | M16: TICKET PROMEDIO ACUMULADO
A17: BOGOTA | B17: 19 | C17: 0.33 | D17: 0.42 | E17: 1.3520275e+08 | F17: 7115934.4 | G17: 1.3163727e+08 | H17: 0.3663758 | I17: 2867.9372 | J17: 150.94406 | K17: 2670 | L17: 0.41595264 | M17: 49302.347
A18: MEDELLIN | B18: 12 | C18: 0.23 | D18: 0.2 | E18: 94232222 | F18: 7852685.2 | G18: 69489038 | H18: 0.19340345 | I18: 1365.6844 | J18: 113.80703 | K18: 1335 | L18: 0.20797632 | M18: 52051.714
A19: BARRANQUILLA | B19: 6 | C19: 0.085 | D19: 0.06 | E19: 34824952 | F19: 5804158.6 | G19: 37431568 | H19: 0.10418038 | I19: 409.70531 | J19: 68.284219 | K19: 535 | L19: 0.083346316 | M19: 69965.548
A20: BUCARAMANGA | B20: 4 | C20: 0.045 | D20: 0.05 | E20: 18436739 | F20: 4609184.8 | G20: 10402389 | H20: 0.028952162 | I20: 341.42109 | J20: 85.355274 | K20: 141 | L20: 0.021966038 | M20: 73775.806
A21: CUCUTA | B21: 3 | C21: 0.025 | D21: 0.03 | E21: 10242633 | F21: 3414210.9 | G21: 12653674 | H21: 0.035217989 | I21: 204.85266 | J21: 68.284219 | K21: 356 | L21: 0.055460352 | M21: 35544.027
A22: VILLAVICENCIO | B22: 3 | C22: 0.11 | D22: 0.08 | E22: 45067584 | F22: 15022528 | G22: 50562455 | H22: 0.14072656 | I22: 546.27375 | J22: 182.09125 | K22: 609 | L22: 0.094874591 | M22: 83025.378
A23: CALI | B23: 1 | C23: 0.02 | D23: 0.04 | E23: 8194106.3 | F23: 8194106.3 | G23: 3900239.1 | H23: 0.010855233 | I23: 273.13688 | J23: 273.13688 | K23: 46 | L23: 0.0071662253
A24: PEREIRA | B24: 2 | C24: 0.02 | D24: 0.02 | E24: 8194106.3 | F24: 4097053.1 | G24: 8970880 | H24: 0.024967955 | I24: 136.56844 | J24: 68.284219 | K24: 148 | L24: 0.023056551 | M24: 60614.054
A25: CARTAGENA | B25: 2 | C25: 0.03 | D25: 0.03 | E25: 12291159 | F25: 6145579.7 | G25: 16373739 | H25: 0.045571758 | I25: 204.85266 | J25: 102.42633 | K25: 274 | L25: 0.042685777 | M25: 59758.17
A26: VALLEDUPAR | B26: 2 | C26: 0.05 | D26: 0.05 | E26: 20485266 | F26: 10242633 | G26: 11476626 | H26: 0.031942004 | I26: 341.42109 | J26: 170.71055 | K26: 205 | L26: 0.031936439 | M26: 55983.543
A27: MONTERIA | B27: 2 | C27: 0.035 | D27: 0.02 | E27: 14339686 | F27: 7169843 | G27: 6397869.1 | H27: 0.017806693 | I27: 136.56844 | J27: 68.284219 | K27: 100 | L27: 0.015578751 | M27: 63978.691
A28: CLIENTE | B28: 0 | C28: 0.02 | D28: 0 | E28: 8194106.3 | G28: 0 | H28: 0 | I28: 0 | K28: 0 | L28: 0 | M28: #DIV/0!
A29: TOTAL | B29: 56 | C29: 1 | D29: 1 | E29: 4.0970531e+08 | F29: 79667917 | G29: 3.5929574e+08 | H29: 1 | I29: 6828.4219 | J29: 1351.6082 | K29: 6419 | L29: 1 | M29: 55973.788
B31: PROY VENTA MES | C31: % | D31: CUMPL PROY VENTA | E31: PEDIDOS MES | F31: %PEDIDOS | G31: CUMPL PEDIDOS | H31: TICKET PROMEDIO
A32: BOGOTA | B32: 1.3163727e+08 | C32: 0.3663758 | D32: 0.9736286 | E32: 2670 | F32: 0.41595264 | G32: 0.93098273 | H32: 49302.347
A33: MEDELLIN | B33: 69489038 | C33: 0.19340345 | D33: 0.73742332 | E33: 1335 | F33: 0.20797632 | G33: 0.97753187 | H33: 52051.714
A34: BARRANQUILLA | B34: 37431568 | C34: 0.10418038 | D34: 1.0748491 | E34: 535 | F34: 0.083346316 | G34: 1.3058166 | H34: 69965.548
A35: BUCARAMANGA | B35: 10402389 | C35: 0.028952162 | D35: 0.56422064 | E35: 141 | F35: 0.021966038 | G35: 0.41297976 | H35: 73775.806
A36: CUCUTA | B36: 12653674 | C36: 0.035217989 | D36: 1.2353927 | E36: 356 | F36: 0.055460352 | G36: 1.7378344 | H36: 35544.027
A37: VILLAVICENCIO | B37: 50562455 | C37: 0.14072656 | D37: 1.1219251 | E37: 609 | F37: 0.094874591 | G37: 1.1148257 | H37: 83025.378
A38: CALI | B38: 3900239.1 | C38: 0.010855233 | D38: 0.47598103 | E38: 46 | F38: 0.0071662253 | G38: 0.16841373 | H38: 84787.807
A39: PEREIRA | B39: 8970880 | C39: 0.024967955 | D39: 1.0947966 | E39: 148 | F39: 0.023056551 | G39: 1.0837057 | H39: 60614.054
A40: CARTAGENA | B40: 16373739 | C40: 0.045571758 | D40: 1.3321557 | E40: 274 | F40: 0.042685777 | G40: 1.3375467 | H40: 59758.17
A41: VALLEDUPAR | B41: 11476626 | C41: 0.031942004 | D41: 0.5602381 | E41: 205 | F41: 0.031936439 | G41: 0.60043156 | H41: 55983.543
A42: MONTERIA | B42: 6397869.1 | C42: 0.017806693 | D42: 0.44616522 | E42: 100 | F42: 0.015578751 | G42: 0.73223361 | H42: 63978.691
A43: CLIENTE | B43: 0 | C43: 0 | D43: 0 | E43: 0 | F43: 0 | G43: #DIV/0! | H43: #DIV/0!
A44: TOTAL | B44: 3.5929574e+08 | C44: 1 | D44: 0.8769614 | E44: 6419 | F44: 1 | G44: 0.94004151 | H44: 55973.788
A46: EJECUCIÓN MES X VENDEDOR
A48: ZONA | B48: REGIONAL | C48: VENDEDOR | D48: META PEDIDOS MES | E48: PEDIDOS ACUMULADOS MES | F48: VENTA ACUMULADA TUTI | G48: VENTA TERCEROS | H48: PROYECCION TERCEROS | I48: CUMPL PEDIDOS | J48: CUMPL TERCEROS
A49: 107 | B49: MEDELLIN | C49: ELIANA GOMEZ 107 | D49: 113.80703 | E49: 267 | F49: 11579167 | G49: 5468399.6 | H49: 8202599.4 | I49: 2.3460765
A50: 104 | B50: MEDELLIN | C50: ANDRES GRACIANO SERNA 104 | D50: 113.80703 | E50: 223 | F50: 19647229 | G50: 3188051.6 | H50: 4782077.4 | I50: 1.9594571
A51: 102 | B51: MEDELLIN | C51: DUBY YARLENY BEDOYA FLOREZ 102 | D51: 113.80703 | E51: 189 | F51: 5278183.2 | G51: 4155565.4 | H51: 6233348 | I51: 1.6607058
A52: 103 | B52: MEDELLIN | C52: KATHERINE GAVIRIA MAZO 103 | D52: 113.80703 | E52: 151 | F52: 3971275.1 | G52: 2888725.9 | H52: 4333088.9 | I52: 1.3268073
A53: 117 | B53: MEDELLIN | C53: GEORLAN GARCIA PANIAGUA 117 | D53: 113.80703 | E53: 121 | F53: 3695642.5 | G53: 2410224.5 | H53: 3615336.7 | I53: 1.0632032
A54: 114 | B54: MEDELLIN | C54: MARIA ELENA JARAMILLO GALEANO 114 | D54: 113.80703 | E54: 133 | F54: 3602918.9 | G54: 2299304.4 | H54: 3448956.6 | I54: 1.1686448
A55: 113 | B55: MEDELLIN | C55: MIGUEL ANGEL HIDALGO SANTOS 113 | D55: 113.80703 | E55: 111 | F55: 2889132.5 | G55: 2307770 | H55: 3461655 | I55: 0.97533517
A56: 605 | B56: PEREIRA | C56: FELIPE ARENAS 605 | D56: 68.284219 | E56: 107 | F56: 5229199.5 | G56: 2533070.7 | H56: 3799606.1 | I56: 1.5669799
A57: 905 | B57: VILLAVICENCIO | C57: CESAR BERMUDEZ 905 | D57: 182.09125 | E57: 277 | F57: 20815403 | G57: 547900.87 | H57: 821851.3 | I57: 1.5212153
A58: 111 | B58: MEDELLIN | C58: INES LILIANA PIEDRAHITA MESA 111 | D58: 113.80703 | E58: 162 | F58: 9339757.9 | G58: 1981974.8 | H58: 2972962.2 | I58: 1.4234621
A59: 906 | B59: VILLAVICENCIO | C59: JHONTAN MENDOZA 906 | D59: 182.09125 | E59: 292 | F59: 19522587 | G59: 325768.88 | H59: 488653.32 | I59: 1.6035916
A60: 405 | B60: BUCARAMANGA | C60: SANDRA PRADA 405 BUCARAMANGA | D60: 85.355274 | E60: 67 | F60: 3917399.9 | G60: 1780255 | H60: 2670382.5 | I60: 0.78495443
... A104: 717 | B104: CARTAGENA | C104: YAFER JESUS CORDOBA BERRIO 717 CARTAGENA | D104: 68.284219 | E104: 78 | F104: 2668710.6 | G104: 49437.94 | H104: 74156.91 | I104: 1.1422844

Sheet NOVIEMBRE-25 
A1: EJECUCIÓN MES
B3: DIAS CALENDARIO TRONEX | C3: DIAS TRANSCURRIDOS
A4: DIAS HABILES MES | B4: 18 | C4: 12
A6: GENERALES | B6: 2024 | C6: META MES | D6: VENTA MES | E6: CUMPLIMIENTO | F6: PROYECCIÓN CUMPLIMIENTO | G6: Var
A7: VENTAS | B7: 319072795 | C7: 433805625 | D7: =G30 -> 2.3932908e+08 | E7: =+D7/C7 -> 0.55169658 | F7: =+(D7/$C$4*$B$4)/C7 -> 0.82754486 | G7: =+D7/B7-1 -> -0.24992327
A8: PEDIDOS | B8: 5363 | C8: =+C7/C9 -> 7230.0938 | D8: =K30 -> 4474 | E8: =+D8/C8 -> 0.61880249 | F8: =+(D8/$C$4*$B$4)/C8 -> 0.92820373 | G8: =+D8/B8-1 -> -0.16576543
A9: TICKET PROMEDIO | B9: =+B7/B8 -> 59495.207 | C9: 60000 | D9: =+D7/D8 -> 53493.312 | E9: =+D9/C9 -> 0.8915552 | F9: =+D9/C9 -> 0.8915552 | G9: =+D9/B9-1 -> -0.10088031
A10: CLIENTE | B10: 6500 | C10: 7000 | D10: 4039 | E10: =+D10/C10 -> 0.577 | F10: =+(D10/$C$4*$B$4)/C10 -> 0.8655 | G10: =+D10/B10-1 -> -0.37861538
A11: FRECUENCIA DE COMPRA | B11: =+B8/B10 -> 0.82507692 | C11: =+C8/C10 -> 1.0328705 | D11: =+D8/D10 -> 1.1076999 | E11: =+D11/C11 -> 1.072448 | F11: =+D11/C11 -> 1.072448 | G11: =+D11/B11-1 -> 0.3425414
A13: VENTAR TERCEROS | B13: 50045346 | C13: 130000000 | D13: 57720997 | E13: =+D13/C13 -> 0.44400767 | F13: =+(D13/$C$4*$B$4)/C13 -> 0.6660115 | G13: =+D13/B13-1 -> 0.15337392
A15: EJECUCIÓN MES REGIONAL
B17: VENDEDORES | C17: % VENTA | D17: % PEDIDOS | E17: VENTA MES | F17: VENTAS X VENDEDOR | G17: VENTA ACUMULADA MES | H17: % VENTA MES | I17: PEDIDOS MES | J17: PEDIDOS X VENDEDOR | K17: PEDIDOS ACUMULADOS MES | L17: % PEDIDOS MES | M17: TICKET PROMEDIO ACUMULADO
A18: BOGOTA | B18: 19 | C18: 0.33 | D18: 0.42 | E18: =+C18*$C$7 -> 1.4315586e+08 | F18: =+E18/B18 -> 7534518.8 | G18: =IFERROR(VLOOKUP(A18,'VENTAS DIARIAS'!A:B,2,0),0) -> 1.0471416e+08 | H18: =+G18/$G$30 -> 0.43753211 | I18: =+D18*$C$8 -> 3036.6394 | J18: =+I18/B18 -> 159.82312 | K18: =IFERROR(VLOOKUP(A18,'PEDIDOS POR VENDEDOR'!B:C,2,0),0) -> 1991 | L18: =+K18/$K$30 -> 0.44501565 | M18: =+G18/K18 -> 52593.751
A19: MEDELLIN | B19: 12 | C19: 0.23 | D19: 0.2 | E19: =+C19*$C$7 -> 99775294 | F19: =+E19/B19 -> 8314607.8 | G19: =IFERROR(VLOOKUP(A19,'VENTAS DIARIAS'!A:B,2,0),0) -> 39305972 | H19: =+G19/$G$30 -> 0.164234 | I19: =+D19*$C$8 -> 1446.0188 | J19: =+I19/B19 -> 120.50156 | K19: =IFERROR(VLOOKUP(A19,'PEDIDOS POR VENDEDOR'!B:C,2,0),0) -> 881 | L19: =+K19/$K$30 -> 0.19691551 | M19: =+G19/K19 -> 44615.178
A20: BARRANQUILLA | B20: 6 | C20: 0.085 | D20: 0.06 | E20: =+C20*$C$7 -> 36873478 | F20: =+E20/B20 -> 6145579.7 | G20: =IFERROR(VLOOKUP(A20,'VENTAS DIARIAS'!A:B,2,0),0) -> 8477446 | H20: =+G20/$G$30 -> 0.035421713 | I20: =+D20*$C$8 -> 433.80562 | J20: =+I20/B20 -> 72.300937 | K20: =IFERROR(VLOOKUP(A20,'PEDIDOS POR VENDEDOR'!B:C,2,0),0) -> 158 | L20: =+K20/$K$30 -> 0.035315154 | M20: =+G20/K20 -> 53654.721
A21: BUCARAMANGA | B21: 4 | C21: 0.045 | D21: 0.05 | E21: =+C21*$C$7 -> 19521253 | F21: =+E21/B21 -> 4880313.3 | G21: =IFERROR(VLOOKUP(A21,'VENTAS DIARIAS'!A:B,2,0),0) -> 5520242.7 | H21: =+G21/$G$30 -> 0.023065491 | I21: =+D21*$C$8 -> 361.50469 | J21: =+I21/B21 -> 90.376172 | K21: =IFERROR(VLOOKUP(A21,'PEDIDOS POR VENDEDOR'!B:C,2,0),0) -> 126 | L21: =+K21/$K$30 -> 0.028162718 | M21: =+G21/K21 -> 43811.45
A22: CUCUTA | B22: 3 | C22: 0.025 | D22: 0.03 | E22: =+C22*$C$7 -> 10845141 | F22: =+E22/B22 -> 3615046.9 | G22: =IFERROR(VLOOKUP(A22,'VENTAS DIARIAS'!A:B,2,0),0) -> 6133455 | H22: =+G22/$G$30 -> 0.025627705 | I22: =+D22*$C$8 -> 216.90281 | J22: =+I22/B22 -> 72.300937 | K22: =IFERROR(VLOOKUP(A22,'PEDIDOS POR VENDEDOR'!B:C,2,0),0) -> 237 | L22: =+K22/$K$30 -> 0.052972731 | M22: =+G22/K22 -> 25879.557
A23: VILLAVICENCIO | B23: 3 | C23: 0.11 | D23: 0.08 | E23: =+C23*$C$7 -> 47718619 | F23: =+E23/B23 -> 15906206 | G23: =IFERROR(VLOOKUP(A23,'VENTAS DIARIAS'!A:B,2,0),0) -> 42613562 | H23: =+G23/$G$30 -> 0.17805426 | I23: =+D23*$C$8 -> 578.4075 | J23: =+I23/B23 -> 192.8025 | K23: =IFERROR(VLOOKUP(A23,'PEDIDOS POR VENDEDOR'!B:C,2,0),0) -> 483 | L23: =+K23/$K$30 -> 0.10795709 | M23: =+G23/K23 -> 88226.837
A24: CALI | B24: 1 | C24: 0.02 | D24: 0.04 | E24: =+C24*$C$7 -> 8676112.5 | F24: =+E24/B24 -> 8676112.5 | G24: =IFERROR(VLOOKUP(A24,'VENTAS DIARIAS'!A:B,2,0),0) -> 3220678.5 | H24: =+G24/$G$30 -> 0.013457113 | I24: =+D24*$C$8 -> 289.20375 | J24: =+I24/B24 -> 289.20375 | K24: =IFERROR(VLOOKUP(A24,'PEDIDOS POR VENDEDOR'!B:C,2,0),0) -> 49 | L24: =+K24/$K$30 -> 0.010952168 | M24: =+G24/K24 -> 65728.134
A25: PEREIRA | B25: 2 | C25: 0.02 | D25: 0.02 | E25: =+C25*$C$7 -> 8676112.5 | F25: =+E25/B25 -> 4338056.2 | G25: =IFERROR(VLOOKUP(A25,'VENTAS DIARIAS'!A:B,2,0),0) -> 4385013.7 | H25: =+G25/$G$30 -> 0.01832211 | I25: =+D25*$C$8 -> 144.60188 | J25: =+I25/B25 -> 72.300938 | K25: =IFERROR(VLOOKUP(A25,'PEDIDOS POR VENDEDOR'!B:C,2,0),0) -> 69 | L25: =+K25/$K$30 -> 0.015422441 | M25: =+G25/K25 -> 63550.923
A26: CARTAGENA | B26: 2 | C26: 0.03 | D26: 0.03 | E26: =+C26*$C$7 -> 13014169 | F26: =+E26/B26 -> 6507084.4 | G26: =IFERROR(VLOOKUP(A26,'VENTAS DIARIAS'!A:B,2,0),0) -> 9518644.9 | H26: =+G26/$G$30 -> 0.039772204 | I26: =+D26*$C$8 -> 216.90281 | J26: =+I26/B26 -> 108.45141 | K26: =IFERROR(VLOOKUP(A26,'PEDIDOS POR VENDEDOR'!B:C,2,0),0) -> 165 | L26: =+K26/$K$30 -> 0.03687975 | M26: =+G26/K26 -> 57688.757
A27: VALLEDUPAR | B27: 2 | C27: 0.05 | D27: 0.05 | E27: =+C27*$C$7 -> 21690281 | F27: =+E27/B27 -> 10845141 | G27: =IFERROR(VLOOKUP(A27,'VENTAS DIARIAS'!A:B,2,0),0) -> 5841956.6 | H27: =+G27/$G$30 -> 0.024409724 | I27: =+D27*$C$8 -> 361.50469 | J27: =+I27/B27 -> 180.75234 | K27: =IFERROR(VLOOKUP(A27,'PEDIDOS POR VENDEDOR'!B:C,2,0),0) -> 143 | L27: =+K27/$K$30 -> 0.03196245 | M27: =+G27/K27 -> 40852.844
A28: MONTERIA | B28: 2 | C28: 0.035 | D28: 0.02 | E28: =+C28*$C$7 -> 15183197 | F28: =+E28/B28 -> 7591598.4 | G28: =IFERROR(VLOOKUP(A28,'VENTAS DIARIAS'!A:B,2,0),0) -> 9597948.8 | H28: =+G28/$G$30 -> 0.040103563 | I28: =+D28*$C$8 -> 144.60188 | J28: =+I28/B28 -> 72.300938 | K28: =IFERROR(VLOOKUP(A28,'PEDIDOS POR VENDEDOR'!B:C,2,0),0) -> 172 | L28: =+K28/$K$30 -> 0.038444345 | M28: =+G28/K28 -> 55802.028
A29: CLIENTE | B29: 0 | C29: 0.02 | D29: 0 | E29: =+C29*$C$7 -> 8676112.5 | G29: =IFERROR(VLOOKUP(A29,'VENTAS DIARIAS'!A:B,2,0),0) -> 0 | H29: =+G29/$G$30 -> 0 | I29: =+D29*$C$8 -> 0 | K29: =IFERROR(VLOOKUP(A29,'PEDIDOS POR VENDEDOR'!B:C,2,0),0) -> 0 | L29: =+K29/$K$30 -> 0 | M29: =+G29/K29 -> #DIV/0!
A30: TOTAL | B30: =SUM(B18:B29) -> 56 | C30: =SUM(C18:C29) -> 1 | D30: =SUM(D18:D29) -> 1 | E30: =SUM(E18:E29) -> 433805625 | F30: =SUM(F18:F29) -> 84354265 | G30: =SUM(G18:G29) -> 2.3932908e+08 | H30: =+G30/$G$30 -> 1 | I30: =+D30*$C$8 -> 7230.0938 | J30: =SUM(J18:J29) -> 1431.1146 | K30: =SUM(K18:K29) -> 4474 | L30: =+K30/$K$30 -> 1 | M30: =+G30/K30 -> 53493.312
B32: PROY VENTA MES | C32: % | D32: CUMPL PROY VENTA | E32: PEDIDOS MES | F32: %PEDIDOS | G32: CUMPL PEDIDOS | H32: TICKET PROMEDIO
A33: BOGOTA | B33: =+G18/$C$4*$B$4 -> 1.5707124e+08 | C33: =+B33/$B$45 -> 0.43753211 | D33: =+B33/E18 -> 1.0972044 | E33: =+K18/$C$4*$B$4 -> 2986.5 | F33: =+E33/$E$45 -> 0.44501565 | G33: =+E33/I18 -> 0.98348853 | H33: =+B33/E33 -> 52593.751
A34: MEDELLIN | B34: =+G19/$C$4*$B$4 -> 58958958 | C34: =+B34/$B$45 -> 0.164234 | D34: =+B34/E19 -> 0.59091741 | E34: =+K19/$C$4*$B$4 -> 1321.5 | F34: =+E34/$E$45 -> 0.19691551 | G34: =+E34/I19 -> 0.91388856 | H34: =+B34/E34 -> 44615.178
A35: BARRANQUILLA | B35: =+G20/$C$4*$B$4 -> 12716169 | C35: =+B35/$B$45 -> 0.035421713 | D35: =+B35/E20 -> 0.34485949 | E35: =+K20/$C$4*$B$4 -> 237 | F35: =+E35/$E$45 -> 0.035315154 | G35: =+E35/I20 -> 0.54632763 | H35: =+B35/E35 -> 53654.721
A36: BUCARAMANGA | B36: =+G21/$C$4*$B$4 -> 8280364 | C36: =+B36/$B$45 -> 0.023065491 | D36: =+B36/E21 -> 0.42417175 | E36: =+K21/$C$4*$B$4 -> 189 | F36: =+E36/$E$45 -> 0.028162718 | G36: =+E36/I21 -> 0.5228148 | H36: =+B36/E36 -> 43811.45
A37: CUCUTA | B37: =+G22/$C$4*$B$4 -> 9200182.5 | C37: =+B37/$B$45 -> 0.025627705 | D37: =+B37/E22 -> 0.84832302 | E37: =+K22/$C$4*$B$4 -> 355.5 | F37: =+E37/$E$45 -> 0.052972731 | G37: =+E37/I22 -> 1.6389829 | H37: =+B37/E37 -> 25879.557
A38: VILLAVICENCIO | B38: =+G23/$C$4*$B$4 -> 63920344 | C38: =+B38/$B$45 -> 0.17805426 | D38: =+B38/E23 -> 1.3395263 | E38: =+K23/$C$4*$B$4 -> 724.5 | F38: =+E38/$E$45 -> 0.10795709 | G38: =+E38/I23 -> 1.2525771 | H38: =+B38/E38 -> 88226.837
A39: CALI | B39: =+G24/$C$4*$B$4 -> 4831017.8 | C39: =+B39/$B$45 -> 0.013457113 | D39: =+B39/E24 -> 0.55681825 | E39: =+K24/$C$4*$B$4 -> 73.5 | F39: =+E39/$E$45 -> 0.010952168 | G39: =+E39/I24 -> 0.25414608 | H39: =+B39/E39 -> 65728.134
A40: PEREIRA | B40: =+G25/$C$4*$B$4 -> 6577520.5 | C40: =+B40/$B$45 -> 0.01832211 | D40: =+B40/E25 -> 0.7581184 | E40: =+K25/$C$4*$B$4 -> 103.5 | F40: =+E40/$E$45 -> 0.015422441 | G40: =+E40/I25 -> 0.71575835 | H40: =+B40/E40 -> 63550.923
A41: CARTAGENA | B41: =+G26/$C$4*$B$4 -> 14277967 | C41: =+B41/$B$45 -> 0.039772204 | D41: =+B41/E26 -> 1.0971094 | E41: =+K26/$C$4*$B$4 -> 247.5 | F41: =+E41/$E$45 -> 0.03687975 | G41: =+E41/I26 -> 1.141064 | H41: =+B41/E41 -> 57688.757
A42: VALLEDUPAR | B42: =+G27/$C$4*$B$4 -> 8762934.9 | C42: =+B42/$B$45 -> 0.024409724 | D42: =+B42/E27 -> 0.40400283 | E42: =+K27/$C$4*$B$4 -> 214.5 | F42: =+E42/$E$45 -> 0.03196245 | G42: =+E42/I27 -> 0.5933533 | H42: =+B42/E42 -> 40852.844
A43: MONTERIA | B43: =+G28/$C$4*$B$4 -> 14396923 | C43: =+B43/$B$45 -> 0.040103563 | D43: =+B43/E28 -> 0.94821422 | E43: =+K28/$C$4*$B$4 -> 258 | F43: =+E43/$E$45 -> 0.038444345 | G43: =+E43/I28 -> 1.7842092 | H43: =+B43/E43 -> 55802.028
A44: CLIENTE | B44: =+G29/$C$4*$B$4 -> 0 | C44: =+B44/$B$45 -> 0 | D44: =+B44/E29 -> 0 | E44: =+K29/$C$4*$B$4 -> 0 | F44: =+E44/$E$45 -> 0 | G44: =+E44/I29 -> #DIV/0! | H44: =+B44/E44 -> #DIV/0!
A45: TOTAL | B45: =SUM(B33:B44) -> 3.5899362e+08 | C45: =+B45/$B$45 -> 1 | D45: =+B45/E30 -> 0.82754486 | E45: =+K30/$C$4*$B$4 -> 6711 | F45: =SUM(F33:F44) -> 1 | G45: =+E45/I30 -> 0.92820373 | H45: =+B45/E45 -> 53493.312
A47: EJECUCIÓN MES X VENDEDOR
A49: ZONA | B49: REGIONAL | C49: VENDEDOR | D49: META PEDIDOS MES | E49: PEDIDOS ACUMULADOS MES | F49: VENTA ACUMULADA TUTI | G49: VENTA TERCEROS | H49: META TERCEROS | I49: PROYECCION TERCEROS | J49: PROY CUMPL META TERCERO | K49: PROY CUMPL PEDIDOS
A50: 107 | B50: MEDELLIN | C50: ELIANA GOMEZ 107 | D50: =$J$19 -> 120.50156 | E50: =IFERROR(VLOOKUP(A50,'PEDIDOS POR VENDEDOR'!D:E,2,0),0) -> 140 | F50: =IFERROR(VLOOKUP(A50,'VENTAS POR VENDEDOR'!A:B,2,0),0) -> 6018575.7 | G50: =IFERROR(VLOOKUP(A50,'VENTA TERCEROS'!A:B,2,0),0) -> 2368929.1 | H50: 5437609.5 | I50: =+(G50/$C$4)*$B$4 -> 3553393.6 | J50: =+((G50/$C$4)*$B$4)/H50 -> 0.65348452 | K50: =(+E50/$C$4*$B$4)/D50 -> 1.742716
A51: 102 | B51: MEDELLIN | C51: DUBY YARLENY BEDOYA FLOREZ 102 | D51: =$J$19 -> 120.50156 | E51: =IFERROR(VLOOKUP(A51,'PEDIDOS POR VENDEDOR'!D:E,2,0),0) -> 91 | F51: =IFERROR(VLOOKUP(A51,'VENTAS POR VENDEDOR'!A:B,2,0),0) -> 2488032.7 | G51: =IFERROR(VLOOKUP(A51,'VENTA TERCEROS'!A:B,2,0),0) -> 2196758.4 | H51: 4650685.2 | I51: =+(G51/$C$4)*$B$4 -> 3295137.6 | J51: =+((G51/$C$4)*$B$4)/H51 -> 0.70852734 | K51: =(+E51/$C$4*$B$4)/D51 -> 1.1327654
A52: 114 | B52: MEDELLIN | C52: MARIA ELENA JARAMILLO GALEANO 114 | D52: =$J$19 -> 120.50156 | E52: =IFERROR(VLOOKUP(A52,'PEDIDOS POR VENDEDOR'!D:E,2,0),0) -> 81 | F52: =IFERROR(VLOOKUP(A52,'VENTAS POR VENDEDOR'!A:B,2,0),0) -> 3095342.5 | G52: =IFERROR(VLOOKUP(A52,'VENTA TERCEROS'!A:B,2,0),0) -> 2319419.4 | H52: 4532572.4 | I52: =+(G52/$C$4)*$B$4 -> 3479129 | J52: =+((G52/$C$4)*$B$4)/H52 -> 0.76758377 | K52: =(+E52/$C$4*$B$4)/D52 -> 1.0082857
A53: 946 | B53: BOGOTA | C53: MONICA RODRIGUEZ RONCANCIO 946 | D53: =$J$18 -> 159.82312 | E53: =IFERROR(VLOOKUP(A53,'PEDIDOS POR VENDEDOR'!D:E,2,0),0) -> 124 | F53: =IFERROR(VLOOKUP(A53,'VENTAS POR VENDEDOR'!A:B,2,0),0) -> 4778620.4 | G53: =IFERROR(VLOOKUP(A53,'VENTA TERCEROS'!A:B,2,0),0) -> 2246930.3 | H53: 4005337.4 | I53: =+(G53/$C$4)*$B$4 -> 3370395.4 | J53: =+((G53/$C$4)*$B$4)/H53 -> 0.84147603 | K53: =(+E53/$C$4*$B$4)/D53 -> 1.1637865
A54: 945 | B54: BOGOTA | C54: CRISTINA QUINTERO RUDAS 945 | D54: =$J$18 -> 159.82312 | E54: =IFERROR(VLOOKUP(A54,'PEDIDOS POR VENDEDOR'!D:E,2,0),0) -> 93 | F54: =IFERROR(VLOOKUP(A54,'VENTAS POR VENDEDOR'!A:B,2,0),0) -> 4371388.1 | G54: =IFERROR(VLOOKUP(A54,'VENTA TERCEROS'!A:B,2,0),0) -> 1579810 | H54: 3849032.9 | I54: =+(G54/$C$4)*$B$4 -> 2369715 | J54: =+((G54/$C$4)*$B$4)/H54 -> 0.61566504 | K54: =(+E54/$C$4*$B$4)/D54 -> 0.8728399
A55: 103 | B55: MEDELLIN | C55: KATHERINE GAVIRIA MAZO 103 | D55: =$J$19 -> 120.50156 | E55: =IFERROR(VLOOKUP(A55,'PEDIDOS POR VENDEDOR'!D:E,2,0),0) -> 91 | F55: =IFERROR(VLOOKUP(A55,'VENTAS POR VENDEDOR'!A:B,2,0),0) -> 2817486.2 | G55: =IFERROR(VLOOKUP(A55,'VENTA TERCEROS'!A:B,2,0),0) -> 2353365.8 | H55: 3715605.5 | I55: =+(G55/$C$4)*$B$4 -> 3530048.7 | J55: =+((G55/$C$4)*$B$4)/H55 -> 0.95006014 | K55: =(+E55/$C$4*$B$4)/D55 -> 1.1327654
A56: 921 | B56: BOGOTA | C56: LEYDY YURLEY MUNEVAR ESPITIA 921 | D56: =$J$18 -> 159.82312 | E56: =IFERROR(VLOOKUP(A56,'PEDIDOS POR VENDEDOR'!D:E,2,0),0) -> 123 | F56: =IFERROR(VLOOKUP(A56,'VENTAS POR VENDEDOR'!A:B,2,0),0) -> 8070896.2 | G56: =IFERROR(VLOOKUP(A56,'VENTA TERCEROS'!A:B,2,0),0) -> 1341659.3 | H56: 3575652 | I56: =+(G56/$C$4)*$B$4 -> 2012489 | J56: =+((G56/$C$4)*$B$4)/H56 -> 0.56283134 | K56: =(+E56/$C$4*$B$4)/D56 -> 1.1544012
A57: 923 | B57: BOGOTA | C57: WILSON JAVIER MONTAÑEZ MARTINEZ 923 | D57: =$J$18 -> 159.82312 | E57: =IFERROR(VLOOKUP(A57,'PEDIDOS POR VENDEDOR'!D:E,2,0),0) -> 166 | F57: =IFERROR(VLOOKUP(A57,'VENTAS POR VENDEDOR'!A:B,2,0),0) -> 3862899.1 | G57: =IFERROR(VLOOKUP(A57,'VENTA TERCEROS'!A:B,2,0),0) -> 1162815.4 | H57: 3226138.5 | I57: =+(G57/$C$4)*$B$4 -> 1744223.1 | J57: =+((G57/$C$4)*$B$4)/H57 -> 0.5406535 | K57: =(+E57/$C$4*$B$4)/D57 -> 1.5579723
A58: 111 | B58: MEDELLIN | C58: INES LILIANA PIEDRAHITA MESA 111 | D58: =$J$19 -> 120.50156 | E58: =IFERROR(VLOOKUP(A58,'PEDIDOS POR VENDEDOR'!D:E,2,0),0) -> 68 | F58: =IFERROR(VLOOKUP(A58,'VENTAS POR VENDEDOR'!A:B,2,0),0) -> 4359844.1 | G58: =IFERROR(VLOOKUP(A58,'VENTA TERCEROS'!A:B,2,0),0) -> 1123178 | H58: 3200578.6 | I58: =+(G58/$C$4)*$B$4 -> 1684767 | J58: =+((G58/$C$4)*$B$4)/H58 -> 0.52639453 | K58: =(+E58/$C$4*$B$4)/D58 -> 0.84646205
A59: 926 | B59: BOGOTA | C59: LEONARDO MANCERA BOLAÑOS 926 | D59: =$J$18 -> 159.82312 | E59: =IFERROR(VLOOKUP(A59,'PEDIDOS POR VENDEDOR'!D:E,2,0),0) -> 127 | F59: =IFERROR(VLOOKUP(A59,'VENTAS POR VENDEDOR'!A:B,2,0),0) -> 3868638.4 | G59: =IFERROR(VLOOKUP(A59,'VENTA TERCEROS'!A:B,2,0),0) -> 1063249.4 | H59: 3177199.9 | I59: =+(G59/$C$4)*$B$4 -> 1594874.1 | J59: =+((G59/$C$4)*$B$4)/H59 -> 0.50197475 | K59: =(+E59/$C$4*$B$4)/D59 -> 1.1919427
A60: 938 | B60: BOGOTA | C60: DIANA MARCELA DIAZ TORRES 938 | D60: =$J$18 -> 159.82312 | E60: =IFERROR(VLOOKUP(A60,'PEDIDOS POR VENDEDOR'!D:E,2,0),0) -> 114 | F60: =IFERROR(VLOOKUP(A60,'VENTAS POR VENDEDOR'!A:B,2,0),0) -> 9798757.6 | G60: =IFERROR(VLOOKUP(A60,'VENTA TERCEROS'!A:B,2,0),0) -> 1528232.7 | H60: 3112949.7 | I60: =+(G60/$C$4)*$B$4 -> 2292349.1 | J60: =+((G60/$C$4)*$B$4)/H60 -> 0.73639132 | K60: =(+E60/$C$4*$B$4)/D60 -> 1.0699328
A61: 104 | B61: MEDELLIN | C61: ANDRES GRACIANO SERNA 104 | D61: =$J$19 -> 120.50156 | E61: =IFERROR(VLOOKUP(A61,'PEDIDOS POR VENDEDOR'!D:E,2,0),0) -> 139 | F61: =IFERROR(VLOOKUP(A61,'VENTAS POR VENDEDOR'!A:B,2,0),0) -> 12603370 | G61: =IFERROR(VLOOKUP(A61,'VENTA TERCEROS'!A:B,2,0),0) -> 1157973.4 | H61: 3036903.2 | I61: =+(G61/$C$4)*$B$4 -> 1736960.2 | J61: =+((G61/$C$4)*$B$4)/H61 -> 0.57195111 | K61: =(+E61/$C$4*$B$4)/D61 -> 1.730268
A62: 117 | B62: MEDELLIN | C62: GEORLAN GARCIA PANIAGUA 117 | D62: =$J$19 -> 120.50156 | E62: =IFERROR(VLOOKUP(A62,'PEDIDOS POR VENDEDOR'!D:E,2,0),0) -> 75 | F62: =IFERROR(VLOOKUP(A62,'VENTAS POR VENDEDOR'!A:B,2,0),0) -> 2007332.3 | G62: =IFERROR(VLOOKUP(A62,'VENTA TERCEROS'!A:B,2,0),0) -> 1407771.9 | H62: 3021662.7 | I62: =+(G62/$C$4)*$B$4 -> 2111657.8 | J62: =+((G62/$C$4)*$B$4)/H62 -> 0.69883969 | K62: =(+E62/$C$4*$B$4)/D62 -> 0.93359785
A63: 935 | B63: BOGOTA | C63: NELLY MARTINEZ FLEREZ 935 | D63: =$J$18 -> 159.82312 | E63: =IFERROR(VLOOKUP(A63,'PEDIDOS POR VENDEDOR'!D:E,2,0),0) -> 80 | F63: =IFERROR(VLOOKUP(A63,'VENTAS POR VENDEDOR'!A:B,2,0),0) -> 3984516.3 | G63: =IFERROR(VLOOKUP(A63,'VENTA TERCEROS'!A:B,2,0),0) -> 1369554.9 | H63: 3000993.6 | I63: =+(G63/$C$4)*$B$4 -> 2054332.3 | J63: =+((G63/$C$4)*$B$4)/H63 -> 0.6845507 | K63: =(+E63/$C$4*$B$4)/D63 -> 0.75083002
A64: 113 | B64: MEDELLIN | C64: MIGUEL ANGEL HIDALGO SANTOS 113 | D64: =$J$19 -> 120.50156 | E64: =IFERROR(VLOOKUP(A64,'PEDIDOS POR VENDEDOR'!D:E,2,0),0) -> 58 | F64: =IFERROR(VLOOKUP(A64,'VENTAS POR VENDEDOR'!A:B,2,0),0) -> 1530633.1 | G64: =IFERROR(VLOOKUP(A64,'VENTA TERCEROS'!A:B,2,0),0) -> 1107858.1 | H64: 2933132.9 | I64: =+(G64/$C$4)*$B$4 -> 1661787.2 | J64: =+((G64/$C$4)*$B$4)/H64 -> 0.56655706 | K64: =(+E64/$C$4*$B$4)/D64 -> 0.72198234
A65: 937 | B65: BOGOTA | C65: MARIA NANCY GUARIN VIRGUEZ 937 | D65: =$J$18 -> 159.82312 | E65: =IFERROR(VLOOKUP(A65,'PEDIDOS POR VENDEDOR'!D:E,2,0),0) -> 102 | F65: =IFERROR(VLOOKUP(A65,'VENTAS POR VENDEDOR'!A:B,2,0),0) -> 6210722.6 | G65: =IFERROR(VLOOKUP(A65,'VENTA TERCEROS'!A:B,2,0),0) -> 1182081.8 | H65: 2861022.4 | I65: =+(G65/$C$4)*$B$4 -> 1773122.6 | J65: =+((G65/$C$4)*$B$4)/H65 -> 0.6197514 | K65: =(+E65/$C$4*$B$4)/D65 -> 0.95730827
A66: 110 | B66: MEDELLIN | C66: HEYLER QUINTO 110 | D66: =$J$19 -> 120.50156 | E66: =IFERROR(VLOOKUP(A66,'PEDIDOS POR VENDEDOR'!D:E,2,0),0) -> 1 | F66: =IFERROR(VLOOKUP(A66,'VENTAS POR VENDEDOR'!A:B,2,0),0) -> 31932.916 | G66: =IFERROR(VLOOKUP(A66,'VENTA TERCEROS'!A:B,2,0),0) -> 1481362.1 | H66: 2671994.8 | I66: =+(G66/$C$4)*$B$4 -> 2222043.1 | J66: =+((G66/$C$4)*$B$4)/H66 -> 0.83160456 | K66: =(+E66/$C$4*$B$4)/D66 -> 0.012447971
A67: 105 | B67: MEDELLIN | C67: SEBASTIAN DIAZ VELEZ 105 | D67: =$J$19 -> 120.50156 | E67: =IFERROR(VLOOKUP(A67,'PEDIDOS POR VENDEDOR'!D:E,2,0),0) -> 63 | F67: =IFERROR(VLOOKUP(A67,'VENTAS POR VENDEDOR'!A:B,2,0),0) -> 1956639.5 | G67: =IFERROR(VLOOKUP(A67,'VENTA TERCEROS'!A:B,2,0),0) -> 1222388.4 | H67: 2630172.3 | I67: =+(G67/$C$4)*$B$4 -> 1833582.6 | J67: =+((G67/$C$4)*$B$4)/H67 -> 0.69713402 | K67: =(+E67/$C$4*$B$4)/D67 -> 0.7842222
A68: 907 | B68: BOGOTA | C68: SOL KATHERINE BERNAL MONTANO 907 | D68: =$J$18 -> 159.82312 | E68: =IFERROR(VLOOKUP(A68,'PEDIDOS POR VENDEDOR'!D:E,2,0),0) -> 91 | F68: =IFERROR(VLOOKUP(A68,'VENTAS POR VENDEDOR'!A:B,2,0),0) -> 4901449.5 | G68: =IFERROR(VLOOKUP(A68,'VENTA TERCEROS'!A:B,2,0),0) -> 1179323.7 | H68: 2594013.9 | I68: =+(G68/$C$4)*$B$4 -> 1768985.5 | J68: =+((G68/$C$4)*$B$4)/H68 -> 0.68194915 | K68: =(+E68/$C$4*$B$4)/D68 -> 0.85406915
A69: 918 | B69: BOGOTA | C69: MARIBEL REDONDO 918 | D69: =$J$18 -> 159.82312 | E69: =IFERROR(VLOOKUP(A69,'PEDIDOS POR VENDEDOR'!D:E,2,0),0) -> 113 | F69: =IFERROR(VLOOKUP(A69,'VENTAS POR VENDEDOR'!A:B,2,0),0) -> 6197383.5 | G69: =IFERROR(VLOOKUP(A69,'VENTA TERCEROS'!A:B,2,0),0) -> 1052181.5 | H69: 2547142.6 | I69: =+(G69/$C$4)*$B$4 -> 1578272.3 | J69: =+((G69/$C$4)*$B$4)/H69 -> 0.61962462 | K69: =(+E69/$C$4*$B$4)/D69 -> 1.0605474
A70: 919 | B70: BOGOTA | C70: SANDRA PATRICIA ORTIZ ROMERO 919 | D70: =$J$18 -> 159.82312 | E70: =IFERROR(VLOOKUP(A70,'PEDIDOS POR VENDEDOR'!D:E,2,0),0) -> 177 | F70: =IFERROR(VLOOKUP(A70,'VENTAS POR VENDEDOR'!A:B,2,0),0) -> 7546272.6 | G70: =IFERROR(VLOOKUP(A70,'VENTA TERCEROS'!A:B,2,0),0) -> 928384.54 | H70: 2546195.6 | I70: =+(G70/$C$4)*$B$4 -> 1392576.8 | J70: =+((G70/$C$4)*$B$4)/H70 -> 0.54692452 | K70: =(+E70/$C$4*$B$4)/D70 -> 1.6612114
A71: 908 | B71: BOGOTA | C71: ANGIE JOHANA BEDOYA HERRENO 908 | D71: =$J$18 -> 159.82312 | E71: =IFERROR(VLOOKUP(A71,'PEDIDOS POR VENDEDOR'!D:E,2,0),0) -> 111 | F71: =IFERROR(VLOOKUP(A71,'VENTAS POR VENDEDOR'!A:B,2,0),0) -> 4165341.7 | G71: =IFERROR(VLOOKUP(A71,'VENTA TERCEROS'!A:B,2,0),0) -> 885002.5 | H71: 2531578.1 | I71: =+(G71/$C$4)*$B$4 -> 1327503.8 | J71: =+((G71/$C$4)*$B$4)/H71 -> 0.52437795 | K71: =(+E71/$C$4*$B$4)/D71 -> 1.0417767
A72: 920 | B72: BOGOTA | C72: WILLIAM ALBERTO VELASQUEZ BERNAL 920 | D72: =$J$18 -> 159.82312 | E72: =IFERROR(VLOOKUP(A72,'PEDIDOS POR VENDEDOR'!D:E,2,0),0) -> 99 | F72: =IFERROR(VLOOKUP(A72,'VENTAS POR VENDEDOR'!A:B,2,0),0) -> 5429817.8 | G72: =IFERROR(VLOOKUP(A72,'VENTA TERCEROS'!A:B,2,0),0) -> 643960.92 | H72: 2530374.2 | I72: =+(G72/$C$4)*$B$4 -> 965941.37 | J72: =+((G72/$C$4)*$B$4)/H72 -> 0.38173856 | K72: =(+E72/$C$4*$B$4)/D72 -> 0.92915215
A73: 911 | B73: BOGOTA | C73: MARISOL NEIRA PARRA 911 | D73: =$J$18 -> 159.82312 | E73: =IFERROR(VLOOKUP(A73,'PEDIDOS POR VENDEDOR'!D:E,2,0),0) -> 109 | F73: =IFERROR(VLOOKUP(A73,'VENTAS POR VENDEDOR'!A:B,2,0),0) -> 4741012.1 | G73: =IFERROR(VLOOKUP(A73,'VENTA TERCEROS'!A:B,2,0),0) -> 1261159.3 | H73: 2225173.8 | I73: =+(G73/$C$4)*$B$4 -> 1891739 | J73: =+((G73/$C$4)*$B$4)/H73 -> 0.85015337 | K73: =(+E73/$C$4*$B$4)/D73 -> 1.0230059
A74: 933 | B74: BOGOTA | C74: NAIR JAEL VARGAS TALERO 933 | D74: =$J$18 -> 159.82312 | E74: =IFERROR(VLOOKUP(A74,'PEDIDOS POR VENDEDOR'!D:E,2,0),0) -> 45 | F74: =IFERROR(VLOOKUP(A74,'VENTAS POR VENDEDOR'!A:B,2,0),0) -> 3817560 | G74: =IFERROR(VLOOKUP(A74,'VENTA TERCEROS'!A:B,2,0),0) -> 1106295.3 | H74: 2200366.5 | I74: =+(G74/$C$4)*$B$4 -> 1659443 | J74: =+((G74/$C$4)*$B$4)/H74 -> 0.75416664 | K74: =(+E74/$C$4*$B$4)/D74 -> 0.42234189
A75: 115 | B75: MEDELLIN | C75: INGRID RESTREPO 115 | D75: =$J$19 -> 120.50156 | E75: =IFERROR(VLOOKUP(A75,'PEDIDOS POR VENDEDOR'!D:E,2,0),0) -> 44 | F75: =IFERROR(VLOOKUP(A75,'VENTAS POR VENDEDOR'!A:B,2,0),0) -> 1435139.7 | G75: =IFERROR(VLOOKUP(A75,'VENTA TERCEROS'!A:B,2,0),0) -> 918062.58 | H75: 2165594 | I75: =+(G75/$C$4)*$B$4 -> 1377093.9 | J75: =+((G75/$C$4)*$B$4)/H75 -> 0.63589662 | K75: =(+E75/$C$4*$B$4)/D75 -> 0.54771074
A76: 409 | B76: CUCUTA | C76: FREDY ESTEPA 409 CUCUTA | D76: =$J$22 -> 72.300937 | E76: =IFERROR(VLOOKUP(A76,'PEDIDOS POR VENDEDOR'!D:E,2,0),0) -> 89 | F76: =IFERROR(VLOOKUP(A76,'VENTAS POR VENDEDOR'!A:B,2,0),0) -> 2178276.7 | G76: =IFERROR(VLOOKUP(A76,'VENTA TERCEROS'!A:B,2,0),0) -> 1716266.4 | H76: 2111505.8 | I76: =+(G76/$C$4)*$B$4 -> 2574399.5 | J76: =+((G76/$C$4)*$B$4)/H76 -> 1.2192245 | K76: =(+E76/$C$4*$B$4)/D76 -> 1.8464491
A77: 932 | B77: BOGOTA | C77: OSCAR GIOVANNY NASAYO BLANCO 932 | D77: =$J$18 -> 159.82312 | E77: =IFERROR(VLOOKUP(A77,'PEDIDOS POR VENDEDOR'!D:E,2,0),0) -> 62 | F77: =IFERROR(VLOOKUP(A77,'VENTAS POR VENDEDOR'!A:B,2,0),0) -> 3604268.7 | G77: =IFERROR(VLOOKUP(A77,'VENTA TERCEROS'!A:B,2,0),0) -> 779942.33 | H77: 1972638.1 | I77: =+(G77/$C$4)*$B$4 -> 1169913.5 | J77: =+((G77/$C$4)*$B$4)/H77 -> 0.59307053 | K77: =(+E77/$C$4*$B$4)/D77 -> 0.58189326
A78: 925 | B78: BOGOTA | C78: LAURA SERNA HERNANDEZ 925 | D78: =$J$18 -> 159.82312 | E78: =IFERROR(VLOOKUP(A78,'PEDIDOS POR VENDEDOR'!D:E,2,0),0) -> 67 | F78: =IFERROR(VLOOKUP(A78,'VENTAS POR VENDEDOR'!A:B,2,0),0) -> 4762538.4 | G78: =IFERROR(VLOOKUP(A78,'VENTA TERCEROS'!A:B,2,0),0) -> 1001562.1 | H78: 1960977.8 | I78: =+(G78/$C$4)*$B$4 -> 1502343.1 | J78: =+((G78/$C$4)*$B$4)/H78 -> 0.76611937 | K78: =(+E78/$C$4*$B$4)/D78 -> 0.62882014
A79: 405 | B79: BUCARAMANGA | C79: SANDRA PRADA 405 BUCARAMANGA | D79: =$J$21 -> 90.376172 | E79: =IFERROR(VLOOKUP(A79,'PEDIDOS POR VENDEDOR'!D:E,2,0),0) -> 65 | F79: =IFERROR(VLOOKUP(A79,'VENTAS POR VENDEDOR'!A:B,2,0),0) -> 4038565.1 | G79: =IFERROR(VLOOKUP(A79,'VENTA TERCEROS'!A:B,2,0),0) -> 1066790.1 | H79: 1871646.9 | I79: =+(G79/$C$4)*$B$4 -> 1600185.1 | J79: =+((G79/$C$4)*$B$4)/H79 -> 0.85496103 | K79: =(+E79/$C$4*$B$4)/D79 -> 1.0788242
A80: 407 | B80: BUCARAMANGA | C80: YOHAN PITA 407 BUCARAMANGA | D80: =$J$21 -> 90.376172 | E80: =IFERROR(VLOOKUP(A80,'PEDIDOS POR VENDEDOR'!D:E,2,0),0) -> 29 | F80: =IFERROR(VLOOKUP(A80,'VENTAS POR VENDEDOR'!A:B,2,0),0) -> 502589.25 | G80: =IFERROR(VLOOKUP(A80,'VENTA TERCEROS'!A:B,2,0),0) -> 388588.08 | H80: 1826205 | I80: =+(G80/$C$4)*$B$4 -> 582882.12 | J80: =+((G80/$C$4)*$B$4)/H80 -> 0.31917671 | K80: =(+E80/$C$4*$B$4)/D80 -> 0.48132156
A81: 936 | B81: BOGOTA | C81: YULIETH HERNANDEZ | D81: =$J$18 -> 159.82312 | E81: =IFERROR(VLOOKUP(A81,'PEDIDOS POR VENDEDOR'!D:E,2,0),0) -> 133 | F81: =IFERROR(VLOOKUP(A81,'VENTAS POR VENDEDOR'!A:B,2,0),0) -> 11959979 | G81: =IFERROR(VLOOKUP(A81,'VENTA TERCEROS'!A:B,2,0),0) -> 1136533 | H81: 1792964.2 | I81: =+(G81/$C$4)*$B$4 -> 1704799.4 | J81: =+((G81/$C$4)*$B$4)/H81 -> 0.95082735 | K81: =(+E81/$C$4*$B$4)/D81 -> 1.2482549
A82: 411 | B82: CUCUTA | C82: MAIRA TORRES 411 CUCUTA | D82: =$J$22 -> 72.300937 | E82: =IFERROR(VLOOKUP(A82,'PEDIDOS POR VENDEDOR'!D:E,2,0),0) -> 72 | F82: =IFERROR(VLOOKUP(A82,'VENTAS POR VENDEDOR'!A:B,2,0),0) -> 1634397.4 | G82: =IFERROR(VLOOKUP(A82,'VENTA TERCEROS'!A:B,2,0),0) -> 1442799.9 | H82: 1769869.7 | I82: =+(G82/$C$4)*$B$4 -> 2164199.8 | J82: =+((G82/$C$4)*$B$4)/H82 -> 1.2228018 | K82: =(+E82/$C$4*$B$4)/D82 -> 1.4937566
A83: 605 | B83: PEREIRA | C83: FELIPE ARENAS 605 | D83: =$J$25 -> 72.300938 | E83: =IFERROR(VLOOKUP(A83,'PEDIDOS POR VENDEDOR'!D:E,2,0),0) -> 55 | F83: =IFERROR(VLOOKUP(A83,'VENTAS POR VENDEDOR'!A:B,2,0),0) -> 3099083.7 | G83: =IFERROR(VLOOKUP(A83,'VENTA TERCEROS'!A:B,2,0),0) -> 907600.22 | H83: 1736414.2 | I83: =+(G83/$C$4)*$B$4 -> 1361400.3 | J83: =+((G83/$C$4)*$B$4)/H83 -> 0.7840297 | K83: =(+E83/$C$4*$B$4)/D83 -> 1.141064
A84: 706 | B84: VALLEDUPAR | C84: LILIANA MARCELA GONZALEZ PLATA 706 VALLEDUPAR | D84: =$J$27 -> 180.75234 | E84: =IFERROR(VLOOKUP(A84,'PEDIDOS POR VENDEDOR'!D:E,2,0),0) -> 46 | F84: =IFERROR(VLOOKUP(A84,'VENTAS POR VENDEDOR'!A:B,2,0),0) -> 1533863.6 | G84: =IFERROR(VLOOKUP(A84,'VENTA TERCEROS'!A:B,2,0),0) -> 567065.83 | H84: 1653580.1 | I84: =+(G84/$C$4)*$B$4 -> 850598.74 | J84: =+((G84/$C$4)*$B$4)/H84 -> 0.51439827 | K84: =(+E84/$C$4*$B$4)/D84 -> 0.38173779
A85: 713 | B85: BARRANQUILLA | C85: YOANY SARMIENTO PEREZ 713 BARRANQUILLA | D85: =$J$20 -> 72.300937 | E85: =IFERROR(VLOOKUP(A85,'PEDIDOS POR VENDEDOR'!D:E,2,0),0) -> 46 | F85: =IFERROR(VLOOKUP(A85,'VENTAS POR VENDEDOR'!A:B,2,0),0) -> 3478628.1 | G85: =IFERROR(VLOOKUP(A85,'VENTA TERCEROS'!A:B,2,0),0) -> 645822.67 | H85: 1652608.1 | I85: =+(G85/$C$4)*$B$4 -> 968734.01 | J85: =+((G85/$C$4)*$B$4)/H85 -> 0.58618496 | K85: =(+E85/$C$4*$B$4)/D85 -> 0.95434447
A86: 116 | B86: MEDELLIN | C86: EDISON ALBERTO SALAZAR YEPES 116 | D86: =$J$19 -> 120.50156 | E86: =IFERROR(VLOOKUP(A86,'PEDIDOS POR VENDEDOR'!D:E,2,0),0) -> 32 | F86: =IFERROR(VLOOKUP(A86,'VENTAS POR VENDEDOR'!A:B,2,0),0) -> 961643.3 | G86: =IFERROR(VLOOKUP(A86,'VENTA TERCEROS'!A:B,2,0),0) -> 381605.35 | H86: 1517087.7 | I86: =+(G86/$C$4)*$B$4 -> 572408.02 | J86: =+((G86/$C$4)*$B$4)/H86 -> 0.37730715 | K86: =(+E86/$C$4*$B$4)/D86 -> 0.39833508
A87: 906 | B87: VILLAVICENCIO | C87: JHONTAN MENDOZA 906 | D87: =$J$23 -> 192.8025 | E87: =IFERROR(VLOOKUP(A87,'PEDIDOS POR VENDEDOR'!D:E,2,0),0) -> 176 | F87: =IFERROR(VLOOKUP(A87,'VENTAS POR VENDEDOR'!A:B,2,0),0) -> 12734664 | G87: =IFERROR(VLOOKUP(A87,'VENTA TERCEROS'!A:B,2,0),0) -> 232396.8 | H87: 1500000 | I87: =+(G87/$C$4)*$B$4 -> 348595.2 | J87: =+((G87/$C$4)*$B$4)/H87 -> 0.2323968 | K87: =(+E87/$C$4*$B$4)/D87 -> 1.3692769
A88: 715 | B88: BARRANQUILLA | C88: ALVARO ENRIQUE CASTAÑEDA MANJARRES 715 BARRANQUILLA | D88: =$J$20 -> 72.300937 | E88: =IFERROR(VLOOKUP(A88,'PEDIDOS POR VENDEDOR'!D:E,2,0),0) -> 25 | F88: =IFERROR(VLOOKUP(A88,'VENTAS POR VENDEDOR'!A:B,2,0),0) -> 1409284.6 | G88: =IFERROR(VLOOKUP(A88,'VENTA TERCEROS'!A:B,2,0),0) -> 596298.43 | H88: 1500000 | I88: =+(G88/$C$4)*$B$4 -> 894447.64 | J88: =+((G88/$C$4)*$B$4)/H88 -> 0.59629843 | K88: =(+E88/$C$4*$B$4)/D88 -> 0.51866547
A89: 410 | B89: BUCARAMANGA | C89: CAROLINA RUEDA 410 BUCARAMANGA | D89: =$J$21 -> 90.376172 | E89: =IFERROR(VLOOKUP(A89,'PEDIDOS POR VENDEDOR'!D:E,2,0),0) -> 27 | F89: =IFERROR(VLOOKUP(A89,'VENTAS POR VENDEDOR'!A:B,2,0),0) -> 738601.95 | G89: =IFERROR(VLOOKUP(A89,'VENTA TERCEROS'!A:B,2,0),0) -> 451114.39 | H89: 1500000 | I89: =+(G89/$C$4)*$B$4 -> 676671.59 | J89: =+((G89/$C$4)*$B$4)/H89 -> 0.45111439 | K89: =(+E89/$C$4*$B$4)/D89 -> 0.44812697
A90: 720 | B90: BARRANQUILLA | C90: MARIELA ESTER DE LEON 720 BARRANQUILLA | D90: =$J$20 -> 72.300937 | E90: =IFERROR(VLOOKUP(A90,'PEDIDOS POR VENDEDOR'!D:E,2,0),0) -> 64 | F90: =IFERROR(VLOOKUP(A90,'VENTAS POR VENDEDOR'!A:B,2,0),0) -> 1783119.8 | G90: =IFERROR(VLOOKUP(A90,'VENTA TERCEROS'!A:B,2,0),0) -> 205767.35 | H90: 1500000 | I90: =+(G90/$C$4)*$B$4 -> 308651.03 | J90: =+((G90/$C$4)*$B$4)/H90 -> 0.20576735 | K90: =(+E90/$C$4*$B$4)/D90 -> 1.3277836
A91: 620 | B91: CALI | C91: GERALDINE MEZA VALENCIA 620 | D91: =$J$20 -> 72.300937 | E91: =IFERROR(VLOOKUP(A91,'PEDIDOS POR VENDEDOR'!D:E,2,0),0) -> 48 | F91: =IFERROR(VLOOKUP(A91,'VENTAS POR VENDEDOR'!A:B,2,0),0) -> 3193955.9 | G91: =IFERROR(VLOOKUP(A91,'VENTA TERCEROS'!A:B,2,0),0) -> 1186491.4 | H91: 1500000 | I91: =+(G91/$C$4)*$B$4 -> 1779737 | J91: =+((G91/$C$4)*$B$4)/H91 -> 1.1864914 | K91: =(+E91/$C$4*$B$4)/D91 -> 0.99583771
A92: 415 | B92: BUCARAMANGA | C92: IVONNE RAMIREZ 415 BUCARAMANGA | D92: =$J$21 -> 90.376172 | E92: =IFERROR(VLOOKUP(A92,'PEDIDOS POR VENDEDOR'!D:E,2,0),0) -> 9 | F92: =IFERROR(VLOOKUP(A92,'VENTAS POR VENDEDOR'!A:B,2,0),0) -> 240486.4 | G92: =IFERROR(VLOOKUP(A92,'VENTA TERCEROS'!A:B,2,0),0) -> 119783.71 | H92: 1500000 | I92: =+(G92/$C$4)*$B$4 -> 179675.57 | J92: =+((G92/$C$4)*$B$4)/H92 -> 0.11978371 | K92: =(+E92/$C$4*$B$4)/D92 -> 0.14937566
A93: 964 | B93: VILLAVICENCIO | C93: JHON GRANADOS | D93: =$J$26 -> 108.45141 | E93: =IFERROR(VLOOKUP(A93,'PEDIDOS POR VENDEDOR'!D:E,2,0),0) -> 143 | F93: =IFERROR(VLOOKUP(A93,'VENTAS POR VENDEDOR'!A:B,2,0),0) -> 12882190 | G93: =IFERROR(VLOOKUP(A93,'VENTA TERCEROS'!A:B,2,0),0) -> 259924.96 | H93: 1500000 | I93: =+(G93/$C$4)*$B$4 -> 389887.44 | J93: =+((G93/$C$4)*$B$4)/H93 -> 0.25992496 | K93: =(+E93/$C$4*$B$4)/D93 -> 1.9778443
A94: 712 | B94: BARRANQUILLA | C94: STHEFANY OJITO BARRANQUILLA 712 | D94: =$J$20 -> 72.300937 | E94: =IFERROR(VLOOKUP(A94,'PEDIDOS POR VENDEDOR'!D:E,2,0),0) -> 12 | F94: =IFERROR(VLOOKUP(A94,'VENTAS POR VENDEDOR'!A:B,2,0),0) -> 1453608.7 | G94: =IFERROR(VLOOKUP(A94,'VENTA TERCEROS'!A:B,2,0),0) -> 14117.66 | H94: 1500000 | I94: =+(G94/$C$4)*$B$4 -> 21176.49 | J94: =+((G94/$C$4)*$B$4)/H94 -> 0.01411766 | K94: =(+E94/$C$4*$B$4)/D94 -> 0.24895943
A95: 714 | B95: BARRANQUILLA | C95: JESUS ENRIQUE GIRALDO SOTO 714 BARRANQUILLA | D95: =$J$20 -> 72.300937 | E95: =IFERROR(VLOOKUP(A95,'PEDIDOS POR VENDEDOR'!D:E,2,0),0) -> 10 | F95: =IFERROR(VLOOKUP(A95,'VENTAS POR VENDEDOR'!A:B,2,0),0) -> 319329.17 | G95: =IFERROR(VLOOKUP(A95,'VENTA TERCEROS'!A:B,2,0),0) -> 301902.3 | H95: 1500000 | I95: =+(G95/$C$4)*$B$4 -> 452853.45 | J95: =+((G95/$C$4)*$B$4)/H95 -> 0.3019023 | K95: =(+E95/$C$4*$B$4)/D95 -> 0.20746619
A96: 413 | B96: CUCUTA | C96: ZULY RANGEL GARCIA 413 CUCUTA | D96: =$J$22 -> 72.300937 | E96: =IFERROR(VLOOKUP(A96,'PEDIDOS POR VENDEDOR'!D:E,2,0),0) -> 76 | F96: =IFERROR(VLOOKUP(A96,'VENTAS POR VENDEDOR'!A:B,2,0),0) -> 2320780.9 | G96: =IFERROR(VLOOKUP(A96,'VENTA TERCEROS'!A:B,2,0),0) -> 499129.96 | H96: 1500000 | I96: =+(G96/$C$4)*$B$4 -> 748694.94 | J96: =+((G96/$C$4)*$B$4)/H96 -> 0.49912996 | K96: =(+E96/$C$4*$B$4)/D96 -> 1.576743
A97: 612 | B97: PEREIRA | C97: LEONARDO RIOS HENAO 612 | D97: =$J$25 -> 72.300938 | E97: =IFERROR(VLOOKUP(A97,'PEDIDOS POR VENDEDOR'!D:E,2,0),0) -> 42 | F97: =IFERROR(VLOOKUP(A97,'VENTAS POR VENDEDOR'!A:B,2,0),0) -> 2893673.2 | G97: =IFERROR(VLOOKUP(A97,'VENTA TERCEROS'!A:B,2,0),0) -> 733418.26 | H97: 1500000 | I97: =+(G97/$C$4)*$B$4 -> 1100127.4 | J97: =+((G97/$C$4)*$B$4)/H97 -> 0.73341826 | K97: =(+E97/$C$4*$B$4)/D97 -> 0.871358
A98: 510 | B98: MONTERIA | C98: NELSON ENRIQUE LOPEZ GONZALEZ 510 | D98: =$J$28 -> 72.300938 | E98: =IFERROR(VLOOKUP(A98,'PEDIDOS POR VENDEDOR'!D:E,2,0),0) -> 65 | F98: =IFERROR(VLOOKUP(A98,'VENTAS POR VENDEDOR'!A:B,2,0),0) -> 4510068.8 | G98: =IFERROR(VLOOKUP(A98,'VENTA TERCEROS'!A:B,2,0),0) -> 665600.4 | H98: 1500000 | I98: =+(G98/$C$4)*$B$4 -> 998400.6 | J98: =+((G98/$C$4)*$B$4)/H98 -> 0.6656004 | K98: =(+E98/$C$4*$B$4)/D98 -> 1.3485302
A99: 711 | B99: BARRANQUILLA | C99: JHON WILLIAM JIMENEZ CADENA 711 BARRANQUILLA | D99: =$J$20 -> 72.300937 | E99: =IFERROR(VLOOKUP(A99,'PEDIDOS POR VENDEDOR'!D:E,2,0),0) -> 1 | F99: =IFERROR(VLOOKUP(A99,'VENTAS POR VENDEDOR'!A:B,2,0),0) -> 33475.63 | G99: =IFERROR(VLOOKUP(A99,'VENTA TERCEROS'!A:B,2,0),0) -> 9075.63 | H99: 1500000 | I99: =+(G99/$C$4)*$B$4 -> 13613.445 | J99: =+((G99/$C$4)*$B$4)/H99 -> 0.00907563 | K99: =(+E99/$C$4*$B$4)/D99 -> 0.020746619
A100: 717 | B100: CARTAGENA | C100: YAFER JESUS CORDOBA BERRIO 717 CARTAGENA | D100: =$J$20 -> 72.300937 | E100: =IFERROR(VLOOKUP(A100,'PEDIDOS POR VENDEDOR'!D:E,2,0),0) -> 18 | F100: =IFERROR(VLOOKUP(A100,'VENTAS POR VENDEDOR'!A:B,2,0),0) -> 611363.54 | G100: =IFERROR(VLOOKUP(A100,'VENTA TERCEROS'!A:B,2,0),0) -> 83047.56 | H100: 1500000 | I100: =+(G100/$C$4)*$B$4 -> 124571.34 | J100: =+((G100/$C$4)*$B$4)/H100 -> 0.08304756 | K100: =(+E100/$C$4*$B$4)/D100 -> 0.37343914
A101: 509 | B101: MONTERIA | C101: JOSE GREGORIO OSTEN MERCADO 509 | D101: =$J$28 -> 72.300938 | E101: =IFERROR(VLOOKUP(A101,'PEDIDOS POR VENDEDOR'!D:E,2,0),0) -> 79 | F101: =IFERROR(VLOOKUP(A101,'VENTAS POR VENDEDOR'!A:B,2,0),0) -> 3480136.8 | G101: =IFERROR(VLOOKUP(A101,'VENTA TERCEROS'!A:B,2,0),0) -> 1085075 | H101: 1310257 | I101: =+(G101/$C$4)*$B$4 -> 1627612.5 | J101: =+((G101/$C$4)*$B$4)/H101 -> 1.2422085 | K101: =(+E101/$C$4*$B$4)/D101 -> 1.6389829
A102: 934 | B102: BOGOTA | C102: CARLOS EDUARDO ROMERO 934 | D102: =$J$18 -> 159.82312 | E102: =IFERROR(VLOOKUP(A102,'PEDIDOS POR VENDEDOR'!D:E,2,0),0) -> 55 | F102: =IFERROR(VLOOKUP(A102,'VENTAS POR VENDEDOR'!A:B,2,0),0) -> 2642095.8 | G102: =IFERROR(VLOOKUP(A102,'VENTA TERCEROS'!A:B,2,0),0) -> 557512.81 | H102: 1267181.5 | I102: =+(G102/$C$4)*$B$4 -> 836269.21 | J102: =+((G102/$C$4)*$B$4)/H102 -> 0.65994431 | K102: =(+E102/$C$4*$B$4)/D102 -> 0.51619564
A103: 905 | B103: VILLAVICENCIO | C103: CESAR BERMUDEZ 905 | D103: =$J$23 -> 192.8025 | E103: =IFERROR(VLOOKUP(A103,'PEDIDOS POR VENDEDOR'!D:E,2,0),0) -> 164 | F103: =IFERROR(VLOOKUP(A103,'VENTAS POR VENDEDOR'!A:B,2,0),0) -> 16996708 | G103: =IFERROR(VLOOKUP(A103,'VENTA TERCEROS'!A:B,2,0),0) -> 672839.04 | H103: 1200068.9 | I103: =+(G103/$C$4)*$B$4 -> 1009258.6 | J103: =+((G103/$C$4)*$B$4)/H103 -> 0.84100049 | K103: =(+E103/$C$4*$B$4)/D103 -> 1.2759171
A104: 718 | B104: CARTAGENA | C104: NEIL TORRES 718 CARTAGENA | D104: =$J$26 -> 108.45141 | E104: =IFERROR(VLOOKUP(A104,'PEDIDOS POR VENDEDOR'!D:E,2,0),0) -> 147 | F104: =IFERROR(VLOOKUP(A104,'VENTAS POR VENDEDOR'!A:B,2,0),0) -> 8907281.4 | G104: =IFERROR(VLOOKUP(A104,'VENTA TERCEROS'!A:B,2,0),0) -> 253956.77 | H104: 1120240.6 | I104: =+(G104/$C$4)*$B$4 -> 380935.15 | J104: =+((G104/$C$4)*$B$4)/H104 -> 0.34004763 | K104: =(+E104/$C$4*$B$4)/D104 -> 2.0331687
A105: 705 | B105: VALLEDUPAR | C105: LIZETH FERNANDA OBANDO ARAUJO 705 VALLEDUPAR | D105: =$J$27 -> 180.75234 | E105: =IFERROR(VLOOKUP(A105,'PEDIDOS POR VENDEDOR'!D:E,2,0),0) -> 97 | F105: =IFERROR(VLOOKUP(A105,'VENTAS POR VENDEDOR'!A:B,2,0),0) -> 4308093 | G105: =IFERROR(VLOOKUP(A105,'VENTA TERCEROS'!A:B,2,0),0) -> 439497.2 | H105: 1055252 | I105: =+(G105/$C$4)*$B$4 -> 659245.8 | J105: =+((G105/$C$4)*$B$4)/H105 -> 0.62472831 | K105: =(+E105/$C$4*$B$4)/D105 -> 0.80496882

Sheet MESaMES
B1: ENERO | E1: FEBRERO | H1: MARZO | K1: ABRIL | N1: MAYO | Q1: JUNIO | T1: JULIO | W1: AGOSTO | Z1: SEPTIEMBRE | AC1: OCTUBRE | AF1: NOVIEMBRE | AI1: DICIEMBRE | AL1: ACUMULADO
A2: TUTI | B2: 2024 | C2: 2025 | D2: VAR | E2: 2024 | F2: 2025 | G2: VAR | H2: 2024 | I2: 2025 | J2: VAR | K2: 2024 | L2: 2025 | M2: VAR | N2: 2024 | O2: 2025 | P2: VAR | Q2: 2023 | R2: 2025 | S2: VAR | T2: 2023 | U2: 2025 | V2: VAR | W2: 2023 | X2: 2025 | Y2: VAR | Z2: 2023 | AA2: 2025 | AB2: VAR | AC2: 2023 | AD2: 2025 | AE2: VAR | AF2: 2024 | AG2: 2025 | AH2: VAR | AI2: 2024 | AJ2: 2025 | AK2: VAR | AL2: 2024 | AM2: 2025 | AN2: VAR
A3: Ventas | B3: =+'ENERO-25'!B14 -> 280184625 | C3: =+'ENERO-25'!C7 -> 3.4245274e+08 | D3: =+C3/B3-1 -> 0.22223958 | E3: =+'FEBRERO-25'!B7 -> 364874472 | F3: =+'FEBRERO-25'!D7 -> 4.8996772e+08 | G3: =+F3/E3-1 -> 0.34283914 | H3: =+'MARZO-25'!B7 -> 269027773 | I3: =+'MARZO-25'!D7 -> 4.3701223e+08 | J3: =+I3/H3-1 -> 0.62441306 | K3: =+'ABRIL-25 '!B7 -> 280184624 | L3: =+'ABRIL-25 '!D7 -> 3.8301288e+08 | M3: =+L3/K3-1 -> 0.36700178 | N3: =+'MAYO-25'!B7 -> 402585958 | O3: =+'MAYO-25'!D7 -> 4.4644205e+08 | P3: =+O3/N3-1 -> 0.10893598 | Q3: =+'JUNIO-25'!B7 -> 351424111 | R3: =+'JUNIO-25'!D7 -> 3.6271586e+08 | S3: =+R3/Q3-1 -> 0.032131403 | T3: =+'JULIO-25 '!B7 -> 363499363 | U3: =+'JULIO-25 '!D7 -> 4.3482194e+08 | V3: =+U3/T3-1 -> 0.196211 | W3: =+'AGOSTO-25'!B7 -> 357657385 | X3: =+'AGOSTO-25'!D7 -> 3.4754472e+08 | Y3: =+X3/W3-1 -> -0.028274728 | Z3: =+'SEPTIEMBRE-25'!B7 -> 318164072 | AA3: =+'SEPTIEMBRE-25'!D7 -> 3.1306489e+08 | AB3: =+AA3/Z3-1 -> -0.016026898 | AC3: =+'OCTUBRE-25 '!B7 -> 344061968 | AD3: =+'OCTUBRE-25 '!D7 -> 3.5929574e+08 | AL3: =+B3+E3+H3+K3+N3+Q3+T3+W3+Z3+AC3+AF3+AI3 -> 3331664351 | AM3: =+C3+F3+I3+L3+O3+R3+U3+X3+AA3+AD3+AG3+AJ3 -> 3.9163308e+09 | AN3: =+AM3/AL3-1 -> 0.17548779
A4: Pedidos | B4: =+'ENERO-25'!B15 -> 4701 | C4: =+'ENERO-25'!C8 -> 6359 | D4: =+C4/B4-1 -> 0.35269092 | E4: =+'FEBRERO-25'!B8 -> 6379 | F4: =+'FEBRERO-25'!D8 -> 10009 | G4: =+F4/E4-1 -> 0.56905471 | H4: =+'MARZO-25'!B8 -> 4924 | I4: =+'MARZO-25'!D8 -> 8927 | J4: =+I4/H4-1 -> 0.81295695 | K4: =+'ABRIL-25 '!B8 -> 4701.0054 | L4: =+'ABRIL-25 '!D8 -> 7740 | M4: =+L4/K4-1 -> 0.6464563 | N4: =+'MAYO-25'!B8 -> 7319.7447 | O4: =+'MAYO-25'!D8 -> 8767 | P4: =+O4/N4-1 -> 0.19771937 | Q4: =+'JUNIO-25'!B8 -> 6083 | R4: =+'JUNIO-25'!D8 -> 7690 | S4: =+R4/Q4-1 -> 0.26417886 | T4: =+'JULIO-25 '!B8 -> 6083 | U4: =+'JULIO-25 '!D8 -> 8256 | V4: =+U4/T4-1 -> 0.35722505 | W4: =+'AGOSTO-25'!B8 -> 5958 | X4: =+'AGOSTO-25'!D8 -> 6764 | Y4: =+X4/W4-1 -> 0.1352803 | Z4: =+'SEPTIEMBRE-25'!B8 -> 5106 | AA4: =+'SEPTIEMBRE-25'!D8 -> 6559 | AB4: =+AA4/Z4-1 -> 0.28456718 | AC4: =+'OCTUBRE-25 '!B8 -> 5788 | AD4: =+'OCTUBRE-25 '!D8 -> 6419 | AL4: =+B4+E4+H4+K4+N4+Q4+T4+W4+Z4+AC4+AF4+AI4 -> 57042.75 | AM4: =+C4+F4+I4+L4+O4+R4+U4+X4+AA4+AD4+AG4+AJ4 -> 77490 | AN4: =+AM4/AL4-1 -> 0.35845484
A5: Ticket promedio | B5: =+'ENERO-25'!B16 -> 59601.069 | C5: =+'ENERO-25'!C9 -> 64085.353 | D5: =+C5/B5-1 -> 0.075238318 | E5: =+'FEBRERO-25'!B9 -> 57199.322 | F5: =+'FEBRERO-25'!D9 -> 58253.73 | G5: =+F5/E5-1 -> 0.018433941 | H5: =+H3/H4 -> 54636.022 | I5: =+I3/I4 -> 48953.985 | J5: =+I5/H5-1 -> -0.103998 | K5: =+K3/K4 -> 59601 | L5: =+L3/L4 -> 49484.868 | M5: =+L5/K5-1 -> -0.16973091 | N5: =+N3/N4 -> 55000 | O5: =+O3/O4 -> 50923.013 | P5: =+O5/N5-1 -> -0.07412704 | Q5: =+Q3/Q4 -> 57771.513 | R5: =+R3/R4 -> 47167.212 | S5: =+R5/Q5-1 -> -0.18355587 | T5: =+'JULIO-25 '!B9 -> 59756.594 | U5: =+'JULIO-25 '!D9 -> 52667.386 | V5: =+U5/T5-1 -> -0.11863475 | W5: =+W3/W4 -> 60029.773 | X5: =+X3/X4 -> 51381.538 | Y5: =+X5/W5-1 -> -0.14406576 | Z5: =+Z3/Z4 -> 62311.804 | AA5: =+AA3/AA4 -> 47730.582 | AB5: =+AA5/Z5-1 -> -0.23400417 | AC5: =+AC3/AC4 -> 59444.017 | AD5: =+AD3/AD4 -> 55973.788 | AL5: =+AL3/AL4 -> 58406.447 | AM5: =+AM3/AM4 -> 50539.822 | AN5: =+AM5/AL5-1 -> -0.13468762
A6: Clientes | B6: =+'ENERO-25'!B17 -> 4446 | C6: =+'ENERO-25'!C10 -> 6099 | D6: =+C6/B6-1 -> 0.37179487 | E6: =+'FEBRERO-25'!B10 -> 5790 | F6: =+'FEBRERO-25'!D10 -> 8921 | G6: =+F6/E6-1 -> 0.54075993 | H6: =+'MARZO-25'!B10 -> 4646 | I6: =+'MARZO-25'!D10 -> 7743 | J6: =+I6/H6-1 -> 0.66659492 | M6: =+L6/K6-1 -> #DIV/0! | P6: =+O6/N6-1 -> #DIV/0! | Q6: =+'JUNIO-25'!B10 -> 5486 | R6: =+'JUNIO-25'!D10 -> 6792 | S6: =+R6/Q6-1 -> 0.23806052 | T6: =+'JULIO-25 '!B10 -> 5373 | U6: =+'JULIO-25 '!D10 -> 6927 | V6: =+U6/T6-1 -> 0.2892239 | W6: =+'AGOSTO-25'!B10 -> 5266 | X6: =+'AGOSTO-25'!D10 -> 5651 | Y6: =+X6/W6-1 -> 0.07311052 | Z6: =+'SEPTIEMBRE-25'!B10 -> 5267 | AA6: =+'SEPTIEMBRE-25'!D10 -> 6029 | AB6: =+AA6/Z6-1 -> 0.14467439 | AC6: =+'OCTUBRE-25 '!B10 -> 6000 | AD6: =+'OCTUBRE-25 '!D10 -> 6449 | AL6: =+B6+E6+H6+K6+N6+Q6+T6+W6+Z6+AC6+AF6+AI6 -> 42274 | AM6: =+C6+F6+I6+L6+O6+R6+U6+X6+AA6+AD6+AG6+AJ6 -> 54611 | AN6: =+AM6/AL6-1 -> 0.29183422
A7: Frecuencia de compra promedio | B7: =+'ENERO-25'!B18 -> 1.0573549 | C7: =+'ENERO-25'!C11 -> 1.0426299 | D7: =+C7/B7-1 -> -0.013926248 | E7: =+'FEBRERO-25'!B11 -> 1.1017271 | F7: =+'FEBRERO-25'!D11 -> 1.1219594 | G7: =+F7/E7-1 -> 0.018364172 | J7: =+I7/H7-1 -> #DIV/0! | M7: =+L7/K7-1 -> #DIV/0! | P7: =+O7/N7-1 -> #DIV/0! | S7: =+R7/Q7-1 -> #DIV/0! | T7: =+'JULIO-25 '!B11 -> 1.1321422 | U7: =+'JULIO-25 '!D11 -> 1.1 | V7: =+U7/T7-1 -> -0.028390597 | W7: =+'AGOSTO-25'!B11 -> 1.131409 | X7: =+'AGOSTO-25'!D11 -> 1.13 | Y7: =+X7/W7-1 -> -0.0012453844 | Z7: =+'SEPTIEMBRE-25'!B11 -> 0.96943231 | AA7: =+'SEPTIEMBRE-25'!D11 -> 1.0879084 | AB7: =+AA7/Z7-1 -> 0.12221186 | AC7: =+'OCTUBRE-25 '!B11 -> 0.96466667 | AD7: =+'OCTUBRE-25 '!D11 -> 0.99534812 | AL7: =+AL4/AL6 -> 1.3493578 | AM7: =+AM4/AM6 -> 1.4189449 | AN7: =+AM7/AL7-1 -> 0.051570561
B9: ENERO | F9: FEBRERO | J9: MARZO | N9: ABRIL | R9: MAYO | V9: JUNIO | Z9: JULIO | AD9: AGOSTO | AF9: SEPTIEMBRE | AH9: OCTUBRE | AJ9: ACUMULADO VENTAS
A10: CIUDADES | B10: PEDIDOS 2025 | C10: % | D10: VENTAS 2025 | E10: % | F10: PEDIDOS 2025 | G10: % | H10: VENTAS 2025 | I10: % | J10: PEDIDOS 2025 | K10: % | L10: VENTAS 2025 | M10: % | N10: PEDIDOS 2025 | O10: % | P10: VENTAS 2025 | Q10: % | R10: PEDIDOS 2025 | S10: % | T10: VENTAS 2025 | U10: % | V10: PEDIDOS 2025 | W10: % | X10: VENTAS 2025 | Y10: % | Z10: PEDIDOS 2025 | AA10: % | AB10: VENTAS 2025 | AC10: % | AD10: VENTA 2025 | AE10: % | AF10: VENTA 2025 | AG10: % | AH10: VENTA 2025 | AI10: % | AJ10: 2025 | AK10: % | AL10: 2025 | AM10: % | AN10: ticket promedio | AO10: VENDEDORES | AP10: PEDIDOSXVENDEDOR | AQ10: prom mensual
A11: Bogota | B11: =+'ENERO-25'!J23 -> 2568 | C11: =+B11/$B$23 -> 0.40383708 | D11: =+'ENERO-25'!B41 -> 1.0124008e+08 | E11: =+D11/$D$23 -> 0.29563228 | F11: =+'FEBRERO-25'!J17 -> 4159 | G11: =+F11/$F$23 -> 0.41552603 | H11: =+'FEBRERO-25'!B35 -> 1.6520076e+08 | I11: =+H11/$H$23 -> 0.33293561 | J11: =+'MARZO-25'!J17 -> 3830 | K11: =+J11/$J$23 -> 0.42000219 | L11: =+'MARZO-25'!B32 -> 1.4937978e+08 | M11: =+L11/$L$23 -> 0.3418206 | N11: =+'ABRIL-25 '!J17 -> 3512 | O11: =+N11/$N$23 -> 0.45374677 | P11: =+'ABRIL-25 '!B32 -> 1.4288082e+08 | Q11: =+P11/$P$23 -> 0.37304442 | R11: =+'MAYO-25'!J17 -> 3840 | S11: =+R11/$R$23 -> 0.43800616 | T11: =+'MAYO-25'!B32 -> 1.6387569e+08 | U11: =+T11/$T$23 -> 0.36707046 | V11: =+'JUNIO-25'!J17 -> 3412 | W11: =+V11/$V$23 -> 0.44369311 | X11: =+'JUNIO-25'!F17 -> 1.3623013e+08 | Y11: =+X11/$X$23 -> 0.37558362 | Z11: =+'JULIO-25 '!J17 -> 3505 | AA11: =+Z11/$Z$23 -> 0.42453973 | AB11: =+'JULIO-25 '!F17 -> 1.5587221e+08 | AC11: =+AB11/$AB$23 -> 0.35847366 | AD11: =+'AGOSTO-25'!F17 -> 1.1778168e+08 | AE11: =+AD11/$AD$23 -> 0.33889648 | AF11: =+'SEPTIEMBRE-25'!B32 -> 1.2397704e+08 | AG11: =+AF11/$AF$23 -> 0.3960107 | AH11: =+'OCTUBRE-25 '!G17 -> 1.3163727e+08 | AJ11: =+D11+H11+L11+P11+T11+X11+AB11+AD11+AF11 -> 1.2564382e+09 | AK11: =+AJ11/$AJ$23 -> 0.35260902 | AL11: =+B11+F11+J11+N11+R11+V11 -> 21321 | AM11: =+AL11/$AL$23 -> 0.42913211 | AN11: =+AJ11/AL11 -> 58929.61 | AO11: 19 | AP11: =+AL11/AO11 -> 1122.1579 | AQ11: =+AP11/2 -> 561.07895 | AR11: =+AJ11+AJ13 -> 1.6519053e+09 | AS11: 390739000
